{"records": {"expiryDates": ["31-Jul-2025", "28-Aug-2025", "30-Sep-2025"], "data": [{"strikePrice": 170, "expiryDate": "31-Jul-2025", "CE": {"strikePrice": 170, "expiryDate": "31-Jul-2025", "underlying": "NYKAA", "identifier": "OPTSTKNYKAA31-07-2025CE170.00", "openInterest": 0, "changeinOpenInterest": 0, "pchangeinOpenInterest": 0, "totalTradedVolume": 0, "impliedVolatility": 0, "lastPrice": 0, "change": 0, "pChange": 0, "totalBuyQuantity": 237500, "totalSellQuantity": 225000, "bidQty": 9375, "bidprice": 41.05, "askQty": 12500, "askPrice": 42.9, "underlyingValue": 213}, "PE": {"strikePrice": 170, "expiryDate": "31-Jul-2025", "underlying": "NYKAA", "identifier": "OPTSTKNYKAA31-07-2025PE170.00", "openInterest": 52, "changeinOpenInterest": -3, "pchangeinOpenInterest": -5.454545454545454, "totalTradedVolume": 13, "impliedVolatility": 43, "lastPrice": 0.1, "change": -0.15, "pChange": -60, "totalBuyQuantity": 56250, "totalSellQuantity": 478125, "bidQty": 3125, "bidprice": 0.1, "askQty": 50000, "askPrice": 0.15, "underlyingValue": 213}}, {"strikePrice": 170, "expiryDate": "28-Aug-2025", "CE": {"strikePrice": 170, "expiryDate": "28-Aug-2025", "underlying": "NYKAA", "identifier": "OPTSTKNYKAA28-08-2025CE170.00", "openInterest": 0, "changeinOpenInterest": 0, "pchangeinOpenInterest": 0, "totalTradedVolume": 0, "impliedVolatility": 0, "lastPrice": 0, "change": 0, "pChange": 0, "totalBuyQuantity": 43750, "totalSellQuantity": 43750, "bidQty": 12500, "bidprice": 39.35, "askQty": 31250, "askPrice": 44.5, "underlyingValue": 213}, "PE": {"strikePrice": 170, "expiryDate": "28-Aug-2025", "underlying": "NYKAA", "identifier": "OPTSTKNYKAA28-08-2025PE170.00", "openInterest": 0, "changeinOpenInterest": 0, "pchangeinOpenInterest": 0, "totalTradedVolume": 0, "impliedVolatility": 0, "lastPrice": 0, "change": 0, "pChange": 0, "totalBuyQuantity": 3125, "totalSellQuantity": 43750, "bidQty": 3125, "bidprice": 0.05, "askQty": 12500, "askPrice": 3.7, "underlyingValue": 213}}, {"strikePrice": 175, "expiryDate": "31-Jul-2025", "CE": {"strikePrice": 175, "expiryDate": "31-Jul-2025", "underlying": "NYKAA", "identifier": "OPTSTKNYKAA31-07-2025CE175.00", "openInterest": 1, "changeinOpenInterest": 0, "pchangeinOpenInterest": 0, "totalTradedVolume": 0, "impliedVolatility": 0, "lastPrice": 0, "change": 0, "pChange": 0, "totalBuyQuantity": 240625, "totalSellQuantity": 231250, "bidQty": 9375, "bidprice": 36.25, "askQty": 12500, "askPrice": 38, "underlyingValue": 213}, "PE": {"strikePrice": 175, "expiryDate": "31-Jul-2025", "underlying": "NYKAA", "identifier": "OPTSTKNYKAA31-07-2025PE175.00", "openInterest": 57, "changeinOpenInterest": 4, "pchangeinOpenInterest": 7.547169811320755, "totalTradedVolume": 12, "impliedVolatility": 40.61, "lastPrice": 0.15, "change": -0.1, "pChange": -40, "totalBuyQuantity": 68750, "totalSellQuantity": 465625, "bidQty": 18750, "bidprice": 0.1, "askQty": 12500, "askPrice": 0.15, "underlyingValue": 213}}, {"strikePrice": 175, "expiryDate": "28-Aug-2025", "PE": {"strikePrice": 175, "expiryDate": "28-Aug-2025", "underlying": "NYKAA", "identifier": "OPTSTKNYKAA28-08-2025PE175.00", "openInterest": 0, "changeinOpenInterest": 0, "pchangeinOpenInterest": 0, "totalTradedVolume": 0, "impliedVolatility": 0, "lastPrice": 0, "change": 0, "pChange": 0, "totalBuyQuantity": 6250, "totalSellQuantity": 43750, "bidQty": 6250, "bidprice": 0.05, "askQty": 12500, "askPrice": 3.7, "underlyingValue": 213}, "CE": {"strikePrice": 175, "expiryDate": "28-Aug-2025", "underlying": "NYKAA", "identifier": "OPTSTKNYKAA28-08-2025CE175.00", "openInterest": 0, "changeinOpenInterest": 0, "pchangeinOpenInterest": 0, "totalTradedVolume": 0, "impliedVolatility": 0, "lastPrice": 0, "change": 0, "pChange": 0, "totalBuyQuantity": 43750, "totalSellQuantity": 43750, "bidQty": 12500, "bidprice": 34.4, "askQty": 12500, "askPrice": 39.2, "underlyingValue": 213}}, {"strikePrice": 177.5, "expiryDate": "31-Jul-2025", "CE": {"strikePrice": 177.5, "expiryDate": "31-Jul-2025", "underlying": "NYKAA", "identifier": "OPTSTKNYKAA31-07-2025CE177.50", "openInterest": 1, "changeinOpenInterest": 0, "pchangeinOpenInterest": 0, "totalTradedVolume": 0, "impliedVolatility": 0, "lastPrice": 0, "change": 0, "pChange": 0, "totalBuyQuantity": 231250, "totalSellQuantity": 228125, "bidQty": 12500, "bidprice": 33.85, "askQty": 12500, "askPrice": 35.8, "underlyingValue": 213}, "PE": {"strikePrice": 177.5, "expiryDate": "31-Jul-2025", "underlying": "NYKAA", "identifier": "OPTSTKNYKAA31-07-2025PE177.50", "openInterest": 0, "changeinOpenInterest": 0, "pchangeinOpenInterest": 0, "totalTradedVolume": 0, "impliedVolatility": 0, "lastPrice": 0, "change": 0, "pChange": 0, "totalBuyQuantity": 712500, "totalSellQuantity": 331250, "bidQty": 712500, "bidprice": 0.05, "askQty": 31250, "askPrice": 0.45, "underlyingValue": 213}}, {"strikePrice": 177.5, "expiryDate": "28-Aug-2025", "CE": {"strikePrice": 177.5, "expiryDate": "28-Aug-2025", "underlying": "NYKAA", "identifier": "OPTSTKNYKAA28-08-2025CE177.50", "openInterest": 0, "changeinOpenInterest": 0, "pchangeinOpenInterest": 0, "totalTradedVolume": 0, "impliedVolatility": 0, "lastPrice": 0, "change": 0, "pChange": 0, "totalBuyQuantity": 43750, "totalSellQuantity": 43750, "bidQty": 12500, "bidprice": 31.95, "askQty": 31250, "askPrice": 37.05, "underlyingValue": 213}, "PE": {"strikePrice": 177.5, "expiryDate": "28-Aug-2025", "underlying": "NYKAA", "identifier": "OPTSTKNYKAA28-08-2025PE177.50", "openInterest": 0, "changeinOpenInterest": 0, "pchangeinOpenInterest": 0, "totalTradedVolume": 0, "impliedVolatility": 0, "lastPrice": 0, "change": 0, "pChange": 0, "totalBuyQuantity": 6250, "totalSellQuantity": 43750, "bidQty": 6250, "bidprice": 0.05, "askQty": 12500, "askPrice": 3.7, "underlyingValue": 213}}, {"strikePrice": 180, "expiryDate": "31-Jul-2025", "PE": {"strikePrice": 180, "expiryDate": "31-Jul-2025", "underlying": "NYKAA", "identifier": "OPTSTKNYKAA31-07-2025PE180.00", "openInterest": 162, "changeinOpenInterest": -31, "pchangeinOpenInterest": -16.06217616580311, "totalTradedVolume": 122, "impliedVolatility": 37.43, "lastPrice": 0.2, "change": -0.25, "pChange": -55.55555555555556, "totalBuyQuantity": 453125, "totalSellQuantity": 712500, "bidQty": 78125, "bidprice": 0.15, "askQty": 40625, "askPrice": 0.2, "underlyingValue": 213}, "CE": {"strikePrice": 180, "expiryDate": "31-Jul-2025", "underlying": "NYKAA", "identifier": "OPTSTKNYKAA31-07-2025CE180.00", "openInterest": 17, "changeinOpenInterest": 0, "pchangeinOpenInterest": 0, "totalTradedVolume": 2, "impliedVolatility": 0, "lastPrice": 31.35, "change": 8.850000000000001, "pChange": 39.33333333333334, "totalBuyQuantity": 281250, "totalSellQuantity": 275000, "bidQty": 3125, "bidprice": 32.05, "askQty": 3125, "askPrice": 32.5, "underlyingValue": 213}}, {"strikePrice": 180, "expiryDate": "28-Aug-2025", "CE": {"strikePrice": 180, "expiryDate": "28-Aug-2025", "underlying": "NYKAA", "identifier": "OPTSTKNYKAA28-08-2025CE180.00", "openInterest": 0, "changeinOpenInterest": 0, "pchangeinOpenInterest": 0, "totalTradedVolume": 0, "impliedVolatility": 0, "lastPrice": 0, "change": 0, "pChange": 0, "totalBuyQuantity": 43750, "totalSellQuantity": 43750, "bidQty": 12500, "bidprice": 29.65, "askQty": 31250, "askPrice": 34.65, "underlyingValue": 213}, "PE": {"strikePrice": 180, "expiryDate": "28-Aug-2025", "underlying": "NYKAA", "identifier": "OPTSTKNYKAA28-08-2025PE180.00", "openInterest": 0, "changeinOpenInterest": 0, "pchangeinOpenInterest": 0, "totalTradedVolume": 0, "impliedVolatility": 0, "lastPrice": 0, "change": 0, "pChange": 0, "totalBuyQuantity": 9375, "totalSellQuantity": 43750, "bidQty": 3125, "bidprice": 0.3, "askQty": 12500, "askPrice": 3.7, "underlyingValue": 213}}, {"strikePrice": 182.5, "expiryDate": "31-Jul-2025", "CE": {"strikePrice": 182.5, "expiryDate": "31-Jul-2025", "underlying": "NYKAA", "identifier": "OPTSTKNYKAA31-07-2025CE182.50", "openInterest": 18, "changeinOpenInterest": 0, "pchangeinOpenInterest": 0, "totalTradedVolume": 1, "impliedVolatility": 0, "lastPrice": 23.75, "change": 2.8000000000000007, "pChange": 13.365155131264919, "totalBuyQuantity": 253125, "totalSellQuantity": 234375, "bidQty": 3125, "bidprice": 29.55, "askQty": 3125, "askPrice": 30.4, "underlyingValue": 213}, "PE": {"strikePrice": 182.5, "expiryDate": "31-Jul-2025", "underlying": "NYKAA", "identifier": "OPTSTKNYKAA31-07-2025PE182.50", "openInterest": 26, "changeinOpenInterest": 0, "pchangeinOpenInterest": 0, "totalTradedVolume": 1, "impliedVolatility": 33.28, "lastPrice": 0.15, "change": -0.75, "pChange": -83.33333333333333, "totalBuyQuantity": 325000, "totalSellQuantity": 412500, "bidQty": 3125, "bidprice": 0.2, "askQty": 3125, "askPrice": 0.6, "underlyingValue": 213}}, {"strikePrice": 182.5, "expiryDate": "28-Aug-2025", "PE": {"strikePrice": 182.5, "expiryDate": "28-Aug-2025", "underlying": "NYKAA", "identifier": "OPTSTKNYKAA28-08-2025PE182.50", "openInterest": 0, "changeinOpenInterest": 0, "pchangeinOpenInterest": 0, "totalTradedVolume": 0, "impliedVolatility": 0, "lastPrice": 0, "change": 0, "pChange": 0, "totalBuyQuantity": 15625, "totalSellQuantity": 43750, "bidQty": 3125, "bidprice": 0.25, "askQty": 12500, "askPrice": 3.7, "underlyingValue": 213}, "CE": {"strikePrice": 182.5, "expiryDate": "28-Aug-2025", "underlying": "NYKAA", "identifier": "OPTSTKNYKAA28-08-2025CE182.50", "openInterest": 0, "changeinOpenInterest": 0, "pchangeinOpenInterest": 0, "totalTradedVolume": 0, "impliedVolatility": 0, "lastPrice": 0, "change": 0, "pChange": 0, "totalBuyQuantity": 43750, "totalSellQuantity": 43750, "bidQty": 12500, "bidprice": 27.2, "askQty": 12500, "askPrice": 31.8, "underlyingValue": 213}}, {"strikePrice": 185, "expiryDate": "31-Jul-2025", "CE": {"strikePrice": 185, "expiryDate": "31-Jul-2025", "underlying": "NYKAA", "identifier": "OPTSTKNYKAA31-07-2025CE185.00", "openInterest": 14, "changeinOpenInterest": -2, "pchangeinOpenInterest": -12.5, "totalTradedVolume": 5, "impliedVolatility": 0, "lastPrice": 25.05, "change": 6.350000000000001, "pChange": 33.95721925133691, "totalBuyQuantity": 259375, "totalSellQuantity": 243750, "bidQty": 3125, "bidprice": 27.2, "askQty": 3125, "askPrice": 27.95, "underlyingValue": 213}, "PE": {"strikePrice": 185, "expiryDate": "31-Jul-2025", "underlying": "NYKAA", "identifier": "OPTSTKNYKAA31-07-2025PE185.00", "openInterest": 113, "changeinOpenInterest": -84, "pchangeinOpenInterest": -42.63959390862944, "totalTradedVolume": 189, "impliedVolatility": 34.91, "lastPrice": 0.3, "change": -0.6000000000000001, "pChange": -66.66666666666667, "totalBuyQuantity": 696875, "totalSellQuantity": 684375, "bidQty": 21875, "bidprice": 0.3, "askQty": 21875, "askPrice": 0.35, "underlyingValue": 213}}, {"strikePrice": 185, "expiryDate": "28-Aug-2025", "CE": {"strikePrice": 185, "expiryDate": "28-Aug-2025", "underlying": "NYKAA", "identifier": "OPTSTKNYKAA28-08-2025CE185.00", "openInterest": 0, "changeinOpenInterest": 0, "pchangeinOpenInterest": 0, "totalTradedVolume": 0, "impliedVolatility": 0, "lastPrice": 0, "change": 0, "pChange": 0, "totalBuyQuantity": 43750, "totalSellQuantity": 43750, "bidQty": 12500, "bidprice": 24.7, "askQty": 31250, "askPrice": 30.25, "underlyingValue": 213}, "PE": {"strikePrice": 185, "expiryDate": "28-Aug-2025", "underlying": "NYKAA", "identifier": "OPTSTKNYKAA28-08-2025PE185.00", "openInterest": 0, "changeinOpenInterest": 0, "pchangeinOpenInterest": 0, "totalTradedVolume": 0, "impliedVolatility": 0, "lastPrice": 0, "change": 0, "pChange": 0, "totalBuyQuantity": 12500, "totalSellQuantity": 43750, "bidQty": 3125, "bidprice": 0.25, "askQty": 12500, "askPrice": 4, "underlyingValue": 213}}, {"strikePrice": 187.5, "expiryDate": "31-Jul-2025", "CE": {"strikePrice": 187.5, "expiryDate": "31-Jul-2025", "underlying": "NYKAA", "identifier": "OPTSTKNYKAA31-07-2025CE187.50", "openInterest": 13, "changeinOpenInterest": -1, "pchangeinOpenInterest": -7.142857142857143, "totalTradedVolume": 8, "impliedVolatility": 0, "lastPrice": 22.7, "change": 6.349999999999998, "pChange": 38.83792048929662, "totalBuyQuantity": 256250, "totalSellQuantity": 253125, "bidQty": 3125, "bidprice": 24.9, "askQty": 3125, "askPrice": 25.4, "underlyingValue": 213}, "PE": {"strikePrice": 187.5, "expiryDate": "31-Jul-2025", "underlying": "NYKAA", "identifier": "OPTSTKNYKAA31-07-2025PE187.50", "openInterest": 51, "changeinOpenInterest": -8, "pchangeinOpenInterest": -13.559322033898304, "totalTradedVolume": 55, "impliedVolatility": 34.23, "lastPrice": 0.4, "change": -0.7999999999999999, "pChange": -66.66666666666666, "totalBuyQuantity": 456250, "totalSellQuantity": 590625, "bidQty": 3125, "bidprice": 0.4, "askQty": 9375, "askPrice": 0.45, "underlyingValue": 213}}, {"strikePrice": 187.5, "expiryDate": "28-Aug-2025", "CE": {"strikePrice": 187.5, "expiryDate": "28-Aug-2025", "underlying": "NYKAA", "identifier": "OPTSTKNYKAA28-08-2025CE187.50", "openInterest": 0, "changeinOpenInterest": 0, "pchangeinOpenInterest": 0, "totalTradedVolume": 0, "impliedVolatility": 0, "lastPrice": 0, "change": 0, "pChange": 0, "totalBuyQuantity": 43750, "totalSellQuantity": 43750, "bidQty": 12500, "bidprice": 22.35, "askQty": 31250, "askPrice": 27.15, "underlyingValue": 213}, "PE": {"strikePrice": 187.5, "expiryDate": "28-Aug-2025", "underlying": "NYKAA", "identifier": "OPTSTKNYKAA28-08-2025PE187.50", "openInterest": 0, "changeinOpenInterest": 0, "pchangeinOpenInterest": 0, "totalTradedVolume": 0, "impliedVolatility": 0, "lastPrice": 0, "change": 0, "pChange": 0, "totalBuyQuantity": 15625, "totalSellQuantity": 43750, "bidQty": 3125, "bidprice": 0.35, "askQty": 12500, "askPrice": 3.7, "underlyingValue": 213}}, {"strikePrice": 190, "expiryDate": "31-Jul-2025", "PE": {"strikePrice": 190, "expiryDate": "31-Jul-2025", "underlying": "NYKAA", "identifier": "OPTSTKNYKAA31-07-2025PE190.00", "openInterest": 590, "changeinOpenInterest": -2, "pchangeinOpenInterest": -0.33783783783783783, "totalTradedVolume": 704, "impliedVolatility": 33.84, "lastPrice": 0.55, "change": -1.0999999999999999, "pChange": -66.66666666666666, "totalBuyQuantity": 1078125, "totalSellQuantity": 1187500, "bidQty": 21875, "bidprice": 0.55, "askQty": 62500, "askPrice": 0.6, "underlyingValue": 213}, "CE": {"strikePrice": 190, "expiryDate": "31-Jul-2025", "underlying": "NYKAA", "identifier": "OPTSTKNYKAA31-07-2025CE190.00", "openInterest": 64, "changeinOpenInterest": -1, "pchangeinOpenInterest": -1.5384615384615385, "totalTradedVolume": 27, "impliedVolatility": 0, "lastPrice": 22.3, "change": 7.800000000000001, "pChange": 53.79310344827587, "totalBuyQuantity": 328125, "totalSellQuantity": 337500, "bidQty": 3125, "bidprice": 22.55, "askQty": 3125, "askPrice": 22.8, "underlyingValue": 213}}, {"strikePrice": 190, "expiryDate": "28-Aug-2025", "CE": {"strikePrice": 190, "expiryDate": "28-Aug-2025", "underlying": "NYKAA", "identifier": "OPTSTKNYKAA28-08-2025CE190.00", "openInterest": 0, "changeinOpenInterest": 0, "pchangeinOpenInterest": 0, "totalTradedVolume": 0, "impliedVolatility": 0, "lastPrice": 0, "change": 0, "pChange": 0, "totalBuyQuantity": 43750, "totalSellQuantity": 43750, "bidQty": 12500, "bidprice": 21.6, "askQty": 31250, "askPrice": 24.1, "underlyingValue": 213}, "PE": {"strikePrice": 190, "expiryDate": "28-Aug-2025", "underlying": "NYKAA", "identifier": "OPTSTKNYKAA28-08-2025PE190.00", "openInterest": 9, "changeinOpenInterest": 0, "pchangeinOpenInterest": 0, "totalTradedVolume": 5, "impliedVolatility": 35.24, "lastPrice": 2.25, "change": -2.0999999999999996, "pChange": -48.275862068965516, "totalBuyQuantity": 56250, "totalSellQuantity": 71875, "bidQty": 3125, "bidprice": 2.1, "askQty": 6250, "askPrice": 2.95, "underlyingValue": 213}}, {"strikePrice": 190, "expiryDate": "30-Sep-2025", "PE": {"strikePrice": 190, "expiryDate": "30-Sep-2025", "underlying": "NYKAA", "identifier": "OPTSTKNYKAA30-09-2025PE190.00", "openInterest": 4, "changeinOpenInterest": 0, "pchangeinOpenInterest": 0, "totalTradedVolume": 1, "impliedVolatility": 36.32, "lastPrice": 4.2, "change": -4.3, "pChange": -50.588235294117645, "totalBuyQuantity": 9375, "totalSellQuantity": 6250, "bidQty": 3125, "bidprice": 3.55, "askQty": 6250, "askPrice": 7, "underlyingValue": 213}}, {"strikePrice": 192.5, "expiryDate": "31-Jul-2025", "CE": {"strikePrice": 192.5, "expiryDate": "31-Jul-2025", "underlying": "NYKAA", "identifier": "OPTSTKNYKAA31-07-2025CE192.50", "openInterest": 15, "changeinOpenInterest": -3, "pchangeinOpenInterest": -16.666666666666668, "totalTradedVolume": 14, "impliedVolatility": 0, "lastPrice": 19.55, "change": 7.5, "pChange": 62.24066390041494, "totalBuyQuantity": 296875, "totalSellQuantity": 387500, "bidQty": 3125, "bidprice": 20.25, "askQty": 3125, "askPrice": 20.45, "underlyingValue": 213}, "PE": {"strikePrice": 192.5, "expiryDate": "31-Jul-2025", "underlying": "NYKAA", "identifier": "OPTSTKNYKAA31-07-2025PE192.50", "openInterest": 67, "changeinOpenInterest": -16, "pchangeinOpenInterest": -19.27710843373494, "totalTradedVolume": 80, "impliedVolatility": 33.48, "lastPrice": 0.75, "change": -1.4, "pChange": -65.11627906976743, "totalBuyQuantity": 412500, "totalSellQuantity": 621875, "bidQty": 6250, "bidprice": 0.7, "askQty": 3125, "askPrice": 0.75, "underlyingValue": 213}}, {"strikePrice": 192.5, "expiryDate": "28-Aug-2025", "CE": {"strikePrice": 192.5, "expiryDate": "28-Aug-2025", "underlying": "NYKAA", "identifier": "OPTSTKNYKAA28-08-2025CE192.50", "openInterest": 0, "changeinOpenInterest": 0, "pchangeinOpenInterest": 0, "totalTradedVolume": 0, "impliedVolatility": 0, "lastPrice": 0, "change": 0, "pChange": 0, "totalBuyQuantity": 43750, "totalSellQuantity": 43750, "bidQty": 12500, "bidprice": 18.4, "askQty": 12500, "askPrice": 25.25, "underlyingValue": 213}, "PE": {"strikePrice": 192.5, "expiryDate": "28-Aug-2025", "underlying": "NYKAA", "identifier": "OPTSTKNYKAA28-08-2025PE192.50", "openInterest": 0, "changeinOpenInterest": 0, "pchangeinOpenInterest": 0, "totalTradedVolume": 0, "impliedVolatility": 0, "lastPrice": 0, "change": 0, "pChange": 0, "totalBuyQuantity": 43750, "totalSellQuantity": 43750, "bidQty": 12500, "bidprice": 1.35, "askQty": 12500, "askPrice": 7.2, "underlyingValue": 213}}, {"strikePrice": 195, "expiryDate": "31-Jul-2025", "PE": {"strikePrice": 195, "expiryDate": "31-Jul-2025", "underlying": "NYKAA", "identifier": "OPTSTKNYKAA31-07-2025PE195.00", "openInterest": 252, "changeinOpenInterest": -30, "pchangeinOpenInterest": -10.638297872340425, "totalTradedVolume": 518, "impliedVolatility": 33.54, "lastPrice": 1.05, "change": -1.5999999999999999, "pChange": -60.37735849056604, "totalBuyQuantity": 906250, "totalSellQuantity": 1121875, "bidQty": 109375, "bidprice": 1, "askQty": 53125, "askPrice": 1.05, "underlyingValue": 213}, "CE": {"strikePrice": 195, "expiryDate": "31-Jul-2025", "underlying": "NYKAA", "identifier": "OPTSTKNYKAA31-07-2025CE195.00", "openInterest": 97, "changeinOpenInterest": -1, "pchangeinOpenInterest": -1.0204081632653061, "totalTradedVolume": 42, "impliedVolatility": 0, "lastPrice": 18.05, "change": 7.450000000000001, "pChange": 70.28301886792454, "totalBuyQuantity": 406250, "totalSellQuantity": 396875, "bidQty": 3125, "bidprice": 18, "askQty": 3125, "askPrice": 18.25, "underlyingValue": 213}}, {"strikePrice": 195, "expiryDate": "28-Aug-2025", "CE": {"strikePrice": 195, "expiryDate": "28-Aug-2025", "underlying": "NYKAA", "identifier": "OPTSTKNYKAA28-08-2025CE195.00", "openInterest": 0, "changeinOpenInterest": 0, "pchangeinOpenInterest": 0, "totalTradedVolume": 0, "impliedVolatility": 0, "lastPrice": 0, "change": 0, "pChange": 0, "totalBuyQuantity": 43750, "totalSellQuantity": 50000, "bidQty": 12500, "bidprice": 15.9, "askQty": 3125, "askPrice": 24.25, "underlyingValue": 213}, "PE": {"strikePrice": 195, "expiryDate": "28-Aug-2025", "underlying": "NYKAA", "identifier": "OPTSTKNYKAA28-08-2025PE195.00", "openInterest": 0, "changeinOpenInterest": 0, "pchangeinOpenInterest": 0, "totalTradedVolume": 0, "impliedVolatility": 0, "lastPrice": 0, "change": 0, "pChange": 0, "totalBuyQuantity": 43750, "totalSellQuantity": 46875, "bidQty": 12500, "bidprice": 1.35, "askQty": 3125, "askPrice": 7.15, "underlyingValue": 213}}, {"strikePrice": 197.5, "expiryDate": "31-Jul-2025", "PE": {"strikePrice": 197.5, "expiryDate": "31-Jul-2025", "underlying": "NYKAA", "identifier": "OPTSTKNYKAA31-07-2025PE197.50", "openInterest": 88, "changeinOpenInterest": -1, "pchangeinOpenInterest": -1.1235955056179776, "totalTradedVolume": 112, "impliedVolatility": 33.29, "lastPrice": 1.35, "change": -2.25, "pChange": -62.5, "totalBuyQuantity": 681250, "totalSellQuantity": 856250, "bidQty": 15625, "bidprice": 1.3, "askQty": 18750, "askPrice": 1.4, "underlyingValue": 213}, "CE": {"strikePrice": 197.5, "expiryDate": "31-Jul-2025", "underlying": "NYKAA", "identifier": "OPTSTKNYKAA31-07-2025CE197.50", "openInterest": 52, "changeinOpenInterest": -2, "pchangeinOpenInterest": -3.7037037037037037, "totalTradedVolume": 35, "impliedVolatility": 0, "lastPrice": 15.85, "change": 6.85, "pChange": 76.11111111111111, "totalBuyQuantity": 378125, "totalSellQuantity": 371875, "bidQty": 3125, "bidprice": 15.9, "askQty": 3125, "askPrice": 16.1, "underlyingValue": 213}}, {"strikePrice": 197.5, "expiryDate": "28-Aug-2025", "CE": {"strikePrice": 197.5, "expiryDate": "28-Aug-2025", "underlying": "NYKAA", "identifier": "OPTSTKNYKAA28-08-2025CE197.50", "openInterest": 0, "changeinOpenInterest": 0, "pchangeinOpenInterest": 0, "totalTradedVolume": 0, "impliedVolatility": 0, "lastPrice": 0, "change": 0, "pChange": 0, "totalBuyQuantity": 43750, "totalSellQuantity": 46875, "bidQty": 12500, "bidprice": 13.45, "askQty": 3125, "askPrice": 22.3, "underlyingValue": 213}, "PE": {"strikePrice": 197.5, "expiryDate": "28-Aug-2025", "underlying": "NYKAA", "identifier": "OPTSTKNYKAA28-08-2025PE197.50", "openInterest": 0, "changeinOpenInterest": 0, "pchangeinOpenInterest": 0, "totalTradedVolume": 0, "impliedVolatility": 0, "lastPrice": 0, "change": 0, "pChange": 0, "totalBuyQuantity": 43750, "totalSellQuantity": 46875, "bidQty": 12500, "bidprice": 1.35, "askQty": 12500, "askPrice": 7.2, "underlyingValue": 213}}, {"strikePrice": 200, "expiryDate": "31-Jul-2025", "PE": {"strikePrice": 200, "expiryDate": "31-Jul-2025", "underlying": "NYKAA", "identifier": "OPTSTKNYKAA31-07-2025PE200.00", "openInterest": 799, "changeinOpenInterest": 134, "pchangeinOpenInterest": 20.150375939849624, "totalTradedVolume": 1178, "impliedVolatility": 33.14, "lastPrice": 1.8, "change": -2.75, "pChange": -60.439560439560445, "totalBuyQuantity": 1043750, "totalSellQuantity": 1462500, "bidQty": 71875, "bidprice": 1.75, "askQty": 65625, "askPrice": 1.85, "underlyingValue": 213}, "CE": {"strikePrice": 200, "expiryDate": "31-Jul-2025", "underlying": "NYKAA", "identifier": "OPTSTKNYKAA31-07-2025CE200.00", "openInterest": 564, "changeinOpenInterest": -121, "pchangeinOpenInterest": -17.664233576642335, "totalTradedVolume": 809, "impliedVolatility": 0, "lastPrice": 13.85, "change": 6.3, "pChange": 83.44370860927152, "totalBuyQuantity": 528125, "totalSellQuantity": 590625, "bidQty": 3125, "bidprice": 13.85, "askQty": 3125, "askPrice": 14.05, "underlyingValue": 213}}, {"strikePrice": 200, "expiryDate": "28-Aug-2025", "PE": {"strikePrice": 200, "expiryDate": "28-Aug-2025", "underlying": "NYKAA", "identifier": "OPTSTKNYKAA28-08-2025PE200.00", "openInterest": 0, "changeinOpenInterest": 0, "pchangeinOpenInterest": 0, "totalTradedVolume": 0, "impliedVolatility": 0, "lastPrice": 0, "change": 0, "pChange": 0, "totalBuyQuantity": 46875, "totalSellQuantity": 46875, "bidQty": 3125, "bidprice": 4.45, "askQty": 3125, "askPrice": 6.45, "underlyingValue": 213}, "CE": {"strikePrice": 200, "expiryDate": "28-Aug-2025", "underlying": "NYKAA", "identifier": "OPTSTKNYKAA28-08-2025CE200.00", "openInterest": 0, "changeinOpenInterest": 0, "pchangeinOpenInterest": 0, "totalTradedVolume": 0, "impliedVolatility": 0, "lastPrice": 0, "change": 0, "pChange": 0, "totalBuyQuantity": 43750, "totalSellQuantity": 46875, "bidQty": 12500, "bidprice": 14.05, "askQty": 3125, "askPrice": 17.15, "underlyingValue": 213}}, {"strikePrice": 200, "expiryDate": "30-Sep-2025", "CE": {"strikePrice": 200, "expiryDate": "30-Sep-2025", "underlying": "NYKAA", "identifier": "OPTSTKNYKAA30-09-2025CE200.00", "openInterest": 0, "changeinOpenInterest": 0, "pchangeinOpenInterest": 0, "totalTradedVolume": 0, "impliedVolatility": 0, "lastPrice": 0, "change": 0, "pChange": 0, "totalBuyQuantity": 3125, "totalSellQuantity": 0, "bidQty": 3125, "bidprice": 0.1, "askQty": 0, "askPrice": 0, "underlyingValue": 213}}, {"strikePrice": 202.5, "expiryDate": "31-Jul-2025", "CE": {"strikePrice": 202.5, "expiryDate": "31-Jul-2025", "underlying": "NYKAA", "identifier": "OPTSTKNYKAA31-07-2025CE202.50", "openInterest": 102, "changeinOpenInterest": -51, "pchangeinOpenInterest": -33.333333333333336, "totalTradedVolume": 300, "impliedVolatility": 13.03, "lastPrice": 11.95, "change": 5.699999999999999, "pChange": 91.19999999999999, "totalBuyQuantity": 475000, "totalSellQuantity": 459375, "bidQty": 3125, "bidprice": 12, "askQty": 6250, "askPrice": 12.15, "underlyingValue": 213}, "PE": {"strikePrice": 202.5, "expiryDate": "31-Jul-2025", "underlying": "NYKAA", "identifier": "OPTSTKNYKAA31-07-2025PE202.50", "openInterest": 54, "changeinOpenInterest": -10, "pchangeinOpenInterest": -15.625, "totalTradedVolume": 154, "impliedVolatility": 32.64, "lastPrice": 2.35, "change": -3.4499999999999997, "pChange": -59.48275862068966, "totalBuyQuantity": 800000, "totalSellQuantity": 975000, "bidQty": 9375, "bidprice": 2.35, "askQty": 9375, "askPrice": 2.45, "underlyingValue": 213}}, {"strikePrice": 202.5, "expiryDate": "28-Aug-2025", "PE": {"strikePrice": 202.5, "expiryDate": "28-Aug-2025", "underlying": "NYKAA", "identifier": "OPTSTKNYKAA28-08-2025PE202.50", "openInterest": 0, "changeinOpenInterest": 0, "pchangeinOpenInterest": 0, "totalTradedVolume": 0, "impliedVolatility": 0, "lastPrice": 0, "change": 0, "pChange": 0, "totalBuyQuantity": 43750, "totalSellQuantity": 46875, "bidQty": 12500, "bidprice": 3.7, "askQty": 3125, "askPrice": 9.65, "underlyingValue": 213}, "CE": {"strikePrice": 202.5, "expiryDate": "28-Aug-2025", "underlying": "NYKAA", "identifier": "OPTSTKNYKAA28-08-2025CE202.50", "openInterest": 0, "changeinOpenInterest": 0, "pchangeinOpenInterest": 0, "totalTradedVolume": 0, "impliedVolatility": 0, "lastPrice": 0, "change": 0, "pChange": 0, "totalBuyQuantity": 43750, "totalSellQuantity": 43750, "bidQty": 31250, "bidprice": 11, "askQty": 12500, "askPrice": 17.95, "underlyingValue": 213}}, {"strikePrice": 205, "expiryDate": "31-Jul-2025", "PE": {"strikePrice": 205, "expiryDate": "31-Jul-2025", "underlying": "NYKAA", "identifier": "OPTSTKNYKAA31-07-2025PE205.00", "openInterest": 412, "changeinOpenInterest": 203, "pchangeinOpenInterest": 97.12918660287082, "totalTradedVolume": 892, "impliedVolatility": 33.82, "lastPrice": 3.1, "change": -4.050000000000001, "pChange": -56.64335664335665, "totalBuyQuantity": 1078125, "totalSellQuantity": 1171875, "bidQty": 9375, "bidprice": 3.1, "askQty": 15625, "askPrice": 3.15, "underlyingValue": 213}, "CE": {"strikePrice": 205, "expiryDate": "31-Jul-2025", "underlying": "NYKAA", "identifier": "OPTSTKNYKAA31-07-2025CE205.00", "openInterest": 607, "changeinOpenInterest": -196, "pchangeinOpenInterest": -24.408468244084684, "totalTradedVolume": 1475, "impliedVolatility": 18.57, "lastPrice": 10.25, "change": 5.15, "pChange": 100.98039215686276, "totalBuyQuantity": 687500, "totalSellQuantity": 528125, "bidQty": 6250, "bidprice": 10.25, "askQty": 12500, "askPrice": 10.4, "underlyingValue": 213}}, {"strikePrice": 205, "expiryDate": "28-Aug-2025", "CE": {"strikePrice": 205, "expiryDate": "28-Aug-2025", "underlying": "NYKAA", "identifier": "OPTSTKNYKAA28-08-2025CE205.00", "openInterest": 10, "changeinOpenInterest": -1, "pchangeinOpenInterest": -9.090909090909092, "totalTradedVolume": 13, "impliedVolatility": 15.72, "lastPrice": 12, "change": 3.5, "pChange": 41.17647058823529, "totalBuyQuantity": 100000, "totalSellQuantity": 106250, "bidQty": 3125, "bidprice": 11.75, "askQty": 6250, "askPrice": 12.5, "underlyingValue": 213}, "PE": {"strikePrice": 205, "expiryDate": "28-Aug-2025", "underlying": "NYKAA", "identifier": "OPTSTKNYKAA28-08-2025PE205.00", "openInterest": 0, "changeinOpenInterest": 0, "pchangeinOpenInterest": 0, "totalTradedVolume": 0, "impliedVolatility": 0, "lastPrice": 0, "change": 0, "pChange": 0, "totalBuyQuantity": 43750, "totalSellQuantity": 43750, "bidQty": 31250, "bidprice": 5.55, "askQty": 12500, "askPrice": 7.85, "underlyingValue": 213}}, {"strikePrice": 205, "expiryDate": "30-Sep-2025", "CE": {"strikePrice": 205, "expiryDate": "30-Sep-2025", "underlying": "NYKAA", "identifier": "OPTSTKNYKAA30-09-2025CE205.00", "openInterest": 0, "changeinOpenInterest": 0, "pchangeinOpenInterest": 0, "totalTradedVolume": 0, "impliedVolatility": 0, "lastPrice": 0, "change": 0, "pChange": 0, "totalBuyQuantity": 3125, "totalSellQuantity": 0, "bidQty": 3125, "bidprice": 0.05, "askQty": 0, "askPrice": 0, "underlyingValue": 213}}, {"strikePrice": 207.5, "expiryDate": "31-Jul-2025", "CE": {"strikePrice": 207.5, "expiryDate": "31-Jul-2025", "underlying": "NYKAA", "identifier": "OPTSTKNYKAA31-07-2025CE207.50", "openInterest": 81, "changeinOpenInterest": -12, "pchangeinOpenInterest": -12.903225806451612, "totalTradedVolume": 782, "impliedVolatility": 21.1, "lastPrice": 8.7, "change": 4.6, "pChange": 112.19512195121952, "totalBuyQuantity": 528125, "totalSellQuantity": 487500, "bidQty": 3125, "bidprice": 8.7, "askQty": 3125, "askPrice": 8.8, "underlyingValue": 213}, "PE": {"strikePrice": 207.5, "expiryDate": "31-Jul-2025", "underlying": "NYKAA", "identifier": "OPTSTKNYKAA31-07-2025PE207.50", "openInterest": 84, "changeinOpenInterest": 37, "pchangeinOpenInterest": 78.72340425531915, "totalTradedVolume": 241, "impliedVolatility": 34.14, "lastPrice": 4.1, "change": -4.550000000000001, "pChange": -52.601156069364166, "totalBuyQuantity": 706250, "totalSellQuantity": 796875, "bidQty": 9375, "bidprice": 4, "askQty": 9375, "askPrice": 4.1, "underlyingValue": 213}}, {"strikePrice": 207.5, "expiryDate": "28-Aug-2025", "CE": {"strikePrice": 207.5, "expiryDate": "28-Aug-2025", "underlying": "NYKAA", "identifier": "OPTSTKNYKAA28-08-2025CE207.50", "openInterest": 0, "changeinOpenInterest": 0, "pchangeinOpenInterest": 0, "totalTradedVolume": 0, "impliedVolatility": 0, "lastPrice": 0, "change": 0, "pChange": 0, "totalBuyQuantity": 43750, "totalSellQuantity": 46875, "bidQty": 12500, "bidprice": 8.85, "askQty": 12500, "askPrice": 12.35, "underlyingValue": 213}, "PE": {"strikePrice": 207.5, "expiryDate": "28-Aug-2025", "underlying": "NYKAA", "identifier": "OPTSTKNYKAA28-08-2025PE207.50", "openInterest": 0, "changeinOpenInterest": 0, "pchangeinOpenInterest": 0, "totalTradedVolume": 0, "impliedVolatility": 0, "lastPrice": 0, "change": 0, "pChange": 0, "totalBuyQuantity": 43750, "totalSellQuantity": 46875, "bidQty": 12500, "bidprice": 4.95, "askQty": 3125, "askPrice": 10.1, "underlyingValue": 213}}, {"strikePrice": 210, "expiryDate": "31-Jul-2025", "CE": {"strikePrice": 210, "expiryDate": "31-Jul-2025", "underlying": "NYKAA", "identifier": "OPTSTKNYKAA31-07-2025CE210.00", "openInterest": 968, "changeinOpenInterest": -259, "pchangeinOpenInterest": -21.10839445802771, "totalTradedVolume": 5456, "impliedVolatility": 22.9, "lastPrice": 7.3, "change": 4, "pChange": 121.21212121212122, "totalBuyQuantity": 1171875, "totalSellQuantity": 1006250, "bidQty": 6250, "bidprice": 7.3, "askQty": 6250, "askPrice": 7.4, "underlyingValue": 213}, "PE": {"strikePrice": 210, "expiryDate": "31-Jul-2025", "underlying": "NYKAA", "identifier": "OPTSTKNYKAA31-07-2025PE210.00", "openInterest": 417, "changeinOpenInterest": 129, "pchangeinOpenInterest": 44.791666666666664, "totalTradedVolume": 1172, "impliedVolatility": 34.74, "lastPrice": 5.25, "change": -5, "pChange": -48.78048780487805, "totalBuyQuantity": 1012500, "totalSellQuantity": 940625, "bidQty": 15625, "bidprice": 5.1, "askQty": 12500, "askPrice": 5.2, "underlyingValue": 213}}, {"strikePrice": 210, "expiryDate": "28-Aug-2025", "CE": {"strikePrice": 210, "expiryDate": "28-Aug-2025", "underlying": "NYKAA", "identifier": "OPTSTKNYKAA28-08-2025CE210.00", "openInterest": 17, "changeinOpenInterest": 9, "pchangeinOpenInterest": 112.5, "totalTradedVolume": 18, "impliedVolatility": 19.12, "lastPrice": 9.9, "change": 3.6500000000000004, "pChange": 58.400000000000006, "totalBuyQuantity": 156250, "totalSellQuantity": 59375, "bidQty": 6250, "bidprice": 9.9, "askQty": 3125, "askPrice": 10.2, "underlyingValue": 213}, "PE": {"strikePrice": 210, "expiryDate": "28-Aug-2025", "underlying": "NYKAA", "identifier": "OPTSTKNYKAA28-08-2025PE210.00", "openInterest": 0, "changeinOpenInterest": 0, "pchangeinOpenInterest": 0, "totalTradedVolume": 0, "impliedVolatility": 0, "lastPrice": 0, "change": 0, "pChange": 0, "totalBuyQuantity": 46875, "totalSellQuantity": 46875, "bidQty": 3125, "bidprice": 8.1, "askQty": 3125, "askPrice": 10.2, "underlyingValue": 213}}, {"strikePrice": 210, "expiryDate": "30-Sep-2025", "CE": {"strikePrice": 210, "expiryDate": "30-Sep-2025", "underlying": "NYKAA", "identifier": "OPTSTKNYKAA30-09-2025CE210.00", "openInterest": 0, "changeinOpenInterest": 0, "pchangeinOpenInterest": 0, "totalTradedVolume": 0, "impliedVolatility": 0, "lastPrice": 0, "change": 0, "pChange": 0, "totalBuyQuantity": 3125, "totalSellQuantity": 0, "bidQty": 3125, "bidprice": 0.05, "askQty": 0, "askPrice": 0, "underlyingValue": 213}}, {"strikePrice": 212.5, "expiryDate": "31-Jul-2025", "PE": {"strikePrice": 212.5, "expiryDate": "31-Jul-2025", "underlying": "NYKAA", "identifier": "OPTSTKNYKAA31-07-2025PE212.50", "openInterest": 44, "changeinOpenInterest": 29, "pchangeinOpenInterest": 193.33333333333334, "totalTradedVolume": 143, "impliedVolatility": 35.85, "lastPrice": 6.4, "change": -5.699999999999999, "pChange": -47.10743801652892, "totalBuyQuantity": 553125, "totalSellQuantity": 559375, "bidQty": 3125, "bidprice": 6.4, "askQty": 3125, "askPrice": 6.5, "underlyingValue": 213}, "CE": {"strikePrice": 212.5, "expiryDate": "31-Jul-2025", "underlying": "NYKAA", "identifier": "OPTSTKNYKAA31-07-2025CE212.50", "openInterest": 142, "changeinOpenInterest": 23, "pchangeinOpenInterest": 19.327731092436974, "totalTradedVolume": 1030, "impliedVolatility": 24.18, "lastPrice": 6.1, "change": 3.4999999999999996, "pChange": 134.6153846153846, "totalBuyQuantity": 878125, "totalSellQuantity": 731250, "bidQty": 3125, "bidprice": 6.1, "askQty": 12500, "askPrice": 6.2, "underlyingValue": 213}}, {"strikePrice": 212.5, "expiryDate": "28-Aug-2025", "CE": {"strikePrice": 212.5, "expiryDate": "28-Aug-2025", "underlying": "NYKAA", "identifier": "OPTSTKNYKAA28-08-2025CE212.50", "openInterest": 0, "changeinOpenInterest": 0, "pchangeinOpenInterest": 0, "totalTradedVolume": 0, "impliedVolatility": 0, "lastPrice": 0, "change": 0, "pChange": 0, "totalBuyQuantity": 46875, "totalSellQuantity": 34375, "bidQty": 31250, "bidprice": 4.8, "askQty": 31250, "askPrice": 11.05, "underlyingValue": 213}, "PE": {"strikePrice": 212.5, "expiryDate": "28-Aug-2025", "underlying": "NYKAA", "identifier": "OPTSTKNYKAA28-08-2025PE212.50", "openInterest": 0, "changeinOpenInterest": 0, "pchangeinOpenInterest": 0, "totalTradedVolume": 0, "impliedVolatility": 0, "lastPrice": 0, "change": 0, "pChange": 0, "totalBuyQuantity": 43750, "totalSellQuantity": 43750, "bidQty": 12500, "bidprice": 7.35, "askQty": 12500, "askPrice": 13.5, "underlyingValue": 213}}, {"strikePrice": 215, "expiryDate": "31-Jul-2025", "CE": {"strikePrice": 215, "expiryDate": "31-Jul-2025", "underlying": "NYKAA", "identifier": "OPTSTKNYKAA31-07-2025CE215.00", "openInterest": 411, "changeinOpenInterest": 65, "pchangeinOpenInterest": 18.786127167630056, "totalTradedVolume": 2116, "impliedVolatility": 25.64, "lastPrice": 5.15, "change": 3.0500000000000003, "pChange": 145.23809523809524, "totalBuyQuantity": 1393750, "totalSellQuantity": 1012500, "bidQty": 21875, "bidprice": 5.1, "askQty": 28125, "askPrice": 5.2, "underlyingValue": 213}, "PE": {"strikePrice": 215, "expiryDate": "31-Jul-2025", "underlying": "NYKAA", "identifier": "OPTSTKNYKAA31-07-2025PE215.00", "openInterest": 45, "changeinOpenInterest": -6, "pchangeinOpenInterest": -11.764705882352942, "totalTradedVolume": 103, "impliedVolatility": 36.29, "lastPrice": 7.9, "change": -6.15, "pChange": -43.77224199288256, "totalBuyQuantity": 496875, "totalSellQuantity": 490625, "bidQty": 3125, "bidprice": 7.85, "askQty": 3125, "askPrice": 7.95, "underlyingValue": 213}}, {"strikePrice": 215, "expiryDate": "28-Aug-2025", "PE": {"strikePrice": 215, "expiryDate": "28-Aug-2025", "underlying": "NYKAA", "identifier": "OPTSTKNYKAA28-08-2025PE215.00", "openInterest": 0, "changeinOpenInterest": 0, "pchangeinOpenInterest": 0, "totalTradedVolume": 0, "impliedVolatility": 0, "lastPrice": 0, "change": 0, "pChange": 0, "totalBuyQuantity": 43750, "totalSellQuantity": 59375, "bidQty": 12500, "bidprice": 8.7, "askQty": 15625, "askPrice": 15.85, "underlyingValue": 213}, "CE": {"strikePrice": 215, "expiryDate": "28-Aug-2025", "underlying": "NYKAA", "identifier": "OPTSTKNYKAA28-08-2025CE215.00", "openInterest": 0, "changeinOpenInterest": 0, "pchangeinOpenInterest": 0, "totalTradedVolume": 0, "impliedVolatility": 0, "lastPrice": 0, "change": 0, "pChange": 0, "totalBuyQuantity": 125000, "totalSellQuantity": 53125, "bidQty": 3125, "bidprice": 4.7, "askQty": 3125, "askPrice": 8.85, "underlyingValue": 213}}, {"strikePrice": 215, "expiryDate": "30-Sep-2025", "CE": {"strikePrice": 215, "expiryDate": "30-Sep-2025", "underlying": "NYKAA", "identifier": "OPTSTKNYKAA30-09-2025CE215.00", "openInterest": 0, "changeinOpenInterest": 0, "pchangeinOpenInterest": 0, "totalTradedVolume": 0, "impliedVolatility": 0, "lastPrice": 0, "change": 0, "pChange": 0, "totalBuyQuantity": 3125, "totalSellQuantity": 0, "bidQty": 3125, "bidprice": 0.05, "askQty": 0, "askPrice": 0, "underlyingValue": 213}}, {"strikePrice": 217.5, "expiryDate": "31-Jul-2025", "PE": {"strikePrice": 217.5, "expiryDate": "31-Jul-2025", "underlying": "NYKAA", "identifier": "OPTSTKNYKAA31-07-2025PE217.50", "openInterest": 56, "changeinOpenInterest": -8, "pchangeinOpenInterest": -12.5, "totalTradedVolume": 50, "impliedVolatility": 37.55, "lastPrice": 9.5, "change": -6.649999999999999, "pChange": -41.17647058823529, "totalBuyQuantity": 403125, "totalSellQuantity": 400000, "bidQty": 6250, "bidprice": 9.45, "askQty": 3125, "askPrice": 9.55, "underlyingValue": 213}, "CE": {"strikePrice": 217.5, "expiryDate": "31-Jul-2025", "underlying": "NYKAA", "identifier": "OPTSTKNYKAA31-07-2025CE217.50", "openInterest": 119, "changeinOpenInterest": 22, "pchangeinOpenInterest": 22.68041237113402, "totalTradedVolume": 203, "impliedVolatility": 26.46, "lastPrice": 4.15, "change": 2.45, "pChange": 144.11764705882354, "totalBuyQuantity": 971875, "totalSellQuantity": 778125, "bidQty": 15625, "bidprice": 4.2, "askQty": 9375, "askPrice": 4.3, "underlyingValue": 213}}, {"strikePrice": 217.5, "expiryDate": "28-Aug-2025", "CE": {"strikePrice": 217.5, "expiryDate": "28-Aug-2025", "underlying": "NYKAA", "identifier": "OPTSTKNYKAA28-08-2025CE217.50", "openInterest": 0, "changeinOpenInterest": 0, "pchangeinOpenInterest": 0, "totalTradedVolume": 0, "impliedVolatility": 0, "lastPrice": 0, "change": 0, "pChange": 0, "totalBuyQuantity": 56250, "totalSellQuantity": 46875, "bidQty": 12500, "bidprice": 4.65, "askQty": 3125, "askPrice": 9.4, "underlyingValue": 213}, "PE": {"strikePrice": 217.5, "expiryDate": "28-Aug-2025", "underlying": "NYKAA", "identifier": "OPTSTKNYKAA28-08-2025PE217.50", "openInterest": 0, "changeinOpenInterest": 0, "pchangeinOpenInterest": 0, "totalTradedVolume": 0, "impliedVolatility": 0, "lastPrice": 0, "change": 0, "pChange": 0, "totalBuyQuantity": 43750, "totalSellQuantity": 46875, "bidQty": 12500, "bidprice": 10.7, "askQty": 3125, "askPrice": 18.2, "underlyingValue": 213}}, {"strikePrice": 220, "expiryDate": "31-Jul-2025", "CE": {"strikePrice": 220, "expiryDate": "31-Jul-2025", "underlying": "NYKAA", "identifier": "OPTSTKNYKAA31-07-2025CE220.00", "openInterest": 931, "changeinOpenInterest": 30, "pchangeinOpenInterest": 3.329633740288568, "totalTradedVolume": 2836, "impliedVolatility": 27.24, "lastPrice": 3.5, "change": 2.2, "pChange": 169.23076923076923, "totalBuyQuantity": 2056250, "totalSellQuantity": 1143750, "bidQty": 3125, "bidprice": 3.5, "askQty": 31250, "askPrice": 3.55, "underlyingValue": 213}, "PE": {"strikePrice": 220, "expiryDate": "31-Jul-2025", "underlying": "NYKAA", "identifier": "OPTSTKNYKAA31-07-2025PE220.00", "openInterest": 54, "changeinOpenInterest": -13, "pchangeinOpenInterest": -19.402985074626866, "totalTradedVolume": 107, "impliedVolatility": 38.75, "lastPrice": 11.15, "change": -7.15, "pChange": -39.07103825136612, "totalBuyQuantity": 443750, "totalSellQuantity": 390625, "bidQty": 3125, "bidprice": 11.2, "askQty": 3125, "askPrice": 11.3, "underlyingValue": 213}}, {"strikePrice": 220, "expiryDate": "28-Aug-2025", "CE": {"strikePrice": 220, "expiryDate": "28-Aug-2025", "underlying": "NYKAA", "identifier": "OPTSTKNYKAA28-08-2025CE220.00", "openInterest": 0, "changeinOpenInterest": 0, "pchangeinOpenInterest": 0, "totalTradedVolume": 0, "impliedVolatility": 0, "lastPrice": 0, "change": 0, "pChange": 0, "totalBuyQuantity": 143750, "totalSellQuantity": 50000, "bidQty": 3125, "bidprice": 5.4, "askQty": 3125, "askPrice": 6.45, "underlyingValue": 213}, "PE": {"strikePrice": 220, "expiryDate": "28-Aug-2025", "underlying": "NYKAA", "identifier": "OPTSTKNYKAA28-08-2025PE220.00", "openInterest": 0, "changeinOpenInterest": 0, "pchangeinOpenInterest": 0, "totalTradedVolume": 0, "impliedVolatility": 0, "lastPrice": 0, "change": 0, "pChange": 0, "totalBuyQuantity": 43750, "totalSellQuantity": 43750, "bidQty": 12500, "bidprice": 14.4, "askQty": 12500, "askPrice": 16.6, "underlyingValue": 213}}, {"strikePrice": 220, "expiryDate": "30-Sep-2025", "CE": {"strikePrice": 220, "expiryDate": "30-Sep-2025", "underlying": "NYKAA", "identifier": "OPTSTKNYKAA30-09-2025CE220.00", "openInterest": 0, "changeinOpenInterest": 0, "pchangeinOpenInterest": 0, "totalTradedVolume": 0, "impliedVolatility": 0, "lastPrice": 0, "change": 0, "pChange": 0, "totalBuyQuantity": 3125, "totalSellQuantity": 0, "bidQty": 3125, "bidprice": 0.05, "askQty": 0, "askPrice": 0, "underlyingValue": 213}}, {"strikePrice": 222.5, "expiryDate": "31-Jul-2025", "CE": {"strikePrice": 222.5, "expiryDate": "31-Jul-2025", "underlying": "NYKAA", "identifier": "OPTSTKNYKAA31-07-2025CE222.50", "openInterest": 57, "changeinOpenInterest": 31, "pchangeinOpenInterest": 119.23076923076923, "totalTradedVolume": 147, "impliedVolatility": 28.36, "lastPrice": 2.85, "change": 1.85, "pChange": 185, "totalBuyQuantity": 828125, "totalSellQuantity": 712500, "bidQty": 12500, "bidprice": 2.8, "askQty": 15625, "askPrice": 2.95, "underlyingValue": 213}, "PE": {"strikePrice": 222.5, "expiryDate": "31-Jul-2025", "underlying": "NYKAA", "identifier": "OPTSTKNYKAA31-07-2025PE222.50", "openInterest": 10, "changeinOpenInterest": 3, "pchangeinOpenInterest": 42.857142857142854, "totalTradedVolume": 12, "impliedVolatility": 38.68, "lastPrice": 12.95, "change": -7.900000000000002, "pChange": -37.889688249400486, "totalBuyQuantity": 340625, "totalSellQuantity": 337500, "bidQty": 3125, "bidprice": 13.05, "askQty": 3125, "askPrice": 13.2, "underlyingValue": 213}}, {"strikePrice": 222.5, "expiryDate": "28-Aug-2025", "PE": {"strikePrice": 222.5, "expiryDate": "28-Aug-2025", "underlying": "NYKAA", "identifier": "OPTSTKNYKAA28-08-2025PE222.50", "openInterest": 0, "changeinOpenInterest": 0, "pchangeinOpenInterest": 0, "totalTradedVolume": 0, "impliedVolatility": 0, "lastPrice": 0, "change": 0, "pChange": 0, "totalBuyQuantity": 43750, "totalSellQuantity": 46875, "bidQty": 12500, "bidprice": 12.6, "askQty": 3125, "askPrice": 21.15, "underlyingValue": 213}, "CE": {"strikePrice": 222.5, "expiryDate": "28-Aug-2025", "underlying": "NYKAA", "identifier": "OPTSTKNYKAA28-08-2025CE222.50", "openInterest": 0, "changeinOpenInterest": 0, "pchangeinOpenInterest": 0, "totalTradedVolume": 0, "impliedVolatility": 0, "lastPrice": 0, "change": 0, "pChange": 0, "totalBuyQuantity": 46875, "totalSellQuantity": 46875, "bidQty": 31250, "bidprice": 0.9, "askQty": 12500, "askPrice": 7.2, "underlyingValue": 213}}, {"strikePrice": 225, "expiryDate": "31-Jul-2025", "PE": {"strikePrice": 225, "expiryDate": "31-Jul-2025", "underlying": "NYKAA", "identifier": "OPTSTKNYKAA31-07-2025PE225.00", "openInterest": 18, "changeinOpenInterest": 9, "pchangeinOpenInterest": 100, "totalTradedVolume": 22, "impliedVolatility": 39.63, "lastPrice": 14.85, "change": -7.9, "pChange": -34.72527472527473, "totalBuyQuantity": 346875, "totalSellQuantity": 362500, "bidQty": 3125, "bidprice": 15, "askQty": 3125, "askPrice": 15.15, "underlyingValue": 213}, "CE": {"strikePrice": 225, "expiryDate": "31-Jul-2025", "underlying": "NYKAA", "identifier": "OPTSTKNYKAA31-07-2025CE225.00", "openInterest": 192, "changeinOpenInterest": 55, "pchangeinOpenInterest": 40.14598540145985, "totalTradedVolume": 491, "impliedVolatility": 28.88, "lastPrice": 2.3, "change": 1.4999999999999998, "pChange": 187.49999999999994, "totalBuyQuantity": 1100000, "totalSellQuantity": 821875, "bidQty": 25000, "bidprice": 2.3, "askQty": 6250, "askPrice": 2.35, "underlyingValue": 213}}, {"strikePrice": 225, "expiryDate": "28-Aug-2025", "CE": {"strikePrice": 225, "expiryDate": "28-Aug-2025", "underlying": "NYKAA", "identifier": "OPTSTKNYKAA28-08-2025CE225.00", "openInterest": 0, "changeinOpenInterest": 0, "pchangeinOpenInterest": 0, "totalTradedVolume": 0, "impliedVolatility": 0, "lastPrice": 0, "change": 0, "pChange": 0, "totalBuyQuantity": 53125, "totalSellQuantity": 46875, "bidQty": 12500, "bidprice": 0.8, "askQty": 3125, "askPrice": 7.05, "underlyingValue": 213}, "PE": {"strikePrice": 225, "expiryDate": "28-Aug-2025", "underlying": "NYKAA", "identifier": "OPTSTKNYKAA28-08-2025PE225.00", "openInterest": 0, "changeinOpenInterest": 0, "pchangeinOpenInterest": 0, "totalTradedVolume": 0, "impliedVolatility": 0, "lastPrice": 0, "change": 0, "pChange": 0, "totalBuyQuantity": 43750, "totalSellQuantity": 43750, "bidQty": 12500, "bidprice": 14.5, "askQty": 12500, "askPrice": 22.7, "underlyingValue": 213}}, {"strikePrice": 225, "expiryDate": "30-Sep-2025", "CE": {"strikePrice": 225, "expiryDate": "30-Sep-2025", "underlying": "NYKAA", "identifier": "OPTSTKNYKAA30-09-2025CE225.00", "openInterest": 0, "changeinOpenInterest": 0, "pchangeinOpenInterest": 0, "totalTradedVolume": 0, "impliedVolatility": 0, "lastPrice": 0, "change": 0, "pChange": 0, "totalBuyQuantity": 3125, "totalSellQuantity": 0, "bidQty": 3125, "bidprice": 0.05, "askQty": 0, "askPrice": 0, "underlyingValue": 213}}, {"strikePrice": 227.5, "expiryDate": "31-Jul-2025", "CE": {"strikePrice": 227.5, "expiryDate": "31-Jul-2025", "underlying": "NYKAA", "identifier": "OPTSTKNYKAA31-07-2025CE227.50", "openInterest": 26, "changeinOpenInterest": 11, "pchangeinOpenInterest": 73.33333333333333, "totalTradedVolume": 78, "impliedVolatility": 29.7, "lastPrice": 1.85, "change": 1.1500000000000001, "pChange": 164.28571428571433, "totalBuyQuantity": 593750, "totalSellQuantity": 618750, "bidQty": 3125, "bidprice": 1.9, "askQty": 3125, "askPrice": 1.95, "underlyingValue": 213}, "PE": {"strikePrice": 227.5, "expiryDate": "31-Jul-2025", "underlying": "NYKAA", "identifier": "OPTSTKNYKAA31-07-2025PE227.50", "openInterest": 8, "changeinOpenInterest": 0, "pchangeinOpenInterest": 0, "totalTradedVolume": 1, "impliedVolatility": 39.86, "lastPrice": 16.7, "change": -3.0500000000000007, "pChange": -15.443037974683548, "totalBuyQuantity": 284375, "totalSellQuantity": 284375, "bidQty": 3125, "bidprice": 17.05, "askQty": 6250, "askPrice": 17.25, "underlyingValue": 213}}, {"strikePrice": 227.5, "expiryDate": "28-Aug-2025", "PE": {"strikePrice": 227.5, "expiryDate": "28-Aug-2025", "underlying": "NYKAA", "identifier": "OPTSTKNYKAA28-08-2025PE227.50", "openInterest": 0, "changeinOpenInterest": 0, "pchangeinOpenInterest": 0, "totalTradedVolume": 0, "impliedVolatility": 0, "lastPrice": 0, "change": 0, "pChange": 0, "totalBuyQuantity": 43750, "totalSellQuantity": 46875, "bidQty": 12500, "bidprice": 16.95, "askQty": 3125, "askPrice": 26.3, "underlyingValue": 213}, "CE": {"strikePrice": 227.5, "expiryDate": "28-Aug-2025", "underlying": "NYKAA", "identifier": "OPTSTKNYKAA28-08-2025CE227.50", "openInterest": 0, "changeinOpenInterest": 0, "pchangeinOpenInterest": 0, "totalTradedVolume": 0, "impliedVolatility": 0, "lastPrice": 0, "change": 0, "pChange": 0, "totalBuyQuantity": 43750, "totalSellQuantity": 46875, "bidQty": 12500, "bidprice": 0.8, "askQty": 3125, "askPrice": 6.55, "underlyingValue": 213}}, {"strikePrice": 230, "expiryDate": "31-Jul-2025", "CE": {"strikePrice": 230, "expiryDate": "31-Jul-2025", "underlying": "NYKAA", "identifier": "OPTSTKNYKAA31-07-2025CE230.00", "openInterest": 315, "changeinOpenInterest": -6, "pchangeinOpenInterest": -1.8691588785046729, "totalTradedVolume": 1437, "impliedVolatility": 30.33, "lastPrice": 1.6, "change": 1.05, "pChange": 190.9090909090909, "totalBuyQuantity": 1371875, "totalSellQuantity": 971875, "bidQty": 37500, "bidprice": 1.55, "askQty": 50000, "askPrice": 1.6, "underlyingValue": 213}, "PE": {"strikePrice": 230, "expiryDate": "31-Jul-2025", "underlying": "NYKAA", "identifier": "OPTSTKNYKAA31-07-2025PE230.00", "openInterest": 59, "changeinOpenInterest": 14, "pchangeinOpenInterest": 31.11111111111111, "totalTradedVolume": 22, "impliedVolatility": 44.27, "lastPrice": 19.35, "change": -9.649999999999999, "pChange": -33.27586206896551, "totalBuyQuantity": 306250, "totalSellQuantity": 309375, "bidQty": 6250, "bidprice": 19.15, "askQty": 3125, "askPrice": 19.35, "underlyingValue": 213}}, {"strikePrice": 230, "expiryDate": "28-Aug-2025", "CE": {"strikePrice": 230, "expiryDate": "28-Aug-2025", "underlying": "NYKAA", "identifier": "OPTSTKNYKAA28-08-2025CE230.00", "openInterest": 0, "changeinOpenInterest": 0, "pchangeinOpenInterest": 0, "totalTradedVolume": 0, "impliedVolatility": 0, "lastPrice": 0, "change": 0, "pChange": 0, "totalBuyQuantity": 53125, "totalSellQuantity": 43750, "bidQty": 3125, "bidprice": 1.55, "askQty": 12500, "askPrice": 7.25, "underlyingValue": 213}, "PE": {"strikePrice": 230, "expiryDate": "28-Aug-2025", "underlying": "NYKAA", "identifier": "OPTSTKNYKAA28-08-2025PE230.00", "openInterest": 0, "changeinOpenInterest": 0, "pchangeinOpenInterest": 0, "totalTradedVolume": 0, "impliedVolatility": 0, "lastPrice": 0, "change": 0, "pChange": 0, "totalBuyQuantity": 43750, "totalSellQuantity": 46875, "bidQty": 12500, "bidprice": 20.2, "askQty": 3125, "askPrice": 28.7, "underlyingValue": 213}}, {"strikePrice": 230, "expiryDate": "30-Sep-2025", "CE": {"strikePrice": 230, "expiryDate": "30-Sep-2025", "underlying": "NYKAA", "identifier": "OPTSTKNYKAA30-09-2025CE230.00", "openInterest": 0, "changeinOpenInterest": 0, "pchangeinOpenInterest": 0, "totalTradedVolume": 0, "impliedVolatility": 0, "lastPrice": 0, "change": 0, "pChange": 0, "totalBuyQuantity": 3125, "totalSellQuantity": 0, "bidQty": 3125, "bidprice": 0.05, "askQty": 0, "askPrice": 0, "underlyingValue": 213}}, {"strikePrice": 232.5, "expiryDate": "31-Jul-2025", "PE": {"strikePrice": 232.5, "expiryDate": "31-Jul-2025", "underlying": "NYKAA", "identifier": "OPTSTKNYKAA31-07-2025PE232.50", "openInterest": 1, "changeinOpenInterest": 0, "pchangeinOpenInterest": 0, "totalTradedVolume": 1, "impliedVolatility": 48.88, "lastPrice": 22.05, "change": -9.05, "pChange": -29.099678456591644, "totalBuyQuantity": 243750, "totalSellQuantity": 234375, "bidQty": 6250, "bidprice": 21.35, "askQty": 3125, "askPrice": 21.55, "underlyingValue": 213}, "CE": {"strikePrice": 232.5, "expiryDate": "31-Jul-2025", "underlying": "NYKAA", "identifier": "OPTSTKNYKAA31-07-2025CE232.50", "openInterest": 1, "changeinOpenInterest": 1, "pchangeinOpenInterest": 0, "totalTradedVolume": 5, "impliedVolatility": 31.64, "lastPrice": 1.3, "change": -3.3, "pChange": -71.73913043478261, "totalBuyQuantity": 518750, "totalSellQuantity": 487500, "bidQty": 3125, "bidprice": 1.25, "askQty": 6250, "askPrice": 1.3, "underlyingValue": 213}}, {"strikePrice": 232.5, "expiryDate": "28-Aug-2025", "CE": {"strikePrice": 232.5, "expiryDate": "28-Aug-2025", "underlying": "NYKAA", "identifier": "OPTSTKNYKAA28-08-2025CE232.50", "openInterest": 0, "changeinOpenInterest": 0, "pchangeinOpenInterest": 0, "totalTradedVolume": 0, "impliedVolatility": 0, "lastPrice": 0, "change": 0, "pChange": 0, "totalBuyQuantity": 43750, "totalSellQuantity": 46875, "bidQty": 12500, "bidprice": 0.25, "askQty": 3125, "askPrice": 5.7, "underlyingValue": 213}, "PE": {"strikePrice": 232.5, "expiryDate": "28-Aug-2025", "underlying": "NYKAA", "identifier": "OPTSTKNYKAA28-08-2025PE232.50", "openInterest": 0, "changeinOpenInterest": 0, "pchangeinOpenInterest": 0, "totalTradedVolume": 0, "impliedVolatility": 0, "lastPrice": 0, "change": 0, "pChange": 0, "totalBuyQuantity": 43750, "totalSellQuantity": 46875, "bidQty": 12500, "bidprice": 21.5, "askQty": 3125, "askPrice": 30.95, "underlyingValue": 213}}, {"strikePrice": 235, "expiryDate": "31-Jul-2025", "CE": {"strikePrice": 235, "expiryDate": "31-Jul-2025", "underlying": "NYKAA", "identifier": "OPTSTKNYKAA31-07-2025CE235.00", "openInterest": 70, "changeinOpenInterest": 12, "pchangeinOpenInterest": 20.689655172413794, "totalTradedVolume": 159, "impliedVolatility": 32.16, "lastPrice": 1.05, "change": 0.8, "pChange": 320, "totalBuyQuantity": 653125, "totalSellQuantity": 606250, "bidQty": 25000, "bidprice": 1, "askQty": 31250, "askPrice": 1.1, "underlyingValue": 213}, "PE": {"strikePrice": 235, "expiryDate": "31-Jul-2025", "underlying": "NYKAA", "identifier": "OPTSTKNYKAA31-07-2025PE235.00", "openInterest": 12, "changeinOpenInterest": 0, "pchangeinOpenInterest": 0, "totalTradedVolume": 1, "impliedVolatility": 45.43, "lastPrice": 23.45, "change": -8.3, "pChange": -26.14173228346457, "totalBuyQuantity": 243750, "totalSellQuantity": 246875, "bidQty": 3125, "bidprice": 23.6, "askQty": 3125, "askPrice": 23.8, "underlyingValue": 213}}, {"strikePrice": 235, "expiryDate": "28-Aug-2025", "PE": {"strikePrice": 235, "expiryDate": "28-Aug-2025", "underlying": "NYKAA", "identifier": "OPTSTKNYKAA28-08-2025PE235.00", "openInterest": 0, "changeinOpenInterest": 0, "pchangeinOpenInterest": 0, "totalTradedVolume": 0, "impliedVolatility": 0, "lastPrice": 0, "change": 0, "pChange": 0, "totalBuyQuantity": 43750, "totalSellQuantity": 43750, "bidQty": 12500, "bidprice": 24.9, "askQty": 12500, "askPrice": 30, "underlyingValue": 213}, "CE": {"strikePrice": 235, "expiryDate": "28-Aug-2025", "underlying": "NYKAA", "identifier": "OPTSTKNYKAA28-08-2025CE235.00", "openInterest": 0, "changeinOpenInterest": 0, "pchangeinOpenInterest": 0, "totalTradedVolume": 1, "impliedVolatility": 27.86, "lastPrice": 2.65, "change": -3.8000000000000003, "pChange": -58.91472868217055, "totalBuyQuantity": 6250, "totalSellQuantity": 53125, "bidQty": 6250, "bidprice": 1.05, "askQty": 6250, "askPrice": 5, "underlyingValue": 213}}, {"strikePrice": 237.5, "expiryDate": "31-Jul-2025", "CE": {"strikePrice": 237.5, "expiryDate": "31-Jul-2025", "underlying": "NYKAA", "identifier": "OPTSTKNYKAA31-07-2025CE237.50", "openInterest": 0, "changeinOpenInterest": 0, "pchangeinOpenInterest": 0, "totalTradedVolume": 0, "impliedVolatility": 0, "lastPrice": 0, "change": 0, "pChange": 0, "totalBuyQuantity": 128125, "totalSellQuantity": 225000, "bidQty": 3125, "bidprice": 0.7, "askQty": 3125, "askPrice": 1.05, "underlyingValue": 213}, "PE": {"strikePrice": 237.5, "expiryDate": "31-Jul-2025", "underlying": "NYKAA", "identifier": "OPTSTKNYKAA31-07-2025PE237.50", "openInterest": 0, "changeinOpenInterest": 0, "pchangeinOpenInterest": 0, "totalTradedVolume": 0, "impliedVolatility": 0, "lastPrice": 0, "change": 0, "pChange": 0, "totalBuyQuantity": 118750, "totalSellQuantity": 121875, "bidQty": 3125, "bidprice": 25.05, "askQty": 3125, "askPrice": 27.1, "underlyingValue": 213}}, {"strikePrice": 237.5, "expiryDate": "28-Aug-2025", "PE": {"strikePrice": 237.5, "expiryDate": "28-Aug-2025", "underlying": "NYKAA", "identifier": "OPTSTKNYKAA28-08-2025PE237.50", "openInterest": 0, "changeinOpenInterest": 0, "pchangeinOpenInterest": 0, "totalTradedVolume": 0, "impliedVolatility": 0, "lastPrice": 0, "change": 0, "pChange": 0, "totalBuyQuantity": 43750, "totalSellQuantity": 43750, "bidQty": 12500, "bidprice": 25.65, "askQty": 12500, "askPrice": 33.75, "underlyingValue": 213}, "CE": {"strikePrice": 237.5, "expiryDate": "28-Aug-2025", "underlying": "NYKAA", "identifier": "OPTSTKNYKAA28-08-2025CE237.50", "openInterest": 0, "changeinOpenInterest": 0, "pchangeinOpenInterest": 0, "totalTradedVolume": 0, "impliedVolatility": 0, "lastPrice": 0, "change": 0, "pChange": 0, "totalBuyQuantity": 0, "totalSellQuantity": 43750, "bidQty": 0, "bidprice": 0, "askQty": 12500, "askPrice": 5.75, "underlyingValue": 213}}, {"strikePrice": 240, "expiryDate": "31-Jul-2025", "CE": {"strikePrice": 240, "expiryDate": "31-Jul-2025", "underlying": "NYKAA", "identifier": "OPTSTKNYKAA31-07-2025CE240.00", "openInterest": 65, "changeinOpenInterest": 8, "pchangeinOpenInterest": 14.035087719298245, "totalTradedVolume": 171, "impliedVolatility": 33.37, "lastPrice": 0.7, "change": 0.44999999999999996, "pChange": 179.99999999999997, "totalBuyQuantity": 693750, "totalSellQuantity": 393750, "bidQty": 25000, "bidprice": 0.65, "askQty": 9375, "askPrice": 0.7, "underlyingValue": 213}, "PE": {"strikePrice": 240, "expiryDate": "31-Jul-2025", "underlying": "NYKAA", "identifier": "OPTSTKNYKAA31-07-2025PE240.00", "openInterest": 6, "changeinOpenInterest": 0, "pchangeinOpenInterest": 0, "totalTradedVolume": 0, "impliedVolatility": 0, "lastPrice": 0, "change": 0, "pChange": 0, "totalBuyQuantity": 234375, "totalSellQuantity": 240625, "bidQty": 3125, "bidprice": 27.5, "askQty": 3125, "askPrice": 29.05, "underlyingValue": 213}}, {"strikePrice": 240, "expiryDate": "28-Aug-2025", "CE": {"strikePrice": 240, "expiryDate": "28-Aug-2025", "underlying": "NYKAA", "identifier": "OPTSTKNYKAA28-08-2025CE240.00", "openInterest": 0, "changeinOpenInterest": 0, "pchangeinOpenInterest": 0, "totalTradedVolume": 1, "impliedVolatility": 31.07, "lastPrice": 2.5, "change": -2.95, "pChange": -54.12844036697248, "totalBuyQuantity": 46875, "totalSellQuantity": 25000, "bidQty": 6250, "bidprice": 0.8, "askQty": 9375, "askPrice": 4, "underlyingValue": 213}, "PE": {"strikePrice": 240, "expiryDate": "28-Aug-2025", "underlying": "NYKAA", "identifier": "OPTSTKNYKAA28-08-2025PE240.00", "openInterest": 0, "changeinOpenInterest": 0, "pchangeinOpenInterest": 0, "totalTradedVolume": 0, "impliedVolatility": 0, "lastPrice": 0, "change": 0, "pChange": 0, "totalBuyQuantity": 15625, "totalSellQuantity": 3125, "bidQty": 15625, "bidprice": 17.4, "askQty": 3125, "askPrice": 48.7, "underlyingValue": 213}}, {"strikePrice": 242.5, "expiryDate": "31-Jul-2025", "PE": {"strikePrice": 242.5, "expiryDate": "31-Jul-2025", "underlying": "NYKAA", "identifier": "OPTSTKNYKAA31-07-2025PE242.50", "openInterest": 0, "changeinOpenInterest": 0, "pchangeinOpenInterest": 0, "totalTradedVolume": 0, "impliedVolatility": 0, "lastPrice": 0, "change": 0, "pChange": 0, "totalBuyQuantity": 109375, "totalSellQuantity": 109375, "bidQty": 3125, "bidprice": 29.65, "askQty": 3125, "askPrice": 31.8, "underlyingValue": 213}, "CE": {"strikePrice": 242.5, "expiryDate": "31-Jul-2025", "underlying": "NYKAA", "identifier": "OPTSTKNYKAA31-07-2025CE242.50", "openInterest": 0, "changeinOpenInterest": 0, "pchangeinOpenInterest": 0, "totalTradedVolume": 0, "impliedVolatility": 0, "lastPrice": 0, "change": 0, "pChange": 0, "totalBuyQuantity": 128125, "totalSellQuantity": 225000, "bidQty": 3125, "bidprice": 0.35, "askQty": 3125, "askPrice": 0.8, "underlyingValue": 213}}], "timestamp": "09-Jul-2025 15:21:26", "underlyingValue": 213, "strikePrices": [170, 175, 177.5, 180, 182.5, 185, 187.5, 190, 192.5, 195, 197.5, 200, 202.5, 205, 207.5, 210, 212.5, 215, 217.5, 220, 222.5, 225, 227.5, 230, 232.5, 235, 237.5, 240, 242.5]}, "filtered": {"data": [{"strikePrice": 170, "expiryDate": "31-Jul-2025", "CE": {"strikePrice": 170, "expiryDate": "31-Jul-2025", "underlying": "NYKAA", "identifier": "OPTSTKNYKAA31-07-2025CE170.00", "openInterest": 0, "changeinOpenInterest": 0, "pchangeinOpenInterest": 0, "totalTradedVolume": 0, "impliedVolatility": 0, "lastPrice": 0, "change": 0, "pChange": 0, "totalBuyQuantity": 237500, "totalSellQuantity": 225000, "bidQty": 9375, "bidprice": 41.05, "askQty": 12500, "askPrice": 42.9, "underlyingValue": 213}, "PE": {"strikePrice": 170, "expiryDate": "31-Jul-2025", "underlying": "NYKAA", "identifier": "OPTSTKNYKAA31-07-2025PE170.00", "openInterest": 52, "changeinOpenInterest": -3, "pchangeinOpenInterest": -5.454545454545454, "totalTradedVolume": 13, "impliedVolatility": 43, "lastPrice": 0.1, "change": -0.15, "pChange": -60, "totalBuyQuantity": 56250, "totalSellQuantity": 478125, "bidQty": 3125, "bidprice": 0.1, "askQty": 50000, "askPrice": 0.15, "underlyingValue": 213}}, {"strikePrice": 175, "expiryDate": "31-Jul-2025", "CE": {"strikePrice": 175, "expiryDate": "31-Jul-2025", "underlying": "NYKAA", "identifier": "OPTSTKNYKAA31-07-2025CE175.00", "openInterest": 1, "changeinOpenInterest": 0, "pchangeinOpenInterest": 0, "totalTradedVolume": 0, "impliedVolatility": 0, "lastPrice": 0, "change": 0, "pChange": 0, "totalBuyQuantity": 240625, "totalSellQuantity": 231250, "bidQty": 9375, "bidprice": 36.25, "askQty": 12500, "askPrice": 38, "underlyingValue": 213}, "PE": {"strikePrice": 175, "expiryDate": "31-Jul-2025", "underlying": "NYKAA", "identifier": "OPTSTKNYKAA31-07-2025PE175.00", "openInterest": 57, "changeinOpenInterest": 4, "pchangeinOpenInterest": 7.547169811320755, "totalTradedVolume": 12, "impliedVolatility": 40.61, "lastPrice": 0.15, "change": -0.1, "pChange": -40, "totalBuyQuantity": 68750, "totalSellQuantity": 465625, "bidQty": 18750, "bidprice": 0.1, "askQty": 12500, "askPrice": 0.15, "underlyingValue": 213}}, {"strikePrice": 177.5, "expiryDate": "31-Jul-2025", "CE": {"strikePrice": 177.5, "expiryDate": "31-Jul-2025", "underlying": "NYKAA", "identifier": "OPTSTKNYKAA31-07-2025CE177.50", "openInterest": 1, "changeinOpenInterest": 0, "pchangeinOpenInterest": 0, "totalTradedVolume": 0, "impliedVolatility": 0, "lastPrice": 0, "change": 0, "pChange": 0, "totalBuyQuantity": 231250, "totalSellQuantity": 228125, "bidQty": 12500, "bidprice": 33.85, "askQty": 12500, "askPrice": 35.8, "underlyingValue": 213}, "PE": {"strikePrice": 177.5, "expiryDate": "31-Jul-2025", "underlying": "NYKAA", "identifier": "OPTSTKNYKAA31-07-2025PE177.50", "openInterest": 0, "changeinOpenInterest": 0, "pchangeinOpenInterest": 0, "totalTradedVolume": 0, "impliedVolatility": 0, "lastPrice": 0, "change": 0, "pChange": 0, "totalBuyQuantity": 712500, "totalSellQuantity": 331250, "bidQty": 712500, "bidprice": 0.05, "askQty": 31250, "askPrice": 0.45, "underlyingValue": 213}}, {"strikePrice": 180, "expiryDate": "31-Jul-2025", "PE": {"strikePrice": 180, "expiryDate": "31-Jul-2025", "underlying": "NYKAA", "identifier": "OPTSTKNYKAA31-07-2025PE180.00", "openInterest": 162, "changeinOpenInterest": -31, "pchangeinOpenInterest": -16.06217616580311, "totalTradedVolume": 122, "impliedVolatility": 37.43, "lastPrice": 0.2, "change": -0.25, "pChange": -55.55555555555556, "totalBuyQuantity": 453125, "totalSellQuantity": 712500, "bidQty": 78125, "bidprice": 0.15, "askQty": 40625, "askPrice": 0.2, "underlyingValue": 213}, "CE": {"strikePrice": 180, "expiryDate": "31-Jul-2025", "underlying": "NYKAA", "identifier": "OPTSTKNYKAA31-07-2025CE180.00", "openInterest": 17, "changeinOpenInterest": 0, "pchangeinOpenInterest": 0, "totalTradedVolume": 2, "impliedVolatility": 0, "lastPrice": 31.35, "change": 8.850000000000001, "pChange": 39.33333333333334, "totalBuyQuantity": 281250, "totalSellQuantity": 275000, "bidQty": 3125, "bidprice": 32.05, "askQty": 3125, "askPrice": 32.5, "underlyingValue": 213}}, {"strikePrice": 182.5, "expiryDate": "31-Jul-2025", "CE": {"strikePrice": 182.5, "expiryDate": "31-Jul-2025", "underlying": "NYKAA", "identifier": "OPTSTKNYKAA31-07-2025CE182.50", "openInterest": 18, "changeinOpenInterest": 0, "pchangeinOpenInterest": 0, "totalTradedVolume": 1, "impliedVolatility": 0, "lastPrice": 23.75, "change": 2.8000000000000007, "pChange": 13.365155131264919, "totalBuyQuantity": 253125, "totalSellQuantity": 234375, "bidQty": 3125, "bidprice": 29.55, "askQty": 3125, "askPrice": 30.4, "underlyingValue": 213}, "PE": {"strikePrice": 182.5, "expiryDate": "31-Jul-2025", "underlying": "NYKAA", "identifier": "OPTSTKNYKAA31-07-2025PE182.50", "openInterest": 26, "changeinOpenInterest": 0, "pchangeinOpenInterest": 0, "totalTradedVolume": 1, "impliedVolatility": 33.28, "lastPrice": 0.15, "change": -0.75, "pChange": -83.33333333333333, "totalBuyQuantity": 325000, "totalSellQuantity": 412500, "bidQty": 3125, "bidprice": 0.2, "askQty": 3125, "askPrice": 0.6, "underlyingValue": 213}}, {"strikePrice": 185, "expiryDate": "31-Jul-2025", "CE": {"strikePrice": 185, "expiryDate": "31-Jul-2025", "underlying": "NYKAA", "identifier": "OPTSTKNYKAA31-07-2025CE185.00", "openInterest": 14, "changeinOpenInterest": -2, "pchangeinOpenInterest": -12.5, "totalTradedVolume": 5, "impliedVolatility": 0, "lastPrice": 25.05, "change": 6.350000000000001, "pChange": 33.95721925133691, "totalBuyQuantity": 259375, "totalSellQuantity": 243750, "bidQty": 3125, "bidprice": 27.2, "askQty": 3125, "askPrice": 27.95, "underlyingValue": 213}, "PE": {"strikePrice": 185, "expiryDate": "31-Jul-2025", "underlying": "NYKAA", "identifier": "OPTSTKNYKAA31-07-2025PE185.00", "openInterest": 113, "changeinOpenInterest": -84, "pchangeinOpenInterest": -42.63959390862944, "totalTradedVolume": 189, "impliedVolatility": 34.91, "lastPrice": 0.3, "change": -0.6000000000000001, "pChange": -66.66666666666667, "totalBuyQuantity": 696875, "totalSellQuantity": 684375, "bidQty": 21875, "bidprice": 0.3, "askQty": 21875, "askPrice": 0.35, "underlyingValue": 213}}, {"strikePrice": 187.5, "expiryDate": "31-Jul-2025", "CE": {"strikePrice": 187.5, "expiryDate": "31-Jul-2025", "underlying": "NYKAA", "identifier": "OPTSTKNYKAA31-07-2025CE187.50", "openInterest": 13, "changeinOpenInterest": -1, "pchangeinOpenInterest": -7.142857142857143, "totalTradedVolume": 8, "impliedVolatility": 0, "lastPrice": 22.7, "change": 6.349999999999998, "pChange": 38.83792048929662, "totalBuyQuantity": 256250, "totalSellQuantity": 253125, "bidQty": 3125, "bidprice": 24.9, "askQty": 3125, "askPrice": 25.4, "underlyingValue": 213}, "PE": {"strikePrice": 187.5, "expiryDate": "31-Jul-2025", "underlying": "NYKAA", "identifier": "OPTSTKNYKAA31-07-2025PE187.50", "openInterest": 51, "changeinOpenInterest": -8, "pchangeinOpenInterest": -13.559322033898304, "totalTradedVolume": 55, "impliedVolatility": 34.23, "lastPrice": 0.4, "change": -0.7999999999999999, "pChange": -66.66666666666666, "totalBuyQuantity": 456250, "totalSellQuantity": 590625, "bidQty": 3125, "bidprice": 0.4, "askQty": 9375, "askPrice": 0.45, "underlyingValue": 213}}, {"strikePrice": 190, "expiryDate": "31-Jul-2025", "PE": {"strikePrice": 190, "expiryDate": "31-Jul-2025", "underlying": "NYKAA", "identifier": "OPTSTKNYKAA31-07-2025PE190.00", "openInterest": 590, "changeinOpenInterest": -2, "pchangeinOpenInterest": -0.33783783783783783, "totalTradedVolume": 704, "impliedVolatility": 33.84, "lastPrice": 0.55, "change": -1.0999999999999999, "pChange": -66.66666666666666, "totalBuyQuantity": 1078125, "totalSellQuantity": 1187500, "bidQty": 21875, "bidprice": 0.55, "askQty": 62500, "askPrice": 0.6, "underlyingValue": 213}, "CE": {"strikePrice": 190, "expiryDate": "31-Jul-2025", "underlying": "NYKAA", "identifier": "OPTSTKNYKAA31-07-2025CE190.00", "openInterest": 64, "changeinOpenInterest": -1, "pchangeinOpenInterest": -1.5384615384615385, "totalTradedVolume": 27, "impliedVolatility": 0, "lastPrice": 22.3, "change": 7.800000000000001, "pChange": 53.79310344827587, "totalBuyQuantity": 328125, "totalSellQuantity": 337500, "bidQty": 3125, "bidprice": 22.55, "askQty": 3125, "askPrice": 22.8, "underlyingValue": 213}}, {"strikePrice": 192.5, "expiryDate": "31-Jul-2025", "CE": {"strikePrice": 192.5, "expiryDate": "31-Jul-2025", "underlying": "NYKAA", "identifier": "OPTSTKNYKAA31-07-2025CE192.50", "openInterest": 15, "changeinOpenInterest": -3, "pchangeinOpenInterest": -16.666666666666668, "totalTradedVolume": 14, "impliedVolatility": 0, "lastPrice": 19.55, "change": 7.5, "pChange": 62.24066390041494, "totalBuyQuantity": 296875, "totalSellQuantity": 387500, "bidQty": 3125, "bidprice": 20.25, "askQty": 3125, "askPrice": 20.45, "underlyingValue": 213}, "PE": {"strikePrice": 192.5, "expiryDate": "31-Jul-2025", "underlying": "NYKAA", "identifier": "OPTSTKNYKAA31-07-2025PE192.50", "openInterest": 67, "changeinOpenInterest": -16, "pchangeinOpenInterest": -19.27710843373494, "totalTradedVolume": 80, "impliedVolatility": 33.48, "lastPrice": 0.75, "change": -1.4, "pChange": -65.11627906976743, "totalBuyQuantity": 412500, "totalSellQuantity": 621875, "bidQty": 6250, "bidprice": 0.7, "askQty": 3125, "askPrice": 0.75, "underlyingValue": 213}}, {"strikePrice": 195, "expiryDate": "31-Jul-2025", "PE": {"strikePrice": 195, "expiryDate": "31-Jul-2025", "underlying": "NYKAA", "identifier": "OPTSTKNYKAA31-07-2025PE195.00", "openInterest": 252, "changeinOpenInterest": -30, "pchangeinOpenInterest": -10.638297872340425, "totalTradedVolume": 518, "impliedVolatility": 33.54, "lastPrice": 1.05, "change": -1.5999999999999999, "pChange": -60.37735849056604, "totalBuyQuantity": 906250, "totalSellQuantity": 1121875, "bidQty": 109375, "bidprice": 1, "askQty": 53125, "askPrice": 1.05, "underlyingValue": 213}, "CE": {"strikePrice": 195, "expiryDate": "31-Jul-2025", "underlying": "NYKAA", "identifier": "OPTSTKNYKAA31-07-2025CE195.00", "openInterest": 97, "changeinOpenInterest": -1, "pchangeinOpenInterest": -1.0204081632653061, "totalTradedVolume": 42, "impliedVolatility": 0, "lastPrice": 18.05, "change": 7.450000000000001, "pChange": 70.28301886792454, "totalBuyQuantity": 406250, "totalSellQuantity": 396875, "bidQty": 3125, "bidprice": 18, "askQty": 3125, "askPrice": 18.25, "underlyingValue": 213}}, {"strikePrice": 197.5, "expiryDate": "31-Jul-2025", "PE": {"strikePrice": 197.5, "expiryDate": "31-Jul-2025", "underlying": "NYKAA", "identifier": "OPTSTKNYKAA31-07-2025PE197.50", "openInterest": 88, "changeinOpenInterest": -1, "pchangeinOpenInterest": -1.1235955056179776, "totalTradedVolume": 112, "impliedVolatility": 33.29, "lastPrice": 1.35, "change": -2.25, "pChange": -62.5, "totalBuyQuantity": 681250, "totalSellQuantity": 856250, "bidQty": 15625, "bidprice": 1.3, "askQty": 18750, "askPrice": 1.4, "underlyingValue": 213}, "CE": {"strikePrice": 197.5, "expiryDate": "31-Jul-2025", "underlying": "NYKAA", "identifier": "OPTSTKNYKAA31-07-2025CE197.50", "openInterest": 52, "changeinOpenInterest": -2, "pchangeinOpenInterest": -3.7037037037037037, "totalTradedVolume": 35, "impliedVolatility": 0, "lastPrice": 15.85, "change": 6.85, "pChange": 76.11111111111111, "totalBuyQuantity": 378125, "totalSellQuantity": 371875, "bidQty": 3125, "bidprice": 15.9, "askQty": 3125, "askPrice": 16.1, "underlyingValue": 213}}, {"strikePrice": 200, "expiryDate": "31-Jul-2025", "PE": {"strikePrice": 200, "expiryDate": "31-Jul-2025", "underlying": "NYKAA", "identifier": "OPTSTKNYKAA31-07-2025PE200.00", "openInterest": 799, "changeinOpenInterest": 134, "pchangeinOpenInterest": 20.150375939849624, "totalTradedVolume": 1178, "impliedVolatility": 33.14, "lastPrice": 1.8, "change": -2.75, "pChange": -60.439560439560445, "totalBuyQuantity": 1043750, "totalSellQuantity": 1462500, "bidQty": 71875, "bidprice": 1.75, "askQty": 65625, "askPrice": 1.85, "underlyingValue": 213}, "CE": {"strikePrice": 200, "expiryDate": "31-Jul-2025", "underlying": "NYKAA", "identifier": "OPTSTKNYKAA31-07-2025CE200.00", "openInterest": 564, "changeinOpenInterest": -121, "pchangeinOpenInterest": -17.664233576642335, "totalTradedVolume": 809, "impliedVolatility": 0, "lastPrice": 13.85, "change": 6.3, "pChange": 83.44370860927152, "totalBuyQuantity": 528125, "totalSellQuantity": 590625, "bidQty": 3125, "bidprice": 13.85, "askQty": 3125, "askPrice": 14.05, "underlyingValue": 213}}, {"strikePrice": 202.5, "expiryDate": "31-Jul-2025", "CE": {"strikePrice": 202.5, "expiryDate": "31-Jul-2025", "underlying": "NYKAA", "identifier": "OPTSTKNYKAA31-07-2025CE202.50", "openInterest": 102, "changeinOpenInterest": -51, "pchangeinOpenInterest": -33.333333333333336, "totalTradedVolume": 300, "impliedVolatility": 13.03, "lastPrice": 11.95, "change": 5.699999999999999, "pChange": 91.19999999999999, "totalBuyQuantity": 475000, "totalSellQuantity": 459375, "bidQty": 3125, "bidprice": 12, "askQty": 6250, "askPrice": 12.15, "underlyingValue": 213}, "PE": {"strikePrice": 202.5, "expiryDate": "31-Jul-2025", "underlying": "NYKAA", "identifier": "OPTSTKNYKAA31-07-2025PE202.50", "openInterest": 54, "changeinOpenInterest": -10, "pchangeinOpenInterest": -15.625, "totalTradedVolume": 154, "impliedVolatility": 32.64, "lastPrice": 2.35, "change": -3.4499999999999997, "pChange": -59.48275862068966, "totalBuyQuantity": 800000, "totalSellQuantity": 975000, "bidQty": 9375, "bidprice": 2.35, "askQty": 9375, "askPrice": 2.45, "underlyingValue": 213}}, {"strikePrice": 205, "expiryDate": "31-Jul-2025", "PE": {"strikePrice": 205, "expiryDate": "31-Jul-2025", "underlying": "NYKAA", "identifier": "OPTSTKNYKAA31-07-2025PE205.00", "openInterest": 412, "changeinOpenInterest": 203, "pchangeinOpenInterest": 97.12918660287082, "totalTradedVolume": 892, "impliedVolatility": 33.82, "lastPrice": 3.1, "change": -4.050000000000001, "pChange": -56.64335664335665, "totalBuyQuantity": 1078125, "totalSellQuantity": 1171875, "bidQty": 9375, "bidprice": 3.1, "askQty": 15625, "askPrice": 3.15, "underlyingValue": 213}, "CE": {"strikePrice": 205, "expiryDate": "31-Jul-2025", "underlying": "NYKAA", "identifier": "OPTSTKNYKAA31-07-2025CE205.00", "openInterest": 607, "changeinOpenInterest": -196, "pchangeinOpenInterest": -24.408468244084684, "totalTradedVolume": 1475, "impliedVolatility": 18.57, "lastPrice": 10.25, "change": 5.15, "pChange": 100.98039215686276, "totalBuyQuantity": 687500, "totalSellQuantity": 528125, "bidQty": 6250, "bidprice": 10.25, "askQty": 12500, "askPrice": 10.4, "underlyingValue": 213}}, {"strikePrice": 207.5, "expiryDate": "31-Jul-2025", "CE": {"strikePrice": 207.5, "expiryDate": "31-Jul-2025", "underlying": "NYKAA", "identifier": "OPTSTKNYKAA31-07-2025CE207.50", "openInterest": 81, "changeinOpenInterest": -12, "pchangeinOpenInterest": -12.903225806451612, "totalTradedVolume": 782, "impliedVolatility": 21.1, "lastPrice": 8.7, "change": 4.6, "pChange": 112.19512195121952, "totalBuyQuantity": 528125, "totalSellQuantity": 487500, "bidQty": 3125, "bidprice": 8.7, "askQty": 3125, "askPrice": 8.8, "underlyingValue": 213}, "PE": {"strikePrice": 207.5, "expiryDate": "31-Jul-2025", "underlying": "NYKAA", "identifier": "OPTSTKNYKAA31-07-2025PE207.50", "openInterest": 84, "changeinOpenInterest": 37, "pchangeinOpenInterest": 78.72340425531915, "totalTradedVolume": 241, "impliedVolatility": 34.14, "lastPrice": 4.1, "change": -4.550000000000001, "pChange": -52.601156069364166, "totalBuyQuantity": 706250, "totalSellQuantity": 796875, "bidQty": 9375, "bidprice": 4, "askQty": 9375, "askPrice": 4.1, "underlyingValue": 213}}, {"strikePrice": 210, "expiryDate": "31-Jul-2025", "CE": {"strikePrice": 210, "expiryDate": "31-Jul-2025", "underlying": "NYKAA", "identifier": "OPTSTKNYKAA31-07-2025CE210.00", "openInterest": 968, "changeinOpenInterest": -259, "pchangeinOpenInterest": -21.10839445802771, "totalTradedVolume": 5456, "impliedVolatility": 22.9, "lastPrice": 7.3, "change": 4, "pChange": 121.21212121212122, "totalBuyQuantity": 1171875, "totalSellQuantity": 1006250, "bidQty": 6250, "bidprice": 7.3, "askQty": 6250, "askPrice": 7.4, "underlyingValue": 213}, "PE": {"strikePrice": 210, "expiryDate": "31-Jul-2025", "underlying": "NYKAA", "identifier": "OPTSTKNYKAA31-07-2025PE210.00", "openInterest": 417, "changeinOpenInterest": 129, "pchangeinOpenInterest": 44.791666666666664, "totalTradedVolume": 1172, "impliedVolatility": 34.74, "lastPrice": 5.25, "change": -5, "pChange": -48.78048780487805, "totalBuyQuantity": 1012500, "totalSellQuantity": 940625, "bidQty": 15625, "bidprice": 5.1, "askQty": 12500, "askPrice": 5.2, "underlyingValue": 213}}, {"strikePrice": 212.5, "expiryDate": "31-Jul-2025", "PE": {"strikePrice": 212.5, "expiryDate": "31-Jul-2025", "underlying": "NYKAA", "identifier": "OPTSTKNYKAA31-07-2025PE212.50", "openInterest": 44, "changeinOpenInterest": 29, "pchangeinOpenInterest": 193.33333333333334, "totalTradedVolume": 143, "impliedVolatility": 35.85, "lastPrice": 6.4, "change": -5.699999999999999, "pChange": -47.10743801652892, "totalBuyQuantity": 553125, "totalSellQuantity": 559375, "bidQty": 3125, "bidprice": 6.4, "askQty": 3125, "askPrice": 6.5, "underlyingValue": 213}, "CE": {"strikePrice": 212.5, "expiryDate": "31-Jul-2025", "underlying": "NYKAA", "identifier": "OPTSTKNYKAA31-07-2025CE212.50", "openInterest": 142, "changeinOpenInterest": 23, "pchangeinOpenInterest": 19.327731092436974, "totalTradedVolume": 1030, "impliedVolatility": 24.18, "lastPrice": 6.1, "change": 3.4999999999999996, "pChange": 134.6153846153846, "totalBuyQuantity": 878125, "totalSellQuantity": 731250, "bidQty": 3125, "bidprice": 6.1, "askQty": 12500, "askPrice": 6.2, "underlyingValue": 213}}, {"strikePrice": 215, "expiryDate": "31-Jul-2025", "CE": {"strikePrice": 215, "expiryDate": "31-Jul-2025", "underlying": "NYKAA", "identifier": "OPTSTKNYKAA31-07-2025CE215.00", "openInterest": 411, "changeinOpenInterest": 65, "pchangeinOpenInterest": 18.786127167630056, "totalTradedVolume": 2116, "impliedVolatility": 25.64, "lastPrice": 5.15, "change": 3.0500000000000003, "pChange": 145.23809523809524, "totalBuyQuantity": 1393750, "totalSellQuantity": 1012500, "bidQty": 21875, "bidprice": 5.1, "askQty": 28125, "askPrice": 5.2, "underlyingValue": 213}, "PE": {"strikePrice": 215, "expiryDate": "31-Jul-2025", "underlying": "NYKAA", "identifier": "OPTSTKNYKAA31-07-2025PE215.00", "openInterest": 45, "changeinOpenInterest": -6, "pchangeinOpenInterest": -11.764705882352942, "totalTradedVolume": 103, "impliedVolatility": 36.29, "lastPrice": 7.9, "change": -6.15, "pChange": -43.77224199288256, "totalBuyQuantity": 496875, "totalSellQuantity": 490625, "bidQty": 3125, "bidprice": 7.85, "askQty": 3125, "askPrice": 7.95, "underlyingValue": 213}}, {"strikePrice": 217.5, "expiryDate": "31-Jul-2025", "PE": {"strikePrice": 217.5, "expiryDate": "31-Jul-2025", "underlying": "NYKAA", "identifier": "OPTSTKNYKAA31-07-2025PE217.50", "openInterest": 56, "changeinOpenInterest": -8, "pchangeinOpenInterest": -12.5, "totalTradedVolume": 50, "impliedVolatility": 37.55, "lastPrice": 9.5, "change": -6.649999999999999, "pChange": -41.17647058823529, "totalBuyQuantity": 403125, "totalSellQuantity": 400000, "bidQty": 6250, "bidprice": 9.45, "askQty": 3125, "askPrice": 9.55, "underlyingValue": 213}, "CE": {"strikePrice": 217.5, "expiryDate": "31-Jul-2025", "underlying": "NYKAA", "identifier": "OPTSTKNYKAA31-07-2025CE217.50", "openInterest": 119, "changeinOpenInterest": 22, "pchangeinOpenInterest": 22.68041237113402, "totalTradedVolume": 203, "impliedVolatility": 26.46, "lastPrice": 4.15, "change": 2.45, "pChange": 144.11764705882354, "totalBuyQuantity": 971875, "totalSellQuantity": 778125, "bidQty": 15625, "bidprice": 4.2, "askQty": 9375, "askPrice": 4.3, "underlyingValue": 213}}, {"strikePrice": 220, "expiryDate": "31-Jul-2025", "CE": {"strikePrice": 220, "expiryDate": "31-Jul-2025", "underlying": "NYKAA", "identifier": "OPTSTKNYKAA31-07-2025CE220.00", "openInterest": 931, "changeinOpenInterest": 30, "pchangeinOpenInterest": 3.329633740288568, "totalTradedVolume": 2836, "impliedVolatility": 27.24, "lastPrice": 3.5, "change": 2.2, "pChange": 169.23076923076923, "totalBuyQuantity": 2056250, "totalSellQuantity": 1143750, "bidQty": 3125, "bidprice": 3.5, "askQty": 31250, "askPrice": 3.55, "underlyingValue": 213}, "PE": {"strikePrice": 220, "expiryDate": "31-Jul-2025", "underlying": "NYKAA", "identifier": "OPTSTKNYKAA31-07-2025PE220.00", "openInterest": 54, "changeinOpenInterest": -13, "pchangeinOpenInterest": -19.402985074626866, "totalTradedVolume": 107, "impliedVolatility": 38.75, "lastPrice": 11.15, "change": -7.15, "pChange": -39.07103825136612, "totalBuyQuantity": 443750, "totalSellQuantity": 390625, "bidQty": 3125, "bidprice": 11.2, "askQty": 3125, "askPrice": 11.3, "underlyingValue": 213}}, {"strikePrice": 222.5, "expiryDate": "31-Jul-2025", "CE": {"strikePrice": 222.5, "expiryDate": "31-Jul-2025", "underlying": "NYKAA", "identifier": "OPTSTKNYKAA31-07-2025CE222.50", "openInterest": 57, "changeinOpenInterest": 31, "pchangeinOpenInterest": 119.23076923076923, "totalTradedVolume": 147, "impliedVolatility": 28.36, "lastPrice": 2.85, "change": 1.85, "pChange": 185, "totalBuyQuantity": 828125, "totalSellQuantity": 712500, "bidQty": 12500, "bidprice": 2.8, "askQty": 15625, "askPrice": 2.95, "underlyingValue": 213}, "PE": {"strikePrice": 222.5, "expiryDate": "31-Jul-2025", "underlying": "NYKAA", "identifier": "OPTSTKNYKAA31-07-2025PE222.50", "openInterest": 10, "changeinOpenInterest": 3, "pchangeinOpenInterest": 42.857142857142854, "totalTradedVolume": 12, "impliedVolatility": 38.68, "lastPrice": 12.95, "change": -7.900000000000002, "pChange": -37.889688249400486, "totalBuyQuantity": 340625, "totalSellQuantity": 337500, "bidQty": 3125, "bidprice": 13.05, "askQty": 3125, "askPrice": 13.2, "underlyingValue": 213}}, {"strikePrice": 225, "expiryDate": "31-Jul-2025", "PE": {"strikePrice": 225, "expiryDate": "31-Jul-2025", "underlying": "NYKAA", "identifier": "OPTSTKNYKAA31-07-2025PE225.00", "openInterest": 18, "changeinOpenInterest": 9, "pchangeinOpenInterest": 100, "totalTradedVolume": 22, "impliedVolatility": 39.63, "lastPrice": 14.85, "change": -7.9, "pChange": -34.72527472527473, "totalBuyQuantity": 346875, "totalSellQuantity": 362500, "bidQty": 3125, "bidprice": 15, "askQty": 3125, "askPrice": 15.15, "underlyingValue": 213}, "CE": {"strikePrice": 225, "expiryDate": "31-Jul-2025", "underlying": "NYKAA", "identifier": "OPTSTKNYKAA31-07-2025CE225.00", "openInterest": 192, "changeinOpenInterest": 55, "pchangeinOpenInterest": 40.14598540145985, "totalTradedVolume": 491, "impliedVolatility": 28.88, "lastPrice": 2.3, "change": 1.4999999999999998, "pChange": 187.49999999999994, "totalBuyQuantity": 1100000, "totalSellQuantity": 821875, "bidQty": 25000, "bidprice": 2.3, "askQty": 6250, "askPrice": 2.35, "underlyingValue": 213}}, {"strikePrice": 227.5, "expiryDate": "31-Jul-2025", "CE": {"strikePrice": 227.5, "expiryDate": "31-Jul-2025", "underlying": "NYKAA", "identifier": "OPTSTKNYKAA31-07-2025CE227.50", "openInterest": 26, "changeinOpenInterest": 11, "pchangeinOpenInterest": 73.33333333333333, "totalTradedVolume": 78, "impliedVolatility": 29.7, "lastPrice": 1.85, "change": 1.1500000000000001, "pChange": 164.28571428571433, "totalBuyQuantity": 593750, "totalSellQuantity": 618750, "bidQty": 3125, "bidprice": 1.9, "askQty": 3125, "askPrice": 1.95, "underlyingValue": 213}, "PE": {"strikePrice": 227.5, "expiryDate": "31-Jul-2025", "underlying": "NYKAA", "identifier": "OPTSTKNYKAA31-07-2025PE227.50", "openInterest": 8, "changeinOpenInterest": 0, "pchangeinOpenInterest": 0, "totalTradedVolume": 1, "impliedVolatility": 39.86, "lastPrice": 16.7, "change": -3.0500000000000007, "pChange": -15.443037974683548, "totalBuyQuantity": 284375, "totalSellQuantity": 284375, "bidQty": 3125, "bidprice": 17.05, "askQty": 6250, "askPrice": 17.25, "underlyingValue": 213}}, {"strikePrice": 230, "expiryDate": "31-Jul-2025", "CE": {"strikePrice": 230, "expiryDate": "31-Jul-2025", "underlying": "NYKAA", "identifier": "OPTSTKNYKAA31-07-2025CE230.00", "openInterest": 315, "changeinOpenInterest": -6, "pchangeinOpenInterest": -1.8691588785046729, "totalTradedVolume": 1437, "impliedVolatility": 30.33, "lastPrice": 1.6, "change": 1.05, "pChange": 190.9090909090909, "totalBuyQuantity": 1371875, "totalSellQuantity": 971875, "bidQty": 37500, "bidprice": 1.55, "askQty": 50000, "askPrice": 1.6, "underlyingValue": 213}, "PE": {"strikePrice": 230, "expiryDate": "31-Jul-2025", "underlying": "NYKAA", "identifier": "OPTSTKNYKAA31-07-2025PE230.00", "openInterest": 59, "changeinOpenInterest": 14, "pchangeinOpenInterest": 31.11111111111111, "totalTradedVolume": 22, "impliedVolatility": 44.27, "lastPrice": 19.35, "change": -9.649999999999999, "pChange": -33.27586206896551, "totalBuyQuantity": 306250, "totalSellQuantity": 309375, "bidQty": 6250, "bidprice": 19.15, "askQty": 3125, "askPrice": 19.35, "underlyingValue": 213}}, {"strikePrice": 232.5, "expiryDate": "31-Jul-2025", "PE": {"strikePrice": 232.5, "expiryDate": "31-Jul-2025", "underlying": "NYKAA", "identifier": "OPTSTKNYKAA31-07-2025PE232.50", "openInterest": 1, "changeinOpenInterest": 0, "pchangeinOpenInterest": 0, "totalTradedVolume": 1, "impliedVolatility": 48.88, "lastPrice": 22.05, "change": -9.05, "pChange": -29.099678456591644, "totalBuyQuantity": 243750, "totalSellQuantity": 234375, "bidQty": 6250, "bidprice": 21.35, "askQty": 3125, "askPrice": 21.55, "underlyingValue": 213}, "CE": {"strikePrice": 232.5, "expiryDate": "31-Jul-2025", "underlying": "NYKAA", "identifier": "OPTSTKNYKAA31-07-2025CE232.50", "openInterest": 1, "changeinOpenInterest": 1, "pchangeinOpenInterest": 0, "totalTradedVolume": 5, "impliedVolatility": 31.64, "lastPrice": 1.3, "change": -3.3, "pChange": -71.73913043478261, "totalBuyQuantity": 518750, "totalSellQuantity": 487500, "bidQty": 3125, "bidprice": 1.25, "askQty": 6250, "askPrice": 1.3, "underlyingValue": 213}}, {"strikePrice": 235, "expiryDate": "31-Jul-2025", "CE": {"strikePrice": 235, "expiryDate": "31-Jul-2025", "underlying": "NYKAA", "identifier": "OPTSTKNYKAA31-07-2025CE235.00", "openInterest": 70, "changeinOpenInterest": 12, "pchangeinOpenInterest": 20.689655172413794, "totalTradedVolume": 159, "impliedVolatility": 32.16, "lastPrice": 1.05, "change": 0.8, "pChange": 320, "totalBuyQuantity": 653125, "totalSellQuantity": 606250, "bidQty": 25000, "bidprice": 1, "askQty": 31250, "askPrice": 1.1, "underlyingValue": 213}, "PE": {"strikePrice": 235, "expiryDate": "31-Jul-2025", "underlying": "NYKAA", "identifier": "OPTSTKNYKAA31-07-2025PE235.00", "openInterest": 12, "changeinOpenInterest": 0, "pchangeinOpenInterest": 0, "totalTradedVolume": 1, "impliedVolatility": 45.43, "lastPrice": 23.45, "change": -8.3, "pChange": -26.14173228346457, "totalBuyQuantity": 243750, "totalSellQuantity": 246875, "bidQty": 3125, "bidprice": 23.6, "askQty": 3125, "askPrice": 23.8, "underlyingValue": 213}}, {"strikePrice": 237.5, "expiryDate": "31-Jul-2025", "CE": {"strikePrice": 237.5, "expiryDate": "31-Jul-2025", "underlying": "NYKAA", "identifier": "OPTSTKNYKAA31-07-2025CE237.50", "openInterest": 0, "changeinOpenInterest": 0, "pchangeinOpenInterest": 0, "totalTradedVolume": 0, "impliedVolatility": 0, "lastPrice": 0, "change": 0, "pChange": 0, "totalBuyQuantity": 128125, "totalSellQuantity": 225000, "bidQty": 3125, "bidprice": 0.7, "askQty": 3125, "askPrice": 1.05, "underlyingValue": 213}, "PE": {"strikePrice": 237.5, "expiryDate": "31-Jul-2025", "underlying": "NYKAA", "identifier": "OPTSTKNYKAA31-07-2025PE237.50", "openInterest": 0, "changeinOpenInterest": 0, "pchangeinOpenInterest": 0, "totalTradedVolume": 0, "impliedVolatility": 0, "lastPrice": 0, "change": 0, "pChange": 0, "totalBuyQuantity": 118750, "totalSellQuantity": 121875, "bidQty": 3125, "bidprice": 25.05, "askQty": 3125, "askPrice": 27.1, "underlyingValue": 213}}, {"strikePrice": 240, "expiryDate": "31-Jul-2025", "CE": {"strikePrice": 240, "expiryDate": "31-Jul-2025", "underlying": "NYKAA", "identifier": "OPTSTKNYKAA31-07-2025CE240.00", "openInterest": 65, "changeinOpenInterest": 8, "pchangeinOpenInterest": 14.035087719298245, "totalTradedVolume": 171, "impliedVolatility": 33.37, "lastPrice": 0.7, "change": 0.44999999999999996, "pChange": 179.99999999999997, "totalBuyQuantity": 693750, "totalSellQuantity": 393750, "bidQty": 25000, "bidprice": 0.65, "askQty": 9375, "askPrice": 0.7, "underlyingValue": 213}, "PE": {"strikePrice": 240, "expiryDate": "31-Jul-2025", "underlying": "NYKAA", "identifier": "OPTSTKNYKAA31-07-2025PE240.00", "openInterest": 6, "changeinOpenInterest": 0, "pchangeinOpenInterest": 0, "totalTradedVolume": 0, "impliedVolatility": 0, "lastPrice": 0, "change": 0, "pChange": 0, "totalBuyQuantity": 234375, "totalSellQuantity": 240625, "bidQty": 3125, "bidprice": 27.5, "askQty": 3125, "askPrice": 29.05, "underlyingValue": 213}}, {"strikePrice": 242.5, "expiryDate": "31-Jul-2025", "PE": {"strikePrice": 242.5, "expiryDate": "31-Jul-2025", "underlying": "NYKAA", "identifier": "OPTSTKNYKAA31-07-2025PE242.50", "openInterest": 0, "changeinOpenInterest": 0, "pchangeinOpenInterest": 0, "totalTradedVolume": 0, "impliedVolatility": 0, "lastPrice": 0, "change": 0, "pChange": 0, "totalBuyQuantity": 109375, "totalSellQuantity": 109375, "bidQty": 3125, "bidprice": 29.65, "askQty": 3125, "askPrice": 31.8, "underlyingValue": 213}, "CE": {"strikePrice": 242.5, "expiryDate": "31-Jul-2025", "underlying": "NYKAA", "identifier": "OPTSTKNYKAA31-07-2025CE242.50", "openInterest": 0, "changeinOpenInterest": 0, "pchangeinOpenInterest": 0, "totalTradedVolume": 0, "impliedVolatility": 0, "lastPrice": 0, "change": 0, "pChange": 0, "totalBuyQuantity": 128125, "totalSellQuantity": 225000, "bidQty": 3125, "bidprice": 0.35, "askQty": 3125, "askPrice": 0.8, "underlyingValue": 213}}], "CE": {"totOI": 4943, "totVol": 17629}, "PE": {"totOI": 3537, "totVol": 5905}}}