{"records": {"expiryDates": ["31-Jul-2025", "28-Aug-2025", "30-Sep-2025"], "data": [{"strikePrice": 1600, "expiryDate": "31-Jul-2025", "CE": {"strikePrice": 1600, "expiryDate": "31-Jul-2025", "underlying": "BHARTIARTL", "identifier": "OPTSTKBHARTIARTL31-07-2025CE1600.00", "openInterest": 606, "changeinOpenInterest": 0, "pchangeinOpenInterest": 0, "totalTradedVolume": 0, "impliedVolatility": 0, "lastPrice": 0, "change": 0, "pChange": 0, "totalBuyQuantity": 29450, "totalSellQuantity": 29450, "bidQty": 1425, "bidprice": 415, "askQty": 1425, "askPrice": 426.7, "underlyingValue": 2033}, "PE": {"strikePrice": 1600, "expiryDate": "31-Jul-2025", "underlying": "BHARTIARTL", "identifier": "OPTSTKBHARTIARTL31-07-2025PE1600.00", "openInterest": 227, "changeinOpenInterest": 0, "pchangeinOpenInterest": 0, "totalTradedVolume": 1, "impliedVolatility": 0, "lastPrice": 0.2, "change": -0.04999999999999999, "pChange": -19.999999999999996, "totalBuyQuantity": 72675, "totalSellQuantity": 29925, "bidQty": 3800, "bidprice": 0.2, "askQty": 1900, "askPrice": 0.3, "underlyingValue": 2033}}, {"strikePrice": 1600, "expiryDate": "28-Aug-2025", "CE": {"strikePrice": 1600, "expiryDate": "28-Aug-2025", "underlying": "BHARTIARTL", "identifier": "OPTSTKBHARTIARTL28-08-2025CE1600.00", "openInterest": 1, "changeinOpenInterest": 0, "pchangeinOpenInterest": 0, "totalTradedVolume": 0, "impliedVolatility": 0, "lastPrice": 0, "change": 0, "pChange": 0, "totalBuyQuantity": 950, "totalSellQuantity": 3325, "bidQty": 950, "bidprice": 423.55, "askQty": 2375, "askPrice": 453.2, "underlyingValue": 2033}, "PE": {"strikePrice": 1600, "expiryDate": "28-Aug-2025", "underlying": "BHARTIARTL", "identifier": "OPTSTKBHARTIARTL28-08-2025PE1600.00", "openInterest": 41, "changeinOpenInterest": 0, "pchangeinOpenInterest": 0, "totalTradedVolume": 1, "impliedVolatility": 34.11, "lastPrice": 2, "change": -0.25, "pChange": -11.11111111111111, "totalBuyQuantity": 32775, "totalSellQuantity": 2375, "bidQty": 475, "bidprice": 1.6, "askQty": 475, "askPrice": 1.9, "underlyingValue": 2033}}, {"strikePrice": 1640, "expiryDate": "31-Jul-2025", "PE": {"strikePrice": 1640, "expiryDate": "31-Jul-2025", "underlying": "BHARTIARTL", "identifier": "OPTSTKBHARTIARTL31-07-2025PE1640.00", "openInterest": 19, "changeinOpenInterest": 0, "pchangeinOpenInterest": 0, "totalTradedVolume": 0, "impliedVolatility": 0, "lastPrice": 0, "change": 0, "pChange": 0, "totalBuyQuantity": 63175, "totalSellQuantity": 31350, "bidQty": 3800, "bidprice": 0.2, "askQty": 5225, "askPrice": 0.5, "underlyingValue": 2033}}, {"strikePrice": 1680, "expiryDate": "31-Jul-2025", "PE": {"strikePrice": 1680, "expiryDate": "31-Jul-2025", "underlying": "BHARTIARTL", "identifier": "OPTSTKBHARTIARTL31-07-2025PE1680.00", "openInterest": 43, "changeinOpenInterest": 3, "pchangeinOpenInterest": 7.5, "totalTradedVolume": 7, "impliedVolatility": 31.51, "lastPrice": 0.3, "change": 0.04999999999999999, "pChange": 19.999999999999996, "totalBuyQuantity": 175750, "totalSellQuantity": 52725, "bidQty": 101175, "bidprice": 0.25, "askQty": 475, "askPrice": 0.3, "underlyingValue": 2033}, "CE": {"strikePrice": 1680, "expiryDate": "31-Jul-2025", "underlying": "BHARTIARTL", "identifier": "OPTSTKBHARTIARTL31-07-2025CE1680.00", "openInterest": 1, "changeinOpenInterest": 0, "pchangeinOpenInterest": 0, "totalTradedVolume": 0, "impliedVolatility": 0, "lastPrice": 0, "change": 0, "pChange": 0, "totalBuyQuantity": 29450, "totalSellQuantity": 22325, "bidQty": 1425, "bidprice": 335.55, "askQty": 1425, "askPrice": 354.1, "underlyingValue": 2033}}, {"strikePrice": 1700, "expiryDate": "31-Jul-2025", "CE": {"strikePrice": 1700, "expiryDate": "31-Jul-2025", "underlying": "BHARTIARTL", "identifier": "OPTSTKBHARTIARTL31-07-2025CE1700.00", "openInterest": 35, "changeinOpenInterest": 0, "pchangeinOpenInterest": 0, "totalTradedVolume": 0, "impliedVolatility": 0, "lastPrice": 0, "change": 0, "pChange": 0, "totalBuyQuantity": 31350, "totalSellQuantity": 26600, "bidQty": 3325, "bidprice": 316.7, "askQty": 3325, "askPrice": 334.1, "underlyingValue": 2033}, "PE": {"strikePrice": 1700, "expiryDate": "31-Jul-2025", "underlying": "BHARTIARTL", "identifier": "OPTSTKBHARTIARTL31-07-2025PE1700.00", "openInterest": 203, "changeinOpenInterest": -4, "pchangeinOpenInterest": -1.932367149758454, "totalTradedVolume": 25, "impliedVolatility": 31.72, "lastPrice": 0.5, "change": 0.04999999999999999, "pChange": 11.111111111111107, "totalBuyQuantity": 161025, "totalSellQuantity": 89300, "bidQty": 950, "bidprice": 0.4, "askQty": 4750, "askPrice": 0.5, "underlyingValue": 2033}}, {"strikePrice": 1720, "expiryDate": "31-Jul-2025", "PE": {"strikePrice": 1720, "expiryDate": "31-Jul-2025", "underlying": "BHARTIARTL", "identifier": "OPTSTKBHARTIARTL31-07-2025PE1720.00", "openInterest": 158, "changeinOpenInterest": 3, "pchangeinOpenInterest": 1.935483870967742, "totalTradedVolume": 8, "impliedVolatility": 0, "lastPrice": 0.5, "change": 0, "pChange": 0, "totalBuyQuantity": 113525, "totalSellQuantity": 38000, "bidQty": 2375, "bidprice": 0.35, "askQty": 475, "askPrice": 0.45, "underlyingValue": 2033}, "CE": {"strikePrice": 1720, "expiryDate": "31-Jul-2025", "underlying": "BHARTIARTL", "identifier": "OPTSTKBHARTIARTL31-07-2025CE1720.00", "openInterest": 2, "changeinOpenInterest": 0, "pchangeinOpenInterest": 0, "totalTradedVolume": 0, "impliedVolatility": 0, "lastPrice": 0, "change": 0, "pChange": 0, "totalBuyQuantity": 29450, "totalSellQuantity": 15200, "bidQty": 1425, "bidprice": 294.9, "askQty": 1425, "askPrice": 314.55, "underlyingValue": 2033}}, {"strikePrice": 1720, "expiryDate": "28-Aug-2025", "PE": {"strikePrice": 1720, "expiryDate": "28-Aug-2025", "underlying": "BHARTIARTL", "identifier": "OPTSTKBHARTIARTL28-08-2025PE1720.00", "openInterest": 0, "changeinOpenInterest": 0, "pchangeinOpenInterest": 0, "totalTradedVolume": 0, "impliedVolatility": 0, "lastPrice": 0, "change": 0, "pChange": 0, "totalBuyQuantity": 20900, "totalSellQuantity": 0, "bidQty": 6650, "bidprice": 0.6, "askQty": 0, "askPrice": 0, "underlyingValue": 2033}, "CE": {"strikePrice": 1720, "expiryDate": "28-Aug-2025", "underlying": "BHARTIARTL", "identifier": "OPTSTKBHARTIARTL28-08-2025CE1720.00", "openInterest": 0, "changeinOpenInterest": 0, "pchangeinOpenInterest": 0, "totalTradedVolume": 0, "impliedVolatility": 0, "lastPrice": 0, "change": 0, "pChange": 0, "totalBuyQuantity": 2375, "totalSellQuantity": 0, "bidQty": 2375, "bidprice": 249.85, "askQty": 0, "askPrice": 0, "underlyingValue": 2033}}, {"strikePrice": 1740, "expiryDate": "31-Jul-2025", "PE": {"strikePrice": 1740, "expiryDate": "31-Jul-2025", "underlying": "BHARTIARTL", "identifier": "OPTSTKBHARTIARTL31-07-2025PE1740.00", "openInterest": 197, "changeinOpenInterest": -1, "pchangeinOpenInterest": -0.5050505050505051, "totalTradedVolume": 36, "impliedVolatility": 0, "lastPrice": 0.4, "change": -0.09999999999999998, "pChange": -19.999999999999996, "totalBuyQuantity": 121600, "totalSellQuantity": 43225, "bidQty": 15675, "bidprice": 0.35, "askQty": 3800, "askPrice": 0.45, "underlyingValue": 2033}}, {"strikePrice": 1760, "expiryDate": "31-Jul-2025", "PE": {"strikePrice": 1760, "expiryDate": "31-Jul-2025", "underlying": "BHARTIARTL", "identifier": "OPTSTKBHARTIARTL31-07-2025PE1760.00", "openInterest": 110, "changeinOpenInterest": 8, "pchangeinOpenInterest": 7.8431372549019605, "totalTradedVolume": 12, "impliedVolatility": 26.42, "lastPrice": 0.5, "change": -0.25, "pChange": -33.33333333333333, "totalBuyQuantity": 161975, "totalSellQuantity": 53675, "bidQty": 475, "bidprice": 0.5, "askQty": 475, "askPrice": 0.6, "underlyingValue": 2033}, "CE": {"strikePrice": 1760, "expiryDate": "31-Jul-2025", "underlying": "BHARTIARTL", "identifier": "OPTSTKBHARTIARTL31-07-2025CE1760.00", "openInterest": 1, "changeinOpenInterest": 0, "pchangeinOpenInterest": 0, "totalTradedVolume": 0, "impliedVolatility": 0, "lastPrice": 0, "change": 0, "pChange": 0, "totalBuyQuantity": 30400, "totalSellQuantity": 10925, "bidQty": 1425, "bidprice": 256.3, "askQty": 1425, "askPrice": 274.95, "underlyingValue": 2033}}, {"strikePrice": 1760, "expiryDate": "28-Aug-2025", "CE": {"strikePrice": 1760, "expiryDate": "28-Aug-2025", "underlying": "BHARTIARTL", "identifier": "OPTSTKBHARTIARTL28-08-2025CE1760.00", "openInterest": 0, "changeinOpenInterest": 0, "pchangeinOpenInterest": 0, "totalTradedVolume": 0, "impliedVolatility": 0, "lastPrice": 0, "change": 0, "pChange": 0, "totalBuyQuantity": 5225, "totalSellQuantity": 9025, "bidQty": 475, "bidprice": 267.95, "askQty": 2375, "askPrice": 300.8, "underlyingValue": 2033}, "PE": {"strikePrice": 1760, "expiryDate": "28-Aug-2025", "underlying": "BHARTIARTL", "identifier": "OPTSTKBHARTIARTL28-08-2025PE1760.00", "openInterest": 0, "changeinOpenInterest": 0, "pchangeinOpenInterest": 0, "totalTradedVolume": 0, "impliedVolatility": 0, "lastPrice": 0, "change": 0, "pChange": 0, "totalBuyQuantity": 30875, "totalSellQuantity": 6650, "bidQty": 6650, "bidprice": 1.1, "askQty": 1900, "askPrice": 12.85, "underlyingValue": 2033}}, {"strikePrice": 1760, "expiryDate": "30-Sep-2025", "PE": {"strikePrice": 1760, "expiryDate": "30-Sep-2025", "underlying": "BHARTIARTL", "identifier": "OPTSTKBHARTIARTL30-09-2025PE1760.00", "openInterest": 0, "changeinOpenInterest": 0, "pchangeinOpenInterest": 0, "totalTradedVolume": 0, "impliedVolatility": 0, "lastPrice": 0, "change": 0, "pChange": 0, "totalBuyQuantity": 21375, "totalSellQuantity": 475, "bidQty": 6650, "bidprice": 2.1, "askQty": 475, "askPrice": 15, "underlyingValue": 2033}}, {"strikePrice": 1780, "expiryDate": "31-Jul-2025", "PE": {"strikePrice": 1780, "expiryDate": "31-Jul-2025", "underlying": "BHARTIARTL", "identifier": "OPTSTKBHARTIARTL31-07-2025PE1780.00", "openInterest": 363, "changeinOpenInterest": 0, "pchangeinOpenInterest": 0, "totalTradedVolume": 9, "impliedVolatility": 24.99, "lastPrice": 0.55, "change": -0.25, "pChange": -31.25, "totalBuyQuantity": 169575, "totalSellQuantity": 25650, "bidQty": 475, "bidprice": 0.55, "askQty": 475, "askPrice": 0.7, "underlyingValue": 2033}}, {"strikePrice": 1800, "expiryDate": "31-Jul-2025", "PE": {"strikePrice": 1800, "expiryDate": "31-Jul-2025", "underlying": "BHARTIARTL", "identifier": "OPTSTKBHARTIARTL31-07-2025PE1800.00", "openInterest": 1311, "changeinOpenInterest": -21, "pchangeinOpenInterest": -1.5765765765765767, "totalTradedVolume": 122, "impliedVolatility": 24.51, "lastPrice": 0.8, "change": -0.1499999999999999, "pChange": -15.789473684210517, "totalBuyQuantity": 264100, "totalSellQuantity": 81700, "bidQty": 7125, "bidprice": 0.75, "askQty": 950, "askPrice": 0.8, "underlyingValue": 2033}, "CE": {"strikePrice": 1800, "expiryDate": "31-Jul-2025", "underlying": "BHARTIARTL", "identifier": "OPTSTKBHARTIARTL31-07-2025CE1800.00", "openInterest": 572, "changeinOpenInterest": 0, "pchangeinOpenInterest": 0, "totalTradedVolume": 0, "impliedVolatility": 0, "lastPrice": 0, "change": 0, "pChange": 0, "totalBuyQuantity": 54150, "totalSellQuantity": 60800, "bidQty": 950, "bidprice": 221.5, "askQty": 3325, "askPrice": 230.45, "underlyingValue": 2033}}, {"strikePrice": 1800, "expiryDate": "28-Aug-2025", "CE": {"strikePrice": 1800, "expiryDate": "28-Aug-2025", "underlying": "BHARTIARTL", "identifier": "OPTSTKBHARTIARTL28-08-2025CE1800.00", "openInterest": 20, "changeinOpenInterest": 0, "pchangeinOpenInterest": 0, "totalTradedVolume": 0, "impliedVolatility": 0, "lastPrice": 0, "change": 0, "pChange": 0, "totalBuyQuantity": 7125, "totalSellQuantity": 7600, "bidQty": 950, "bidprice": 231.8, "askQty": 950, "askPrice": 245.75, "underlyingValue": 2033}, "PE": {"strikePrice": 1800, "expiryDate": "28-Aug-2025", "underlying": "BHARTIARTL", "identifier": "OPTSTKBHARTIARTL28-08-2025PE1800.00", "openInterest": 75, "changeinOpenInterest": 3, "pchangeinOpenInterest": 4.166666666666667, "totalTradedVolume": 24, "impliedVolatility": 23.95, "lastPrice": 4.8, "change": -0.2999999999999998, "pChange": -5.8823529411764675, "totalBuyQuantity": 31825, "totalSellQuantity": 26600, "bidQty": 475, "bidprice": 4.5, "askQty": 475, "askPrice": 4.85, "underlyingValue": 2033}}, {"strikePrice": 1800, "expiryDate": "30-Sep-2025", "PE": {"strikePrice": 1800, "expiryDate": "30-Sep-2025", "underlying": "BHARTIARTL", "identifier": "OPTSTKBHARTIARTL30-09-2025PE1800.00", "openInterest": 0, "changeinOpenInterest": 0, "pchangeinOpenInterest": 0, "totalTradedVolume": 0, "impliedVolatility": 0, "lastPrice": 0, "change": 0, "pChange": 0, "totalBuyQuantity": 14250, "totalSellQuantity": 0, "bidQty": 14250, "bidprice": 0.05, "askQty": 0, "askPrice": 0, "underlyingValue": 2033}}, {"strikePrice": 1820, "expiryDate": "31-Jul-2025", "PE": {"strikePrice": 1820, "expiryDate": "31-Jul-2025", "underlying": "BHARTIARTL", "identifier": "OPTSTKBHARTIARTL31-07-2025PE1820.00", "openInterest": 725, "changeinOpenInterest": -9, "pchangeinOpenInterest": -1.2261580381471389, "totalTradedVolume": 29, "impliedVolatility": 23.48, "lastPrice": 1, "change": -0.30000000000000004, "pChange": -23.076923076923077, "totalBuyQuantity": 334875, "totalSellQuantity": 63175, "bidQty": 475, "bidprice": 0.95, "askQty": 475, "askPrice": 1.1, "underlyingValue": 2033}, "CE": {"strikePrice": 1820, "expiryDate": "31-Jul-2025", "underlying": "BHARTIARTL", "identifier": "OPTSTKBHARTIARTL31-07-2025CE1820.00", "openInterest": 52, "changeinOpenInterest": 0, "pchangeinOpenInterest": 0, "totalTradedVolume": 0, "impliedVolatility": 0, "lastPrice": 0, "change": 0, "pChange": 0, "totalBuyQuantity": 32300, "totalSellQuantity": 27550, "bidQty": 3325, "bidprice": 197.45, "askQty": 3325, "askPrice": 215.6, "underlyingValue": 2033}}, {"strikePrice": 1820, "expiryDate": "28-Aug-2025", "CE": {"strikePrice": 1820, "expiryDate": "28-Aug-2025", "underlying": "BHARTIARTL", "identifier": "OPTSTKBHARTIARTL28-08-2025CE1820.00", "openInterest": 0, "changeinOpenInterest": 0, "pchangeinOpenInterest": 0, "totalTradedVolume": 0, "impliedVolatility": 0, "lastPrice": 0, "change": 0, "pChange": 0, "totalBuyQuantity": 5225, "totalSellQuantity": 9025, "bidQty": 475, "bidprice": 211, "askQty": 2375, "askPrice": 245.55, "underlyingValue": 2033}, "PE": {"strikePrice": 1820, "expiryDate": "28-Aug-2025", "underlying": "BHARTIARTL", "identifier": "OPTSTKBHARTIARTL28-08-2025PE1820.00", "openInterest": 0, "changeinOpenInterest": 0, "pchangeinOpenInterest": 0, "totalTradedVolume": 0, "impliedVolatility": 0, "lastPrice": 0, "change": 0, "pChange": 0, "totalBuyQuantity": 20900, "totalSellQuantity": 6650, "bidQty": 1900, "bidprice": 2.5, "askQty": 1900, "askPrice": 17.1, "underlyingValue": 2033}}, {"strikePrice": 1840, "expiryDate": "31-Jul-2025", "PE": {"strikePrice": 1840, "expiryDate": "31-Jul-2025", "underlying": "BHARTIARTL", "identifier": "OPTSTKBHARTIARTL31-07-2025PE1840.00", "openInterest": 546, "changeinOpenInterest": -28, "pchangeinOpenInterest": -4.878048780487805, "totalTradedVolume": 105, "impliedVolatility": 23.28, "lastPrice": 1.55, "change": -0.30000000000000004, "pChange": -16.216216216216218, "totalBuyQuantity": 271700, "totalSellQuantity": 61750, "bidQty": 475, "bidprice": 1.4, "askQty": 1425, "askPrice": 1.55, "underlyingValue": 2033}, "CE": {"strikePrice": 1840, "expiryDate": "31-Jul-2025", "underlying": "BHARTIARTL", "identifier": "OPTSTKBHARTIARTL31-07-2025CE1840.00", "openInterest": 179, "changeinOpenInterest": 0, "pchangeinOpenInterest": 0, "totalTradedVolume": 1, "impliedVolatility": 0, "lastPrice": 185, "change": 17.55000000000001, "pChange": 10.480740519558085, "totalBuyQuantity": 35150, "totalSellQuantity": 33250, "bidQty": 475, "bidprice": 184.35, "askQty": 6650, "askPrice": 190.05, "underlyingValue": 2033}}, {"strikePrice": 1840, "expiryDate": "28-Aug-2025", "PE": {"strikePrice": 1840, "expiryDate": "28-Aug-2025", "underlying": "BHARTIARTL", "identifier": "OPTSTKBHARTIARTL28-08-2025PE1840.00", "openInterest": 0, "changeinOpenInterest": 0, "pchangeinOpenInterest": 0, "totalTradedVolume": 0, "impliedVolatility": 0, "lastPrice": 0, "change": 0, "pChange": 0, "totalBuyQuantity": 20900, "totalSellQuantity": 6650, "bidQty": 1900, "bidprice": 2, "askQty": 1900, "askPrice": 17.65, "underlyingValue": 2033}, "CE": {"strikePrice": 1840, "expiryDate": "28-Aug-2025", "underlying": "BHARTIARTL", "identifier": "OPTSTKBHARTIARTL28-08-2025CE1840.00", "openInterest": 0, "changeinOpenInterest": 0, "pchangeinOpenInterest": 0, "totalTradedVolume": 0, "impliedVolatility": 0, "lastPrice": 0, "change": 0, "pChange": 0, "totalBuyQuantity": 5225, "totalSellQuantity": 9025, "bidQty": 475, "bidprice": 189.75, "askQty": 2375, "askPrice": 226.5, "underlyingValue": 2033}}, {"strikePrice": 1860, "expiryDate": "31-Jul-2025", "PE": {"strikePrice": 1860, "expiryDate": "31-Jul-2025", "underlying": "BHARTIARTL", "identifier": "OPTSTKBHARTIARTL31-07-2025PE1860.00", "openInterest": 1220, "changeinOpenInterest": 1, "pchangeinOpenInterest": 0.08203445447087777, "totalTradedVolume": 188, "impliedVolatility": 0, "lastPrice": 2.1, "change": -0.5, "pChange": -19.23076923076923, "totalBuyQuantity": 280725, "totalSellQuantity": 73625, "bidQty": 1425, "bidprice": 1.95, "askQty": 1425, "askPrice": 2.15, "underlyingValue": 2033}, "CE": {"strikePrice": 1860, "expiryDate": "31-Jul-2025", "underlying": "BHARTIARTL", "identifier": "OPTSTKBHARTIARTL31-07-2025CE1860.00", "openInterest": 392, "changeinOpenInterest": -20, "pchangeinOpenInterest": -4.854368932038835, "totalTradedVolume": 25, "impliedVolatility": 0, "lastPrice": 163.45, "change": 0.9499999999999886, "pChange": 0.5846153846153777, "totalBuyQuantity": 40850, "totalSellQuantity": 38475, "bidQty": 475, "bidprice": 165.05, "askQty": 475, "askPrice": 169.2, "underlyingValue": 2033}}, {"strikePrice": 1860, "expiryDate": "28-Aug-2025", "PE": {"strikePrice": 1860, "expiryDate": "28-Aug-2025", "underlying": "BHARTIARTL", "identifier": "OPTSTKBHARTIARTL28-08-2025PE1860.00", "openInterest": 28, "changeinOpenInterest": 0, "pchangeinOpenInterest": 0, "totalTradedVolume": 0, "impliedVolatility": 0, "lastPrice": 0, "change": 0, "pChange": 0, "totalBuyQuantity": 30400, "totalSellQuantity": 8075, "bidQty": 475, "bidprice": 8, "askQty": 475, "askPrice": 8.65, "underlyingValue": 2033}, "CE": {"strikePrice": 1860, "expiryDate": "28-Aug-2025", "underlying": "BHARTIARTL", "identifier": "OPTSTKBHARTIARTL28-08-2025CE1860.00", "openInterest": 0, "changeinOpenInterest": 0, "pchangeinOpenInterest": 0, "totalTradedVolume": 0, "impliedVolatility": 0, "lastPrice": 0, "change": 0, "pChange": 0, "totalBuyQuantity": 5225, "totalSellQuantity": 9025, "bidQty": 475, "bidprice": 175.55, "askQty": 2375, "askPrice": 196.7, "underlyingValue": 2033}}, {"strikePrice": 1880, "expiryDate": "31-Jul-2025", "CE": {"strikePrice": 1880, "expiryDate": "31-Jul-2025", "underlying": "BHARTIARTL", "identifier": "OPTSTKBHARTIARTL31-07-2025CE1880.00", "openInterest": 155, "changeinOpenInterest": 0, "pchangeinOpenInterest": 0, "totalTradedVolume": 0, "impliedVolatility": 0, "lastPrice": 0, "change": 0, "pChange": 0, "totalBuyQuantity": 36100, "totalSellQuantity": 36575, "bidQty": 1900, "bidprice": 143.9, "askQty": 950, "askPrice": 152.4, "underlyingValue": 2033}, "PE": {"strikePrice": 1880, "expiryDate": "31-Jul-2025", "underlying": "BHARTIARTL", "identifier": "OPTSTKBHARTIARTL31-07-2025PE1880.00", "openInterest": 622, "changeinOpenInterest": -13, "pchangeinOpenInterest": -2.047244094488189, "totalTradedVolume": 138, "impliedVolatility": 0, "lastPrice": 2.8, "change": -0.7000000000000002, "pChange": -20.000000000000004, "totalBuyQuantity": 282625, "totalSellQuantity": 74575, "bidQty": 475, "bidprice": 2.65, "askQty": 475, "askPrice": 2.9, "underlyingValue": 2033}}, {"strikePrice": 1880, "expiryDate": "28-Aug-2025", "PE": {"strikePrice": 1880, "expiryDate": "28-Aug-2025", "underlying": "BHARTIARTL", "identifier": "OPTSTKBHARTIARTL28-08-2025PE1880.00", "openInterest": 0, "changeinOpenInterest": 0, "pchangeinOpenInterest": 0, "totalTradedVolume": 0, "impliedVolatility": 0, "lastPrice": 0, "change": 0, "pChange": 0, "totalBuyQuantity": 1900, "totalSellQuantity": 6650, "bidQty": 1900, "bidprice": 2, "askQty": 1900, "askPrice": 22.6, "underlyingValue": 2033}, "CE": {"strikePrice": 1880, "expiryDate": "28-Aug-2025", "underlying": "BHARTIARTL", "identifier": "OPTSTKBHARTIARTL28-08-2025CE1880.00", "openInterest": 0, "changeinOpenInterest": 0, "pchangeinOpenInterest": 0, "totalTradedVolume": 0, "impliedVolatility": 0, "lastPrice": 0, "change": 0, "pChange": 0, "totalBuyQuantity": 5225, "totalSellQuantity": 9025, "bidQty": 475, "bidprice": 151.95, "askQty": 2375, "askPrice": 191.9, "underlyingValue": 2033}}, {"strikePrice": 1900, "expiryDate": "31-Jul-2025", "PE": {"strikePrice": 1900, "expiryDate": "31-Jul-2025", "underlying": "BHARTIARTL", "identifier": "OPTSTKBHARTIARTL31-07-2025PE1900.00", "openInterest": 2241, "changeinOpenInterest": -44, "pchangeinOpenInterest": -1.925601750547046, "totalTradedVolume": 710, "impliedVolatility": 21.12, "lastPrice": 3.85, "change": -0.9999999999999996, "pChange": -20.618556701030922, "totalBuyQuantity": 338675, "totalSellQuantity": 123500, "bidQty": 475, "bidprice": 3.85, "askQty": 950, "askPrice": 3.9, "underlyingValue": 2033}, "CE": {"strikePrice": 1900, "expiryDate": "31-Jul-2025", "underlying": "BHARTIARTL", "identifier": "OPTSTKBHARTIARTL31-07-2025CE1900.00", "openInterest": 484, "changeinOpenInterest": -24, "pchangeinOpenInterest": -4.724409448818897, "totalTradedVolume": 89, "impliedVolatility": 0, "lastPrice": 128.55, "change": 2.1500000000000057, "pChange": 1.7009493670886122, "totalBuyQuantity": 38000, "totalSellQuantity": 32300, "bidQty": 475, "bidprice": 127.2, "askQty": 475, "askPrice": 129.85, "underlyingValue": 2033}}, {"strikePrice": 1900, "expiryDate": "28-Aug-2025", "PE": {"strikePrice": 1900, "expiryDate": "28-Aug-2025", "underlying": "BHARTIARTL", "identifier": "OPTSTKBHARTIARTL28-08-2025PE1900.00", "openInterest": 106, "changeinOpenInterest": 18, "pchangeinOpenInterest": 20.454545454545453, "totalTradedVolume": 39, "impliedVolatility": 0, "lastPrice": 13.15, "change": -0.7999999999999989, "pChange": -5.734767025089598, "totalBuyQuantity": 39425, "totalSellQuantity": 17100, "bidQty": 475, "bidprice": 12.7, "askQty": 475, "askPrice": 13.2, "underlyingValue": 2033}, "CE": {"strikePrice": 1900, "expiryDate": "28-Aug-2025", "underlying": "BHARTIARTL", "identifier": "OPTSTKBHARTIARTL28-08-2025CE1900.00", "openInterest": 7, "changeinOpenInterest": 3, "pchangeinOpenInterest": 75, "totalTradedVolume": 6, "impliedVolatility": 0, "lastPrice": 144.65, "change": -13.299999999999983, "pChange": -8.420386198163966, "totalBuyQuantity": 6650, "totalSellQuantity": 8075, "bidQty": 1425, "bidprice": 142.4, "askQty": 1425, "askPrice": 156.85, "underlyingValue": 2033}}, {"strikePrice": 1920, "expiryDate": "31-Jul-2025", "PE": {"strikePrice": 1920, "expiryDate": "31-Jul-2025", "underlying": "BHARTIARTL", "identifier": "OPTSTKBHARTIARTL31-07-2025PE1920.00", "openInterest": 816, "changeinOpenInterest": -37, "pchangeinOpenInterest": -4.337631887456038, "totalTradedVolume": 374, "impliedVolatility": 20.66, "lastPrice": 5.45, "change": -1, "pChange": -15.503875968992247, "totalBuyQuantity": 334875, "totalSellQuantity": 73150, "bidQty": 1425, "bidprice": 5.15, "askQty": 950, "askPrice": 5.35, "underlyingValue": 2033}, "CE": {"strikePrice": 1920, "expiryDate": "31-Jul-2025", "underlying": "BHARTIARTL", "identifier": "OPTSTKBHARTIARTL31-07-2025CE1920.00", "openInterest": 327, "changeinOpenInterest": -1, "pchangeinOpenInterest": -0.3048780487804878, "totalTradedVolume": 3, "impliedVolatility": 0, "lastPrice": 97.95, "change": -10.950000000000003, "pChange": -10.055096418732784, "totalBuyQuantity": 43225, "totalSellQuantity": 43225, "bidQty": 475, "bidprice": 108.55, "askQty": 950, "askPrice": 112.25, "underlyingValue": 2033}}, {"strikePrice": 1920, "expiryDate": "28-Aug-2025", "PE": {"strikePrice": 1920, "expiryDate": "28-Aug-2025", "underlying": "BHARTIARTL", "identifier": "OPTSTKBHARTIARTL28-08-2025PE1920.00", "openInterest": 0, "changeinOpenInterest": 0, "pchangeinOpenInterest": 0, "totalTradedVolume": 0, "impliedVolatility": 0, "lastPrice": 0, "change": 0, "pChange": 0, "totalBuyQuantity": 0, "totalSellQuantity": 6650, "bidQty": 0, "bidprice": 0, "askQty": 1900, "askPrice": 30.7, "underlyingValue": 2033}, "CE": {"strikePrice": 1920, "expiryDate": "28-Aug-2025", "underlying": "BHARTIARTL", "identifier": "OPTSTKBHARTIARTL28-08-2025CE1920.00", "openInterest": 0, "changeinOpenInterest": 0, "pchangeinOpenInterest": 0, "totalTradedVolume": 0, "impliedVolatility": 0, "lastPrice": 0, "change": 0, "pChange": 0, "totalBuyQuantity": 5225, "totalSellQuantity": 9025, "bidQty": 475, "bidprice": 122.35, "askQty": 2375, "askPrice": 155.95, "underlyingValue": 2033}}, {"strikePrice": 1940, "expiryDate": "31-Jul-2025", "CE": {"strikePrice": 1940, "expiryDate": "31-Jul-2025", "underlying": "BHARTIARTL", "identifier": "OPTSTKBHARTIARTL31-07-2025CE1940.00", "openInterest": 393, "changeinOpenInterest": -2, "pchangeinOpenInterest": -0.5063291139240507, "totalTradedVolume": 9, "impliedVolatility": 0, "lastPrice": 84.9, "change": -7.25, "pChange": -7.867607162235485, "totalBuyQuantity": 31825, "totalSellQuantity": 34675, "bidQty": 950, "bidprice": 90.15, "askQty": 950, "askPrice": 93.05, "underlyingValue": 2033}, "PE": {"strikePrice": 1940, "expiryDate": "31-Jul-2025", "underlying": "BHARTIARTL", "identifier": "OPTSTKBHARTIARTL31-07-2025PE1940.00", "openInterest": 1145, "changeinOpenInterest": -211, "pchangeinOpenInterest": -15.56047197640118, "totalTradedVolume": 1139, "impliedVolatility": 19.91, "lastPrice": 7.3, "change": -1.4500000000000002, "pChange": -16.571428571428573, "totalBuyQuantity": 308275, "totalSellQuantity": 76950, "bidQty": 950, "bidprice": 7.2, "askQty": 950, "askPrice": 7.4, "underlyingValue": 2033}}, {"strikePrice": 1940, "expiryDate": "28-Aug-2025", "PE": {"strikePrice": 1940, "expiryDate": "28-Aug-2025", "underlying": "BHARTIARTL", "identifier": "OPTSTKBHARTIARTL28-08-2025PE1940.00", "openInterest": 10, "changeinOpenInterest": 6, "pchangeinOpenInterest": 150, "totalTradedVolume": 12, "impliedVolatility": 21.34, "lastPrice": 20.2, "change": -5.199999999999999, "pChange": -20.47244094488189, "totalBuyQuantity": 13300, "totalSellQuantity": 8075, "bidQty": 475, "bidprice": 19.35, "askQty": 475, "askPrice": 20.4, "underlyingValue": 2033}, "CE": {"strikePrice": 1940, "expiryDate": "28-Aug-2025", "underlying": "BHARTIARTL", "identifier": "OPTSTKBHARTIARTL28-08-2025CE1940.00", "openInterest": 0, "changeinOpenInterest": 0, "pchangeinOpenInterest": 0, "totalTradedVolume": 0, "impliedVolatility": 0, "lastPrice": 0, "change": 0, "pChange": 0, "totalBuyQuantity": 5225, "totalSellQuantity": 7125, "bidQty": 475, "bidprice": 111, "askQty": 475, "askPrice": 121, "underlyingValue": 2033}}, {"strikePrice": 1960, "expiryDate": "31-Jul-2025", "CE": {"strikePrice": 1960, "expiryDate": "31-Jul-2025", "underlying": "BHARTIARTL", "identifier": "OPTSTKBHARTIARTL31-07-2025CE1960.00", "openInterest": 479, "changeinOpenInterest": -12, "pchangeinOpenInterest": -2.443991853360489, "totalTradedVolume": 91, "impliedVolatility": 0, "lastPrice": 74.3, "change": 0.3999999999999915, "pChange": 0.5412719891745487, "totalBuyQuantity": 39425, "totalSellQuantity": 39425, "bidQty": 1425, "bidprice": 75, "askQty": 950, "askPrice": 76, "underlyingValue": 2033}, "PE": {"strikePrice": 1960, "expiryDate": "31-Jul-2025", "underlying": "BHARTIARTL", "identifier": "OPTSTKBHARTIARTL31-07-2025PE1960.00", "openInterest": 1133, "changeinOpenInterest": -14, "pchangeinOpenInterest": -1.2205754141238012, "totalTradedVolume": 989, "impliedVolatility": 19.67, "lastPrice": 10.35, "change": -1.75, "pChange": -14.462809917355374, "totalBuyQuantity": 285950, "totalSellQuantity": 84550, "bidQty": 475, "bidprice": 10.15, "askQty": 1425, "askPrice": 10.35, "underlyingValue": 2033}}, {"strikePrice": 1960, "expiryDate": "28-Aug-2025", "PE": {"strikePrice": 1960, "expiryDate": "28-Aug-2025", "underlying": "BHARTIARTL", "identifier": "OPTSTKBHARTIARTL28-08-2025PE1960.00", "openInterest": 0, "changeinOpenInterest": 0, "pchangeinOpenInterest": 0, "totalTradedVolume": 0, "impliedVolatility": 0, "lastPrice": 0, "change": 0, "pChange": 0, "totalBuyQuantity": 0, "totalSellQuantity": 6650, "bidQty": 0, "bidprice": 0, "askQty": 1900, "askPrice": 41.5, "underlyingValue": 2033}, "CE": {"strikePrice": 1960, "expiryDate": "28-Aug-2025", "underlying": "BHARTIARTL", "identifier": "OPTSTKBHARTIARTL28-08-2025CE1960.00", "openInterest": 0, "changeinOpenInterest": 0, "pchangeinOpenInterest": 0, "totalTradedVolume": 0, "impliedVolatility": 0, "lastPrice": 0, "change": 0, "pChange": 0, "totalBuyQuantity": 5225, "totalSellQuantity": 6650, "bidQty": 475, "bidprice": 88.85, "askQty": 1900, "askPrice": 122.45, "underlyingValue": 2033}}, {"strikePrice": 1980, "expiryDate": "31-Jul-2025", "CE": {"strikePrice": 1980, "expiryDate": "31-Jul-2025", "underlying": "BHARTIARTL", "identifier": "OPTSTKBHARTIARTL31-07-2025CE1980.00", "openInterest": 465, "changeinOpenInterest": -6, "pchangeinOpenInterest": -1.2738853503184713, "totalTradedVolume": 351, "impliedVolatility": 0, "lastPrice": 59.45, "change": 0.8500000000000014, "pChange": 1.4505119453924937, "totalBuyQuantity": 34200, "totalSellQuantity": 35150, "bidQty": 475, "bidprice": 57.75, "askQty": 475, "askPrice": 60.25, "underlyingValue": 2033}, "PE": {"strikePrice": 1980, "expiryDate": "31-Jul-2025", "underlying": "BHARTIARTL", "identifier": "OPTSTKBHARTIARTL31-07-2025PE1980.00", "openInterest": 952, "changeinOpenInterest": 35, "pchangeinOpenInterest": 3.816793893129771, "totalTradedVolume": 1207, "impliedVolatility": 19.25, "lastPrice": 14.35, "change": -2.4000000000000004, "pChange": -14.328358208955224, "totalBuyQuantity": 285475, "totalSellQuantity": 102125, "bidQty": 950, "bidprice": 14.35, "askQty": 475, "askPrice": 14.55, "underlyingValue": 2033}}, {"strikePrice": 1980, "expiryDate": "28-Aug-2025", "PE": {"strikePrice": 1980, "expiryDate": "28-Aug-2025", "underlying": "BHARTIARTL", "identifier": "OPTSTKBHARTIARTL28-08-2025PE1980.00", "openInterest": 0, "changeinOpenInterest": 0, "pchangeinOpenInterest": 0, "totalTradedVolume": 0, "impliedVolatility": 0, "lastPrice": 0, "change": 0, "pChange": 0, "totalBuyQuantity": 0, "totalSellQuantity": 6650, "bidQty": 0, "bidprice": 0, "askQty": 1900, "askPrice": 44.9, "underlyingValue": 2033}, "CE": {"strikePrice": 1980, "expiryDate": "28-Aug-2025", "underlying": "BHARTIARTL", "identifier": "OPTSTKBHARTIARTL28-08-2025CE1980.00", "openInterest": 0, "changeinOpenInterest": 0, "pchangeinOpenInterest": 0, "totalTradedVolume": 0, "impliedVolatility": 0, "lastPrice": 0, "change": 0, "pChange": 0, "totalBuyQuantity": 5225, "totalSellQuantity": 9025, "bidQty": 475, "bidprice": 72.3, "askQty": 1900, "askPrice": 108.15, "underlyingValue": 2033}}, {"strikePrice": 2000, "expiryDate": "31-Jul-2025", "CE": {"strikePrice": 2000, "expiryDate": "31-Jul-2025", "underlying": "BHARTIARTL", "identifier": "OPTSTKBHARTIARTL31-07-2025CE2000.00", "openInterest": 2502, "changeinOpenInterest": -97, "pchangeinOpenInterest": -3.7322046941131206, "totalTradedVolume": 2477, "impliedVolatility": 0, "lastPrice": 45.25, "change": 0.3500000000000014, "pChange": 0.7795100222717181, "totalBuyQuantity": 167200, "totalSellQuantity": 104500, "bidQty": 950, "bidprice": 44.75, "askQty": 475, "askPrice": 45.25, "underlyingValue": 2033}, "PE": {"strikePrice": 2000, "expiryDate": "31-Jul-2025", "underlying": "BHARTIARTL", "identifier": "OPTSTKBHARTIARTL31-07-2025PE2000.00", "openInterest": 2126, "changeinOpenInterest": 89, "pchangeinOpenInterest": 4.369170348551791, "totalTradedVolume": 2839, "impliedVolatility": 19.17, "lastPrice": 20.25, "change": -2.3999999999999986, "pChange": -10.596026490066219, "totalBuyQuantity": 227050, "totalSellQuantity": 152000, "bidQty": 950, "bidprice": 20.2, "askQty": 475, "askPrice": 20.4, "underlyingValue": 2033}}, {"strikePrice": 2000, "expiryDate": "28-Aug-2025", "PE": {"strikePrice": 2000, "expiryDate": "28-Aug-2025", "underlying": "BHARTIARTL", "identifier": "OPTSTKBHARTIARTL28-08-2025PE2000.00", "openInterest": 124, "changeinOpenInterest": 14, "pchangeinOpenInterest": 12.727272727272727, "totalTradedVolume": 57, "impliedVolatility": 0, "lastPrice": 38.5, "change": -1.7000000000000028, "pChange": -4.2288557213930416, "totalBuyQuantity": 9500, "totalSellQuantity": 18525, "bidQty": 475, "bidprice": 37.45, "askQty": 475, "askPrice": 38.8, "underlyingValue": 2033}, "CE": {"strikePrice": 2000, "expiryDate": "28-Aug-2025", "underlying": "BHARTIARTL", "identifier": "OPTSTKBHARTIARTL28-08-2025CE2000.00", "openInterest": 55, "changeinOpenInterest": 9, "pchangeinOpenInterest": 19.565217391304348, "totalTradedVolume": 24, "impliedVolatility": 10.94, "lastPrice": 71.65, "change": -1.3499999999999943, "pChange": -1.8493150684931428, "totalBuyQuantity": 8075, "totalSellQuantity": 9025, "bidQty": 475, "bidprice": 72.4, "askQty": 475, "askPrice": 74.35, "underlyingValue": 2033}}, {"strikePrice": 2020, "expiryDate": "31-Jul-2025", "PE": {"strikePrice": 2020, "expiryDate": "31-Jul-2025", "underlying": "BHARTIARTL", "identifier": "OPTSTKBHARTIARTL31-07-2025PE2020.00", "openInterest": 1267, "changeinOpenInterest": 90, "pchangeinOpenInterest": 7.646559048428207, "totalTradedVolume": 1630, "impliedVolatility": 19.51, "lastPrice": 28.1, "change": -2.549999999999997, "pChange": -8.319738988580742, "totalBuyQuantity": 244625, "totalSellQuantity": 101175, "bidQty": 950, "bidprice": 27.7, "askQty": 475, "askPrice": 28.4, "underlyingValue": 2033}, "CE": {"strikePrice": 2020, "expiryDate": "31-Jul-2025", "underlying": "BHARTIARTL", "identifier": "OPTSTKBHARTIARTL31-07-2025CE2020.00", "openInterest": 1889, "changeinOpenInterest": -3, "pchangeinOpenInterest": -0.15856236786469344, "totalTradedVolume": 3271, "impliedVolatility": 0, "lastPrice": 33.25, "change": 0.29999999999999716, "pChange": 0.9104704097116757, "totalBuyQuantity": 284525, "totalSellQuantity": 148675, "bidQty": 950, "bidprice": 32.75, "askQty": 475, "askPrice": 33.25, "underlyingValue": 2033}}, {"strikePrice": 2020, "expiryDate": "28-Aug-2025", "PE": {"strikePrice": 2020, "expiryDate": "28-Aug-2025", "underlying": "BHARTIARTL", "identifier": "OPTSTKBHARTIARTL28-08-2025PE2020.00", "openInterest": 0, "changeinOpenInterest": 0, "pchangeinOpenInterest": 0, "totalTradedVolume": 0, "impliedVolatility": 0, "lastPrice": 0, "change": 0, "pChange": 0, "totalBuyQuantity": 950, "totalSellQuantity": 6650, "bidQty": 475, "bidprice": 32, "askQty": 1900, "askPrice": 70.2, "underlyingValue": 2033}, "CE": {"strikePrice": 2020, "expiryDate": "28-Aug-2025", "underlying": "BHARTIARTL", "identifier": "OPTSTKBHARTIARTL28-08-2025CE2020.00", "openInterest": 0, "changeinOpenInterest": 0, "pchangeinOpenInterest": 0, "totalTradedVolume": 0, "impliedVolatility": 0, "lastPrice": 0, "change": 0, "pChange": 0, "totalBuyQuantity": 475, "totalSellQuantity": 6650, "bidQty": 475, "bidprice": 51.2, "askQty": 1900, "askPrice": 83.6, "underlyingValue": 2033}}, {"strikePrice": 2040, "expiryDate": "31-Jul-2025", "PE": {"strikePrice": 2040, "expiryDate": "31-Jul-2025", "underlying": "BHARTIARTL", "identifier": "OPTSTKBHARTIARTL31-07-2025PE2040.00", "openInterest": 997, "changeinOpenInterest": 4, "pchangeinOpenInterest": 0.4028197381671702, "totalTradedVolume": 1338, "impliedVolatility": 19.89, "lastPrice": 37.6, "change": -2.8999999999999986, "pChange": -7.16049382716049, "totalBuyQuantity": 90725, "totalSellQuantity": 59375, "bidQty": 475, "bidprice": 37.5, "askQty": 475, "askPrice": 37.95, "underlyingValue": 2033}, "CE": {"strikePrice": 2040, "expiryDate": "31-Jul-2025", "underlying": "BHARTIARTL", "identifier": "OPTSTKBHARTIARTL31-07-2025CE2040.00", "openInterest": 7003, "changeinOpenInterest": 42, "pchangeinOpenInterest": 0.603361585979026, "totalTradedVolume": 5605, "impliedVolatility": 0, "lastPrice": 22.6, "change": -0.09999999999999787, "pChange": -0.4405286343612241, "totalBuyQuantity": 362425, "totalSellQuantity": 228000, "bidQty": 475, "bidprice": 22.7, "askQty": 11400, "askPrice": 22.9, "underlyingValue": 2033}}, {"strikePrice": 2040, "expiryDate": "28-Aug-2025", "PE": {"strikePrice": 2040, "expiryDate": "28-Aug-2025", "underlying": "BHARTIARTL", "identifier": "OPTSTKBHARTIARTL28-08-2025PE2040.00", "openInterest": 0, "changeinOpenInterest": 0, "pchangeinOpenInterest": 0, "totalTradedVolume": 0, "impliedVolatility": 0, "lastPrice": 0, "change": 0, "pChange": 0, "totalBuyQuantity": 1900, "totalSellQuantity": 6650, "bidQty": 1900, "bidprice": 39.5, "askQty": 1900, "askPrice": 63.05, "underlyingValue": 2033}, "CE": {"strikePrice": 2040, "expiryDate": "28-Aug-2025", "underlying": "BHARTIARTL", "identifier": "OPTSTKBHARTIARTL28-08-2025CE2040.00", "openInterest": 101, "changeinOpenInterest": 7, "pchangeinOpenInterest": 7.446808510638298, "totalTradedVolume": 14, "impliedVolatility": 13.25, "lastPrice": 51.5, "change": 4.5, "pChange": 9.574468085106384, "totalBuyQuantity": 19950, "totalSellQuantity": 13300, "bidQty": 475, "bidprice": 51, "askQty": 475, "askPrice": 52, "underlyingValue": 2033}}, {"strikePrice": 2060, "expiryDate": "31-Jul-2025", "PE": {"strikePrice": 2060, "expiryDate": "31-Jul-2025", "underlying": "BHARTIARTL", "identifier": "OPTSTKBHARTIARTL31-07-2025PE2060.00", "openInterest": 334, "changeinOpenInterest": 16, "pchangeinOpenInterest": 5.031446540880503, "totalTradedVolume": 166, "impliedVolatility": 21.1, "lastPrice": 50.5, "change": -2.6000000000000014, "pChange": -4.89642184557439, "totalBuyQuantity": 19950, "totalSellQuantity": 48925, "bidQty": 475, "bidprice": 49.75, "askQty": 950, "askPrice": 50.45, "underlyingValue": 2033}, "CE": {"strikePrice": 2060, "expiryDate": "31-Jul-2025", "underlying": "BHARTIARTL", "identifier": "OPTSTKBHARTIARTL31-07-2025CE2060.00", "openInterest": 4402, "changeinOpenInterest": 76, "pchangeinOpenInterest": 1.756819232547388, "totalTradedVolume": 3043, "impliedVolatility": 10.6, "lastPrice": 15.45, "change": 0.09999999999999964, "pChange": 0.6514657980456003, "totalBuyQuantity": 339625, "totalSellQuantity": 169100, "bidQty": 475, "bidprice": 15.3, "askQty": 475, "askPrice": 15.45, "underlyingValue": 2033}}, {"strikePrice": 2060, "expiryDate": "28-Aug-2025", "PE": {"strikePrice": 2060, "expiryDate": "28-Aug-2025", "underlying": "BHARTIARTL", "identifier": "OPTSTKBHARTIARTL28-08-2025PE2060.00", "openInterest": 0, "changeinOpenInterest": 0, "pchangeinOpenInterest": 0, "totalTradedVolume": 0, "impliedVolatility": 0, "lastPrice": 0, "change": 0, "pChange": 0, "totalBuyQuantity": 0, "totalSellQuantity": 9025, "bidQty": 0, "bidprice": 0, "askQty": 2375, "askPrice": 84.4, "underlyingValue": 2033}, "CE": {"strikePrice": 2060, "expiryDate": "28-Aug-2025", "underlying": "BHARTIARTL", "identifier": "OPTSTKBHARTIARTL28-08-2025CE2060.00", "openInterest": 0, "changeinOpenInterest": 0, "pchangeinOpenInterest": 0, "totalTradedVolume": 0, "impliedVolatility": 0, "lastPrice": 0, "change": 0, "pChange": 0, "totalBuyQuantity": 0, "totalSellQuantity": 7125, "bidQty": 0, "bidprice": 0, "askQty": 475, "askPrice": 49.9, "underlyingValue": 2033}}, {"strikePrice": 2080, "expiryDate": "31-Jul-2025", "PE": {"strikePrice": 2080, "expiryDate": "31-Jul-2025", "underlying": "BHARTIARTL", "identifier": "OPTSTKBHARTIARTL31-07-2025PE2080.00", "openInterest": 96, "changeinOpenInterest": -9, "pchangeinOpenInterest": -8.571428571428571, "totalTradedVolume": 73, "impliedVolatility": 22.95, "lastPrice": 66, "change": -2.299999999999997, "pChange": -3.3674963396778876, "totalBuyQuantity": 41325, "totalSellQuantity": 45125, "bidQty": 3325, "bidprice": 58.1, "askQty": 950, "askPrice": 66, "underlyingValue": 2033}, "CE": {"strikePrice": 2080, "expiryDate": "31-Jul-2025", "underlying": "BHARTIARTL", "identifier": "OPTSTKBHARTIARTL31-07-2025CE2080.00", "openInterest": 2165, "changeinOpenInterest": 20, "pchangeinOpenInterest": 0.9324009324009324, "totalTradedVolume": 1844, "impliedVolatility": 11.43, "lastPrice": 10.15, "change": -0.09999999999999964, "pChange": -0.9756097560975575, "totalBuyQuantity": 334400, "totalSellQuantity": 92625, "bidQty": 475, "bidprice": 10.15, "askQty": 475, "askPrice": 10.3, "underlyingValue": 2033}}, {"strikePrice": 2080, "expiryDate": "28-Aug-2025", "CE": {"strikePrice": 2080, "expiryDate": "28-Aug-2025", "underlying": "BHARTIARTL", "identifier": "OPTSTKBHARTIARTL28-08-2025CE2080.00", "openInterest": 1, "changeinOpenInterest": 0, "pchangeinOpenInterest": 0, "totalTradedVolume": 0, "impliedVolatility": 0, "lastPrice": 0, "change": 0, "pChange": 0, "totalBuyQuantity": 0, "totalSellQuantity": 8075, "bidQty": 0, "bidprice": 0, "askQty": 475, "askPrice": 38.05, "underlyingValue": 2033}, "PE": {"strikePrice": 2080, "expiryDate": "28-Aug-2025", "underlying": "BHARTIARTL", "identifier": "OPTSTKBHARTIARTL28-08-2025PE2080.00", "openInterest": 0, "changeinOpenInterest": 0, "pchangeinOpenInterest": 0, "totalTradedVolume": 0, "impliedVolatility": 0, "lastPrice": 0, "change": 0, "pChange": 0, "totalBuyQuantity": 0, "totalSellQuantity": 6650, "bidQty": 0, "bidprice": 0, "askQty": 1900, "askPrice": 92.35, "underlyingValue": 2033}}, {"strikePrice": 2100, "expiryDate": "31-Jul-2025", "PE": {"strikePrice": 2100, "expiryDate": "31-Jul-2025", "underlying": "BHARTIARTL", "identifier": "OPTSTKBHARTIARTL31-07-2025PE2100.00", "openInterest": 438, "changeinOpenInterest": -5, "pchangeinOpenInterest": -1.1286681715575622, "totalTradedVolume": 97, "impliedVolatility": 24.86, "lastPrice": 82.6, "change": -1.4000000000000057, "pChange": -1.6666666666666736, "totalBuyQuantity": 45600, "totalSellQuantity": 57950, "bidQty": 475, "bidprice": 81.05, "askQty": 950, "askPrice": 82.6, "underlyingValue": 2033}, "CE": {"strikePrice": 2100, "expiryDate": "31-Jul-2025", "underlying": "BHARTIARTL", "identifier": "OPTSTKBHARTIARTL31-07-2025CE2100.00", "openInterest": 3977, "changeinOpenInterest": -274, "pchangeinOpenInterest": -6.445542225358739, "totalTradedVolume": 2660, "impliedVolatility": 12.27, "lastPrice": 7, "change": -0.2999999999999998, "pChange": -4.109589041095888, "totalBuyQuantity": 405175, "totalSellQuantity": 267425, "bidQty": 950, "bidprice": 6.9, "askQty": 2850, "askPrice": 7.1, "underlyingValue": 2033}}, {"strikePrice": 2100, "expiryDate": "28-Aug-2025", "CE": {"strikePrice": 2100, "expiryDate": "28-Aug-2025", "underlying": "BHARTIARTL", "identifier": "OPTSTKBHARTIARTL28-08-2025CE2100.00", "openInterest": 0, "changeinOpenInterest": 0, "pchangeinOpenInterest": 0, "totalTradedVolume": 0, "impliedVolatility": 0, "lastPrice": 0, "change": 0, "pChange": 0, "totalBuyQuantity": 0, "totalSellQuantity": 8550, "bidQty": 0, "bidprice": 0, "askQty": 950, "askPrice": 36.5, "underlyingValue": 2033}, "PE": {"strikePrice": 2100, "expiryDate": "28-Aug-2025", "underlying": "BHARTIARTL", "identifier": "OPTSTKBHARTIARTL28-08-2025PE2100.00", "openInterest": 0, "changeinOpenInterest": 0, "pchangeinOpenInterest": 0, "totalTradedVolume": 0, "impliedVolatility": 0, "lastPrice": 0, "change": 0, "pChange": 0, "totalBuyQuantity": 6650, "totalSellQuantity": 9025, "bidQty": 1900, "bidprice": 60.75, "askQty": 2375, "askPrice": 119.8, "underlyingValue": 2033}}, {"strikePrice": 2120, "expiryDate": "31-Jul-2025", "PE": {"strikePrice": 2120, "expiryDate": "31-Jul-2025", "underlying": "BHARTIARTL", "identifier": "OPTSTKBHARTIARTL31-07-2025PE2120.00", "openInterest": 39, "changeinOpenInterest": 0, "pchangeinOpenInterest": 0, "totalTradedVolume": 0, "impliedVolatility": 0, "lastPrice": 0, "change": 0, "pChange": 0, "totalBuyQuantity": 35150, "totalSellQuantity": 37050, "bidQty": 4750, "bidprice": 94.65, "askQty": 1900, "askPrice": 103.35, "underlyingValue": 2033}, "CE": {"strikePrice": 2120, "expiryDate": "31-Jul-2025", "underlying": "BHARTIARTL", "identifier": "OPTSTKBHARTIARTL31-07-2025CE2120.00", "openInterest": 777, "changeinOpenInterest": -36, "pchangeinOpenInterest": -4.428044280442805, "totalTradedVolume": 662, "impliedVolatility": 13.07, "lastPrice": 4.8, "change": -0.04999999999999982, "pChange": -1.0309278350515427, "totalBuyQuantity": 402325, "totalSellQuantity": 87875, "bidQty": 1425, "bidprice": 4.65, "askQty": 1425, "askPrice": 4.8, "underlyingValue": 2033}}, {"strikePrice": 2120, "expiryDate": "28-Aug-2025", "CE": {"strikePrice": 2120, "expiryDate": "28-Aug-2025", "underlying": "BHARTIARTL", "identifier": "OPTSTKBHARTIARTL28-08-2025CE2120.00", "openInterest": 0, "changeinOpenInterest": 0, "pchangeinOpenInterest": 0, "totalTradedVolume": 0, "impliedVolatility": 0, "lastPrice": 0, "change": 0, "pChange": 0, "totalBuyQuantity": 0, "totalSellQuantity": 7600, "bidQty": 0, "bidprice": 0, "askQty": 950, "askPrice": 31.75, "underlyingValue": 2033}, "PE": {"strikePrice": 2120, "expiryDate": "28-Aug-2025", "underlying": "BHARTIARTL", "identifier": "OPTSTKBHARTIARTL28-08-2025PE2120.00", "openInterest": 0, "changeinOpenInterest": 0, "pchangeinOpenInterest": 0, "totalTradedVolume": 0, "impliedVolatility": 0, "lastPrice": 0, "change": 0, "pChange": 0, "totalBuyQuantity": 6650, "totalSellQuantity": 6650, "bidQty": 1900, "bidprice": 80.5, "askQty": 1900, "askPrice": 123.4, "underlyingValue": 2033}}, {"strikePrice": 2140, "expiryDate": "31-Jul-2025", "PE": {"strikePrice": 2140, "expiryDate": "31-Jul-2025", "underlying": "BHARTIARTL", "identifier": "OPTSTKBHARTIARTL31-07-2025PE2140.00", "openInterest": 0, "changeinOpenInterest": 0, "pchangeinOpenInterest": 0, "totalTradedVolume": 0, "impliedVolatility": 0, "lastPrice": 0, "change": 0, "pChange": 0, "totalBuyQuantity": 28025, "totalSellQuantity": 32775, "bidQty": 1425, "bidprice": 109.95, "askQty": 2375, "askPrice": 123.9, "underlyingValue": 2033}, "CE": {"strikePrice": 2140, "expiryDate": "31-Jul-2025", "underlying": "BHARTIARTL", "identifier": "OPTSTKBHARTIARTL31-07-2025CE2140.00", "openInterest": 395, "changeinOpenInterest": 43, "pchangeinOpenInterest": 12.215909090909092, "totalTradedVolume": 291, "impliedVolatility": 13.81, "lastPrice": 3.3, "change": -0.15000000000000036, "pChange": -4.347826086956532, "totalBuyQuantity": 400900, "totalSellQuantity": 77425, "bidQty": 475, "bidprice": 3.15, "askQty": 1425, "askPrice": 3.35, "underlyingValue": 2033}}, {"strikePrice": 2140, "expiryDate": "28-Aug-2025", "PE": {"strikePrice": 2140, "expiryDate": "28-Aug-2025", "underlying": "BHARTIARTL", "identifier": "OPTSTKBHARTIARTL28-08-2025PE2140.00", "openInterest": 0, "changeinOpenInterest": 0, "pchangeinOpenInterest": 0, "totalTradedVolume": 0, "impliedVolatility": 0, "lastPrice": 0, "change": 0, "pChange": 0, "totalBuyQuantity": 6650, "totalSellQuantity": 6650, "bidQty": 1900, "bidprice": 100.3, "askQty": 1900, "askPrice": 137.3, "underlyingValue": 2033}, "CE": {"strikePrice": 2140, "expiryDate": "28-Aug-2025", "underlying": "BHARTIARTL", "identifier": "OPTSTKBHARTIARTL28-08-2025CE2140.00", "openInterest": 0, "changeinOpenInterest": 0, "pchangeinOpenInterest": 0, "totalTradedVolume": 0, "impliedVolatility": 0, "lastPrice": 0, "change": 0, "pChange": 0, "totalBuyQuantity": 0, "totalSellQuantity": 7600, "bidQty": 0, "bidprice": 0, "askQty": 950, "askPrice": 26.2, "underlyingValue": 2033}}, {"strikePrice": 2160, "expiryDate": "31-Jul-2025", "PE": {"strikePrice": 2160, "expiryDate": "31-Jul-2025", "underlying": "BHARTIARTL", "identifier": "OPTSTKBHARTIARTL31-07-2025PE2160.00", "openInterest": 6, "changeinOpenInterest": 0, "pchangeinOpenInterest": 0, "totalTradedVolume": 0, "impliedVolatility": 0, "lastPrice": 0, "change": 0, "pChange": 0, "totalBuyQuantity": 26125, "totalSellQuantity": 31825, "bidQty": 1900, "bidprice": 125.4, "askQty": 950, "askPrice": 139.95, "underlyingValue": 2033}, "CE": {"strikePrice": 2160, "expiryDate": "31-Jul-2025", "underlying": "BHARTIARTL", "identifier": "OPTSTKBHARTIARTL31-07-2025CE2160.00", "openInterest": 528, "changeinOpenInterest": -17, "pchangeinOpenInterest": -3.1192660550458715, "totalTradedVolume": 152, "impliedVolatility": 0, "lastPrice": 2.4, "change": 0, "pChange": 0, "totalBuyQuantity": 365275, "totalSellQuantity": 59850, "bidQty": 475, "bidprice": 2.2, "askQty": 475, "askPrice": 2.35, "underlyingValue": 2033}}, {"strikePrice": 2160, "expiryDate": "28-Aug-2025", "PE": {"strikePrice": 2160, "expiryDate": "28-Aug-2025", "underlying": "BHARTIARTL", "identifier": "OPTSTKBHARTIARTL28-08-2025PE2160.00", "openInterest": 0, "changeinOpenInterest": 0, "pchangeinOpenInterest": 0, "totalTradedVolume": 0, "impliedVolatility": 0, "lastPrice": 0, "change": 0, "pChange": 0, "totalBuyQuantity": 9025, "totalSellQuantity": 6650, "bidQty": 2375, "bidprice": 119.55, "askQty": 1900, "askPrice": 146.6, "underlyingValue": 2033}, "CE": {"strikePrice": 2160, "expiryDate": "28-Aug-2025", "underlying": "BHARTIARTL", "identifier": "OPTSTKBHARTIARTL28-08-2025CE2160.00", "openInterest": 83, "changeinOpenInterest": 2, "pchangeinOpenInterest": 2.4691358024691357, "totalTradedVolume": 22, "impliedVolatility": 15.71, "lastPrice": 14.85, "change": -0.40000000000000036, "pChange": -2.6229508196721336, "totalBuyQuantity": 30400, "totalSellQuantity": 17100, "bidQty": 475, "bidprice": 14.9, "askQty": 475, "askPrice": 15.4, "underlyingValue": 2033}}, {"strikePrice": 2180, "expiryDate": "31-Jul-2025", "CE": {"strikePrice": 2180, "expiryDate": "31-Jul-2025", "underlying": "BHARTIARTL", "identifier": "OPTSTKBHARTIARTL31-07-2025CE2180.00", "openInterest": 225, "changeinOpenInterest": -27, "pchangeinOpenInterest": -10.714285714285714, "totalTradedVolume": 92, "impliedVolatility": 0, "lastPrice": 1.65, "change": -0.20000000000000018, "pChange": -10.81081081081082, "totalBuyQuantity": 329650, "totalSellQuantity": 43700, "bidQty": 950, "bidprice": 1.6, "askQty": 475, "askPrice": 1.75, "underlyingValue": 2033}, "PE": {"strikePrice": 2180, "expiryDate": "31-Jul-2025", "underlying": "BHARTIARTL", "identifier": "OPTSTKBHARTIARTL31-07-2025PE2180.00", "openInterest": 0, "changeinOpenInterest": 0, "pchangeinOpenInterest": 0, "totalTradedVolume": 0, "impliedVolatility": 0, "lastPrice": 0, "change": 0, "pChange": 0, "totalBuyQuantity": 24225, "totalSellQuantity": 31350, "bidQty": 1900, "bidprice": 144.85, "askQty": 2375, "askPrice": 162.45, "underlyingValue": 2033}}, {"strikePrice": 2180, "expiryDate": "28-Aug-2025", "PE": {"strikePrice": 2180, "expiryDate": "28-Aug-2025", "underlying": "BHARTIARTL", "identifier": "OPTSTKBHARTIARTL28-08-2025PE2180.00", "openInterest": 0, "changeinOpenInterest": 0, "pchangeinOpenInterest": 0, "totalTradedVolume": 0, "impliedVolatility": 0, "lastPrice": 0, "change": 0, "pChange": 0, "totalBuyQuantity": 6650, "totalSellQuantity": 9025, "bidQty": 1900, "bidprice": 132.6, "askQty": 2375, "askPrice": 179.3, "underlyingValue": 2033}, "CE": {"strikePrice": 2180, "expiryDate": "28-Aug-2025", "underlying": "BHARTIARTL", "identifier": "OPTSTKBHARTIARTL28-08-2025CE2180.00", "openInterest": 0, "changeinOpenInterest": 0, "pchangeinOpenInterest": 0, "totalTradedVolume": 0, "impliedVolatility": 0, "lastPrice": 0, "change": 0, "pChange": 0, "totalBuyQuantity": 0, "totalSellQuantity": 7125, "bidQty": 0, "bidprice": 0, "askQty": 475, "askPrice": 15, "underlyingValue": 2033}}, {"strikePrice": 2200, "expiryDate": "31-Jul-2025", "PE": {"strikePrice": 2200, "expiryDate": "31-Jul-2025", "underlying": "BHARTIARTL", "identifier": "OPTSTKBHARTIARTL31-07-2025PE2200.00", "openInterest": 11, "changeinOpenInterest": 1, "pchangeinOpenInterest": 10, "totalTradedVolume": 3, "impliedVolatility": 0, "lastPrice": 182, "change": -7, "pChange": -3.7037037037037033, "totalBuyQuantity": 32300, "totalSellQuantity": 39900, "bidQty": 950, "bidprice": 172.65, "askQty": 950, "askPrice": 177, "underlyingValue": 2033}, "CE": {"strikePrice": 2200, "expiryDate": "31-Jul-2025", "underlying": "BHARTIARTL", "identifier": "OPTSTKBHARTIARTL31-07-2025CE2200.00", "openInterest": 2051, "changeinOpenInterest": 11, "pchangeinOpenInterest": 0.5392156862745098, "totalTradedVolume": 292, "impliedVolatility": 16.39, "lastPrice": 1.4, "change": 0, "pChange": 0, "totalBuyQuantity": 441275, "totalSellQuantity": 99750, "bidQty": 1425, "bidprice": 1.2, "askQty": 1425, "askPrice": 1.4, "underlyingValue": 2033}}, {"strikePrice": 2200, "expiryDate": "28-Aug-2025", "PE": {"strikePrice": 2200, "expiryDate": "28-Aug-2025", "underlying": "BHARTIARTL", "identifier": "OPTSTKBHARTIARTL28-08-2025PE2200.00", "openInterest": 0, "changeinOpenInterest": 0, "pchangeinOpenInterest": 0, "totalTradedVolume": 0, "impliedVolatility": 0, "lastPrice": 0, "change": 0, "pChange": 0, "totalBuyQuantity": 9025, "totalSellQuantity": 6650, "bidQty": 2375, "bidprice": 155.95, "askQty": 1900, "askPrice": 181.1, "underlyingValue": 2033}, "CE": {"strikePrice": 2200, "expiryDate": "28-Aug-2025", "underlying": "BHARTIARTL", "identifier": "OPTSTKBHARTIARTL28-08-2025CE2200.00", "openInterest": 92, "changeinOpenInterest": 32, "pchangeinOpenInterest": 53.333333333333336, "totalTradedVolume": 51, "impliedVolatility": 0, "lastPrice": 10, "change": -0.25, "pChange": -2.4390243902439024, "totalBuyQuantity": 25175, "totalSellQuantity": 16150, "bidQty": 475, "bidprice": 9.5, "askQty": 475, "askPrice": 10, "underlyingValue": 2033}}, {"strikePrice": 2220, "expiryDate": "31-Jul-2025", "PE": {"strikePrice": 2220, "expiryDate": "31-Jul-2025", "underlying": "BHARTIARTL", "identifier": "OPTSTKBHARTIARTL31-07-2025PE2220.00", "openInterest": 0, "changeinOpenInterest": 0, "pchangeinOpenInterest": 0, "totalTradedVolume": 0, "impliedVolatility": 0, "lastPrice": 0, "change": 0, "pChange": 0, "totalBuyQuantity": 24700, "totalSellQuantity": 30400, "bidQty": 1425, "bidprice": 184.15, "askQty": 1425, "askPrice": 202.85, "underlyingValue": 2033}, "CE": {"strikePrice": 2220, "expiryDate": "31-Jul-2025", "underlying": "BHARTIARTL", "identifier": "OPTSTKBHARTIARTL31-07-2025CE2220.00", "openInterest": 55, "changeinOpenInterest": -6, "pchangeinOpenInterest": -9.836065573770492, "totalTradedVolume": 15, "impliedVolatility": 16.81, "lastPrice": 0.9, "change": -0.2499999999999999, "pChange": -21.7391304347826, "totalBuyQuantity": 109725, "totalSellQuantity": 76475, "bidQty": 950, "bidprice": 0.85, "askQty": 1900, "askPrice": 1, "underlyingValue": 2033}}, {"strikePrice": 2220, "expiryDate": "28-Aug-2025", "PE": {"strikePrice": 2220, "expiryDate": "28-Aug-2025", "underlying": "BHARTIARTL", "identifier": "OPTSTKBHARTIARTL28-08-2025PE2220.00", "openInterest": 0, "changeinOpenInterest": 0, "pchangeinOpenInterest": 0, "totalTradedVolume": 0, "impliedVolatility": 0, "lastPrice": 0, "change": 0, "pChange": 0, "totalBuyQuantity": 9025, "totalSellQuantity": 9025, "bidQty": 2375, "bidprice": 168.1, "askQty": 2375, "askPrice": 218, "underlyingValue": 2033}, "CE": {"strikePrice": 2220, "expiryDate": "28-Aug-2025", "underlying": "BHARTIARTL", "identifier": "OPTSTKBHARTIARTL28-08-2025CE2220.00", "openInterest": 0, "changeinOpenInterest": 0, "pchangeinOpenInterest": 0, "totalTradedVolume": 0, "impliedVolatility": 0, "lastPrice": 0, "change": 0, "pChange": 0, "totalBuyQuantity": 0, "totalSellQuantity": 6650, "bidQty": 0, "bidprice": 0, "askQty": 1900, "askPrice": 25.3, "underlyingValue": 2033}}, {"strikePrice": 2240, "expiryDate": "31-Jul-2025", "CE": {"strikePrice": 2240, "expiryDate": "31-Jul-2025", "underlying": "BHARTIARTL", "identifier": "OPTSTKBHARTIARTL31-07-2025CE2240.00", "openInterest": 414, "changeinOpenInterest": -1, "pchangeinOpenInterest": -0.24096385542168675, "totalTradedVolume": 30, "impliedVolatility": 17.63, "lastPrice": 0.7, "change": -0.10000000000000009, "pChange": -12.50000000000001, "totalBuyQuantity": 235125, "totalSellQuantity": 81225, "bidQty": 950, "bidprice": 0.65, "askQty": 2850, "askPrice": 0.8, "underlyingValue": 2033}, "PE": {"strikePrice": 2240, "expiryDate": "31-Jul-2025", "underlying": "BHARTIARTL", "identifier": "OPTSTKBHARTIARTL31-07-2025PE2240.00", "openInterest": 0, "changeinOpenInterest": 0, "pchangeinOpenInterest": 0, "totalTradedVolume": 0, "impliedVolatility": 0, "lastPrice": 0, "change": 0, "pChange": 0, "totalBuyQuantity": 23275, "totalSellQuantity": 30400, "bidQty": 1425, "bidprice": 203.75, "askQty": 1425, "askPrice": 222.4, "underlyingValue": 2033}}, {"strikePrice": 2240, "expiryDate": "28-Aug-2025", "PE": {"strikePrice": 2240, "expiryDate": "28-Aug-2025", "underlying": "BHARTIARTL", "identifier": "OPTSTKBHARTIARTL28-08-2025PE2240.00", "openInterest": 0, "changeinOpenInterest": 0, "pchangeinOpenInterest": 0, "totalTradedVolume": 0, "impliedVolatility": 0, "lastPrice": 0, "change": 0, "pChange": 0, "totalBuyQuantity": 9025, "totalSellQuantity": 6650, "bidQty": 2375, "bidprice": 190.7, "askQty": 1900, "askPrice": 234.65, "underlyingValue": 2033}, "CE": {"strikePrice": 2240, "expiryDate": "28-Aug-2025", "underlying": "BHARTIARTL", "identifier": "OPTSTKBHARTIARTL28-08-2025CE2240.00", "openInterest": 0, "changeinOpenInterest": 0, "pchangeinOpenInterest": 0, "totalTradedVolume": 0, "impliedVolatility": 0, "lastPrice": 0, "change": 0, "pChange": 0, "totalBuyQuantity": 475, "totalSellQuantity": 6650, "bidQty": 475, "bidprice": 2.5, "askQty": 1900, "askPrice": 25.4, "underlyingValue": 2033}}, {"strikePrice": 2240, "expiryDate": "30-Sep-2025", "CE": {"strikePrice": 2240, "expiryDate": "30-Sep-2025", "underlying": "BHARTIARTL", "identifier": "OPTSTKBHARTIARTL30-09-2025CE2240.00", "openInterest": 0, "changeinOpenInterest": 0, "pchangeinOpenInterest": 0, "totalTradedVolume": 0, "impliedVolatility": 0, "lastPrice": 0, "change": 0, "pChange": 0, "totalBuyQuantity": 0, "totalSellQuantity": 475, "bidQty": 0, "bidprice": 0, "askQty": 475, "askPrice": 21.9, "underlyingValue": 2033}}, {"strikePrice": 2280, "expiryDate": "31-Jul-2025", "CE": {"strikePrice": 2280, "expiryDate": "31-Jul-2025", "underlying": "BHARTIARTL", "identifier": "OPTSTKBHARTIARTL31-07-2025CE2280.00", "openInterest": 252, "changeinOpenInterest": 1, "pchangeinOpenInterest": 0.398406374501992, "totalTradedVolume": 7, "impliedVolatility": 18.96, "lastPrice": 0.4, "change": -0.15000000000000002, "pChange": -27.272727272727277, "totalBuyQuantity": 177650, "totalSellQuantity": 69825, "bidQty": 950, "bidprice": 0.45, "askQty": 2850, "askPrice": 0.55, "underlyingValue": 2033}, "PE": {"strikePrice": 2280, "expiryDate": "31-Jul-2025", "underlying": "BHARTIARTL", "identifier": "OPTSTKBHARTIARTL31-07-2025PE2280.00", "openInterest": 0, "changeinOpenInterest": 0, "pchangeinOpenInterest": 0, "totalTradedVolume": 0, "impliedVolatility": 0, "lastPrice": 0, "change": 0, "pChange": 0, "totalBuyQuantity": 23275, "totalSellQuantity": 30400, "bidQty": 1425, "bidprice": 241.25, "askQty": 1425, "askPrice": 263.25, "underlyingValue": 2033}}, {"strikePrice": 2280, "expiryDate": "28-Aug-2025", "PE": {"strikePrice": 2280, "expiryDate": "28-Aug-2025", "underlying": "BHARTIARTL", "identifier": "OPTSTKBHARTIARTL28-08-2025PE2280.00", "openInterest": 0, "changeinOpenInterest": 0, "pchangeinOpenInterest": 0, "totalTradedVolume": 0, "impliedVolatility": 0, "lastPrice": 0, "change": 0, "pChange": 0, "totalBuyQuantity": 9025, "totalSellQuantity": 6650, "bidQty": 2375, "bidprice": 228.5, "askQty": 1900, "askPrice": 273.95, "underlyingValue": 2033}, "CE": {"strikePrice": 2280, "expiryDate": "28-Aug-2025", "underlying": "BHARTIARTL", "identifier": "OPTSTKBHARTIARTL28-08-2025CE2280.00", "openInterest": 0, "changeinOpenInterest": 0, "pchangeinOpenInterest": 0, "totalTradedVolume": 0, "impliedVolatility": 0, "lastPrice": 0, "change": 0, "pChange": 0, "totalBuyQuantity": 19000, "totalSellQuantity": 6650, "bidQty": 4750, "bidprice": 0.6, "askQty": 1900, "askPrice": 25.4, "underlyingValue": 2033}}, {"strikePrice": 2320, "expiryDate": "31-Jul-2025", "CE": {"strikePrice": 2320, "expiryDate": "31-Jul-2025", "underlying": "BHARTIARTL", "identifier": "OPTSTKBHARTIARTL31-07-2025CE2320.00", "openInterest": 89, "changeinOpenInterest": 2, "pchangeinOpenInterest": 2.2988505747126435, "totalTradedVolume": 14, "impliedVolatility": 21.56, "lastPrice": 0.4, "change": 0, "pChange": 0, "totalBuyQuantity": 170525, "totalSellQuantity": 56050, "bidQty": 950, "bidprice": 0.35, "askQty": 5700, "askPrice": 0.6, "underlyingValue": 2033}, "PE": {"strikePrice": 2320, "expiryDate": "31-Jul-2025", "underlying": "BHARTIARTL", "identifier": "OPTSTKBHARTIARTL31-07-2025PE2320.00", "openInterest": 0, "changeinOpenInterest": 0, "pchangeinOpenInterest": 0, "totalTradedVolume": 0, "impliedVolatility": 0, "lastPrice": 0, "change": 0, "pChange": 0, "totalBuyQuantity": 23275, "totalSellQuantity": 30400, "bidQty": 1425, "bidprice": 282.95, "askQty": 1425, "askPrice": 301.6, "underlyingValue": 2033}}, {"strikePrice": 2320, "expiryDate": "28-Aug-2025", "PE": {"strikePrice": 2320, "expiryDate": "28-Aug-2025", "underlying": "BHARTIARTL", "identifier": "OPTSTKBHARTIARTL28-08-2025PE2320.00", "openInterest": 0, "changeinOpenInterest": 0, "pchangeinOpenInterest": 0, "totalTradedVolume": 0, "impliedVolatility": 0, "lastPrice": 0, "change": 0, "pChange": 0, "totalBuyQuantity": 9025, "totalSellQuantity": 6650, "bidQty": 2375, "bidprice": 263.85, "askQty": 1900, "askPrice": 316, "underlyingValue": 2033}, "CE": {"strikePrice": 2320, "expiryDate": "28-Aug-2025", "underlying": "BHARTIARTL", "identifier": "OPTSTKBHARTIARTL28-08-2025CE2320.00", "openInterest": 0, "changeinOpenInterest": 0, "pchangeinOpenInterest": 0, "totalTradedVolume": 0, "impliedVolatility": 0, "lastPrice": 0, "change": 0, "pChange": 0, "totalBuyQuantity": 14250, "totalSellQuantity": 1900, "bidQty": 14250, "bidprice": 0.05, "askQty": 1900, "askPrice": 25.4, "underlyingValue": 2033}}], "timestamp": "08-Jul-2025 15:30:00", "underlyingValue": 2033, "strikePrices": [1600, 1640, 1680, 1700, 1720, 1740, 1760, 1780, 1800, 1820, 1840, 1860, 1880, 1900, 1920, 1940, 1960, 1980, 2000, 2020, 2040, 2060, 2080, 2100, 2120, 2140, 2160, 2180, 2200, 2220, 2240, 2280, 2320]}, "filtered": {"data": [{"strikePrice": 1600, "expiryDate": "31-Jul-2025", "CE": {"strikePrice": 1600, "expiryDate": "31-Jul-2025", "underlying": "BHARTIARTL", "identifier": "OPTSTKBHARTIARTL31-07-2025CE1600.00", "openInterest": 606, "changeinOpenInterest": 0, "pchangeinOpenInterest": 0, "totalTradedVolume": 0, "impliedVolatility": 0, "lastPrice": 0, "change": 0, "pChange": 0, "totalBuyQuantity": 29450, "totalSellQuantity": 29450, "bidQty": 1425, "bidprice": 415, "askQty": 1425, "askPrice": 426.7, "underlyingValue": 2033}, "PE": {"strikePrice": 1600, "expiryDate": "31-Jul-2025", "underlying": "BHARTIARTL", "identifier": "OPTSTKBHARTIARTL31-07-2025PE1600.00", "openInterest": 227, "changeinOpenInterest": 0, "pchangeinOpenInterest": 0, "totalTradedVolume": 1, "impliedVolatility": 0, "lastPrice": 0.2, "change": -0.04999999999999999, "pChange": -19.999999999999996, "totalBuyQuantity": 72675, "totalSellQuantity": 29925, "bidQty": 3800, "bidprice": 0.2, "askQty": 1900, "askPrice": 0.3, "underlyingValue": 2033}}, {"strikePrice": 1640, "expiryDate": "31-Jul-2025", "PE": {"strikePrice": 1640, "expiryDate": "31-Jul-2025", "underlying": "BHARTIARTL", "identifier": "OPTSTKBHARTIARTL31-07-2025PE1640.00", "openInterest": 19, "changeinOpenInterest": 0, "pchangeinOpenInterest": 0, "totalTradedVolume": 0, "impliedVolatility": 0, "lastPrice": 0, "change": 0, "pChange": 0, "totalBuyQuantity": 63175, "totalSellQuantity": 31350, "bidQty": 3800, "bidprice": 0.2, "askQty": 5225, "askPrice": 0.5, "underlyingValue": 2033}}, {"strikePrice": 1680, "expiryDate": "31-Jul-2025", "PE": {"strikePrice": 1680, "expiryDate": "31-Jul-2025", "underlying": "BHARTIARTL", "identifier": "OPTSTKBHARTIARTL31-07-2025PE1680.00", "openInterest": 43, "changeinOpenInterest": 3, "pchangeinOpenInterest": 7.5, "totalTradedVolume": 7, "impliedVolatility": 31.51, "lastPrice": 0.3, "change": 0.04999999999999999, "pChange": 19.999999999999996, "totalBuyQuantity": 175750, "totalSellQuantity": 52725, "bidQty": 101175, "bidprice": 0.25, "askQty": 475, "askPrice": 0.3, "underlyingValue": 2033}, "CE": {"strikePrice": 1680, "expiryDate": "31-Jul-2025", "underlying": "BHARTIARTL", "identifier": "OPTSTKBHARTIARTL31-07-2025CE1680.00", "openInterest": 1, "changeinOpenInterest": 0, "pchangeinOpenInterest": 0, "totalTradedVolume": 0, "impliedVolatility": 0, "lastPrice": 0, "change": 0, "pChange": 0, "totalBuyQuantity": 29450, "totalSellQuantity": 22325, "bidQty": 1425, "bidprice": 335.55, "askQty": 1425, "askPrice": 354.1, "underlyingValue": 2033}}, {"strikePrice": 1700, "expiryDate": "31-Jul-2025", "CE": {"strikePrice": 1700, "expiryDate": "31-Jul-2025", "underlying": "BHARTIARTL", "identifier": "OPTSTKBHARTIARTL31-07-2025CE1700.00", "openInterest": 35, "changeinOpenInterest": 0, "pchangeinOpenInterest": 0, "totalTradedVolume": 0, "impliedVolatility": 0, "lastPrice": 0, "change": 0, "pChange": 0, "totalBuyQuantity": 31350, "totalSellQuantity": 26600, "bidQty": 3325, "bidprice": 316.7, "askQty": 3325, "askPrice": 334.1, "underlyingValue": 2033}, "PE": {"strikePrice": 1700, "expiryDate": "31-Jul-2025", "underlying": "BHARTIARTL", "identifier": "OPTSTKBHARTIARTL31-07-2025PE1700.00", "openInterest": 203, "changeinOpenInterest": -4, "pchangeinOpenInterest": -1.932367149758454, "totalTradedVolume": 25, "impliedVolatility": 31.72, "lastPrice": 0.5, "change": 0.04999999999999999, "pChange": 11.111111111111107, "totalBuyQuantity": 161025, "totalSellQuantity": 89300, "bidQty": 950, "bidprice": 0.4, "askQty": 4750, "askPrice": 0.5, "underlyingValue": 2033}}, {"strikePrice": 1720, "expiryDate": "31-Jul-2025", "PE": {"strikePrice": 1720, "expiryDate": "31-Jul-2025", "underlying": "BHARTIARTL", "identifier": "OPTSTKBHARTIARTL31-07-2025PE1720.00", "openInterest": 158, "changeinOpenInterest": 3, "pchangeinOpenInterest": 1.935483870967742, "totalTradedVolume": 8, "impliedVolatility": 0, "lastPrice": 0.5, "change": 0, "pChange": 0, "totalBuyQuantity": 113525, "totalSellQuantity": 38000, "bidQty": 2375, "bidprice": 0.35, "askQty": 475, "askPrice": 0.45, "underlyingValue": 2033}, "CE": {"strikePrice": 1720, "expiryDate": "31-Jul-2025", "underlying": "BHARTIARTL", "identifier": "OPTSTKBHARTIARTL31-07-2025CE1720.00", "openInterest": 2, "changeinOpenInterest": 0, "pchangeinOpenInterest": 0, "totalTradedVolume": 0, "impliedVolatility": 0, "lastPrice": 0, "change": 0, "pChange": 0, "totalBuyQuantity": 29450, "totalSellQuantity": 15200, "bidQty": 1425, "bidprice": 294.9, "askQty": 1425, "askPrice": 314.55, "underlyingValue": 2033}}, {"strikePrice": 1740, "expiryDate": "31-Jul-2025", "PE": {"strikePrice": 1740, "expiryDate": "31-Jul-2025", "underlying": "BHARTIARTL", "identifier": "OPTSTKBHARTIARTL31-07-2025PE1740.00", "openInterest": 197, "changeinOpenInterest": -1, "pchangeinOpenInterest": -0.5050505050505051, "totalTradedVolume": 36, "impliedVolatility": 0, "lastPrice": 0.4, "change": -0.09999999999999998, "pChange": -19.999999999999996, "totalBuyQuantity": 121600, "totalSellQuantity": 43225, "bidQty": 15675, "bidprice": 0.35, "askQty": 3800, "askPrice": 0.45, "underlyingValue": 2033}}, {"strikePrice": 1760, "expiryDate": "31-Jul-2025", "PE": {"strikePrice": 1760, "expiryDate": "31-Jul-2025", "underlying": "BHARTIARTL", "identifier": "OPTSTKBHARTIARTL31-07-2025PE1760.00", "openInterest": 110, "changeinOpenInterest": 8, "pchangeinOpenInterest": 7.8431372549019605, "totalTradedVolume": 12, "impliedVolatility": 26.42, "lastPrice": 0.5, "change": -0.25, "pChange": -33.33333333333333, "totalBuyQuantity": 161975, "totalSellQuantity": 53675, "bidQty": 475, "bidprice": 0.5, "askQty": 475, "askPrice": 0.6, "underlyingValue": 2033}, "CE": {"strikePrice": 1760, "expiryDate": "31-Jul-2025", "underlying": "BHARTIARTL", "identifier": "OPTSTKBHARTIARTL31-07-2025CE1760.00", "openInterest": 1, "changeinOpenInterest": 0, "pchangeinOpenInterest": 0, "totalTradedVolume": 0, "impliedVolatility": 0, "lastPrice": 0, "change": 0, "pChange": 0, "totalBuyQuantity": 30400, "totalSellQuantity": 10925, "bidQty": 1425, "bidprice": 256.3, "askQty": 1425, "askPrice": 274.95, "underlyingValue": 2033}}, {"strikePrice": 1780, "expiryDate": "31-Jul-2025", "PE": {"strikePrice": 1780, "expiryDate": "31-Jul-2025", "underlying": "BHARTIARTL", "identifier": "OPTSTKBHARTIARTL31-07-2025PE1780.00", "openInterest": 363, "changeinOpenInterest": 0, "pchangeinOpenInterest": 0, "totalTradedVolume": 9, "impliedVolatility": 24.99, "lastPrice": 0.55, "change": -0.25, "pChange": -31.25, "totalBuyQuantity": 169575, "totalSellQuantity": 25650, "bidQty": 475, "bidprice": 0.55, "askQty": 475, "askPrice": 0.7, "underlyingValue": 2033}}, {"strikePrice": 1800, "expiryDate": "31-Jul-2025", "PE": {"strikePrice": 1800, "expiryDate": "31-Jul-2025", "underlying": "BHARTIARTL", "identifier": "OPTSTKBHARTIARTL31-07-2025PE1800.00", "openInterest": 1311, "changeinOpenInterest": -21, "pchangeinOpenInterest": -1.5765765765765767, "totalTradedVolume": 122, "impliedVolatility": 24.51, "lastPrice": 0.8, "change": -0.1499999999999999, "pChange": -15.789473684210517, "totalBuyQuantity": 264100, "totalSellQuantity": 81700, "bidQty": 7125, "bidprice": 0.75, "askQty": 950, "askPrice": 0.8, "underlyingValue": 2033}, "CE": {"strikePrice": 1800, "expiryDate": "31-Jul-2025", "underlying": "BHARTIARTL", "identifier": "OPTSTKBHARTIARTL31-07-2025CE1800.00", "openInterest": 572, "changeinOpenInterest": 0, "pchangeinOpenInterest": 0, "totalTradedVolume": 0, "impliedVolatility": 0, "lastPrice": 0, "change": 0, "pChange": 0, "totalBuyQuantity": 54150, "totalSellQuantity": 60800, "bidQty": 950, "bidprice": 221.5, "askQty": 3325, "askPrice": 230.45, "underlyingValue": 2033}}, {"strikePrice": 1820, "expiryDate": "31-Jul-2025", "PE": {"strikePrice": 1820, "expiryDate": "31-Jul-2025", "underlying": "BHARTIARTL", "identifier": "OPTSTKBHARTIARTL31-07-2025PE1820.00", "openInterest": 725, "changeinOpenInterest": -9, "pchangeinOpenInterest": -1.2261580381471389, "totalTradedVolume": 29, "impliedVolatility": 23.48, "lastPrice": 1, "change": -0.30000000000000004, "pChange": -23.076923076923077, "totalBuyQuantity": 334875, "totalSellQuantity": 63175, "bidQty": 475, "bidprice": 0.95, "askQty": 475, "askPrice": 1.1, "underlyingValue": 2033}, "CE": {"strikePrice": 1820, "expiryDate": "31-Jul-2025", "underlying": "BHARTIARTL", "identifier": "OPTSTKBHARTIARTL31-07-2025CE1820.00", "openInterest": 52, "changeinOpenInterest": 0, "pchangeinOpenInterest": 0, "totalTradedVolume": 0, "impliedVolatility": 0, "lastPrice": 0, "change": 0, "pChange": 0, "totalBuyQuantity": 32300, "totalSellQuantity": 27550, "bidQty": 3325, "bidprice": 197.45, "askQty": 3325, "askPrice": 215.6, "underlyingValue": 2033}}, {"strikePrice": 1840, "expiryDate": "31-Jul-2025", "PE": {"strikePrice": 1840, "expiryDate": "31-Jul-2025", "underlying": "BHARTIARTL", "identifier": "OPTSTKBHARTIARTL31-07-2025PE1840.00", "openInterest": 546, "changeinOpenInterest": -28, "pchangeinOpenInterest": -4.878048780487805, "totalTradedVolume": 105, "impliedVolatility": 23.28, "lastPrice": 1.55, "change": -0.30000000000000004, "pChange": -16.216216216216218, "totalBuyQuantity": 271700, "totalSellQuantity": 61750, "bidQty": 475, "bidprice": 1.4, "askQty": 1425, "askPrice": 1.55, "underlyingValue": 2033}, "CE": {"strikePrice": 1840, "expiryDate": "31-Jul-2025", "underlying": "BHARTIARTL", "identifier": "OPTSTKBHARTIARTL31-07-2025CE1840.00", "openInterest": 179, "changeinOpenInterest": 0, "pchangeinOpenInterest": 0, "totalTradedVolume": 1, "impliedVolatility": 0, "lastPrice": 185, "change": 17.55000000000001, "pChange": 10.480740519558085, "totalBuyQuantity": 35150, "totalSellQuantity": 33250, "bidQty": 475, "bidprice": 184.35, "askQty": 6650, "askPrice": 190.05, "underlyingValue": 2033}}, {"strikePrice": 1860, "expiryDate": "31-Jul-2025", "PE": {"strikePrice": 1860, "expiryDate": "31-Jul-2025", "underlying": "BHARTIARTL", "identifier": "OPTSTKBHARTIARTL31-07-2025PE1860.00", "openInterest": 1220, "changeinOpenInterest": 1, "pchangeinOpenInterest": 0.08203445447087777, "totalTradedVolume": 188, "impliedVolatility": 0, "lastPrice": 2.1, "change": -0.5, "pChange": -19.23076923076923, "totalBuyQuantity": 280725, "totalSellQuantity": 73625, "bidQty": 1425, "bidprice": 1.95, "askQty": 1425, "askPrice": 2.15, "underlyingValue": 2033}, "CE": {"strikePrice": 1860, "expiryDate": "31-Jul-2025", "underlying": "BHARTIARTL", "identifier": "OPTSTKBHARTIARTL31-07-2025CE1860.00", "openInterest": 392, "changeinOpenInterest": -20, "pchangeinOpenInterest": -4.854368932038835, "totalTradedVolume": 25, "impliedVolatility": 0, "lastPrice": 163.45, "change": 0.9499999999999886, "pChange": 0.5846153846153777, "totalBuyQuantity": 40850, "totalSellQuantity": 38475, "bidQty": 475, "bidprice": 165.05, "askQty": 475, "askPrice": 169.2, "underlyingValue": 2033}}, {"strikePrice": 1880, "expiryDate": "31-Jul-2025", "CE": {"strikePrice": 1880, "expiryDate": "31-Jul-2025", "underlying": "BHARTIARTL", "identifier": "OPTSTKBHARTIARTL31-07-2025CE1880.00", "openInterest": 155, "changeinOpenInterest": 0, "pchangeinOpenInterest": 0, "totalTradedVolume": 0, "impliedVolatility": 0, "lastPrice": 0, "change": 0, "pChange": 0, "totalBuyQuantity": 36100, "totalSellQuantity": 36575, "bidQty": 1900, "bidprice": 143.9, "askQty": 950, "askPrice": 152.4, "underlyingValue": 2033}, "PE": {"strikePrice": 1880, "expiryDate": "31-Jul-2025", "underlying": "BHARTIARTL", "identifier": "OPTSTKBHARTIARTL31-07-2025PE1880.00", "openInterest": 622, "changeinOpenInterest": -13, "pchangeinOpenInterest": -2.047244094488189, "totalTradedVolume": 138, "impliedVolatility": 0, "lastPrice": 2.8, "change": -0.7000000000000002, "pChange": -20.000000000000004, "totalBuyQuantity": 282625, "totalSellQuantity": 74575, "bidQty": 475, "bidprice": 2.65, "askQty": 475, "askPrice": 2.9, "underlyingValue": 2033}}, {"strikePrice": 1900, "expiryDate": "31-Jul-2025", "PE": {"strikePrice": 1900, "expiryDate": "31-Jul-2025", "underlying": "BHARTIARTL", "identifier": "OPTSTKBHARTIARTL31-07-2025PE1900.00", "openInterest": 2241, "changeinOpenInterest": -44, "pchangeinOpenInterest": -1.925601750547046, "totalTradedVolume": 710, "impliedVolatility": 21.12, "lastPrice": 3.85, "change": -0.9999999999999996, "pChange": -20.618556701030922, "totalBuyQuantity": 338675, "totalSellQuantity": 123500, "bidQty": 475, "bidprice": 3.85, "askQty": 950, "askPrice": 3.9, "underlyingValue": 2033}, "CE": {"strikePrice": 1900, "expiryDate": "31-Jul-2025", "underlying": "BHARTIARTL", "identifier": "OPTSTKBHARTIARTL31-07-2025CE1900.00", "openInterest": 484, "changeinOpenInterest": -24, "pchangeinOpenInterest": -4.724409448818897, "totalTradedVolume": 89, "impliedVolatility": 0, "lastPrice": 128.55, "change": 2.1500000000000057, "pChange": 1.7009493670886122, "totalBuyQuantity": 38000, "totalSellQuantity": 32300, "bidQty": 475, "bidprice": 127.2, "askQty": 475, "askPrice": 129.85, "underlyingValue": 2033}}, {"strikePrice": 1920, "expiryDate": "31-Jul-2025", "PE": {"strikePrice": 1920, "expiryDate": "31-Jul-2025", "underlying": "BHARTIARTL", "identifier": "OPTSTKBHARTIARTL31-07-2025PE1920.00", "openInterest": 816, "changeinOpenInterest": -37, "pchangeinOpenInterest": -4.337631887456038, "totalTradedVolume": 374, "impliedVolatility": 20.66, "lastPrice": 5.45, "change": -1, "pChange": -15.503875968992247, "totalBuyQuantity": 334875, "totalSellQuantity": 73150, "bidQty": 1425, "bidprice": 5.15, "askQty": 950, "askPrice": 5.35, "underlyingValue": 2033}, "CE": {"strikePrice": 1920, "expiryDate": "31-Jul-2025", "underlying": "BHARTIARTL", "identifier": "OPTSTKBHARTIARTL31-07-2025CE1920.00", "openInterest": 327, "changeinOpenInterest": -1, "pchangeinOpenInterest": -0.3048780487804878, "totalTradedVolume": 3, "impliedVolatility": 0, "lastPrice": 97.95, "change": -10.950000000000003, "pChange": -10.055096418732784, "totalBuyQuantity": 43225, "totalSellQuantity": 43225, "bidQty": 475, "bidprice": 108.55, "askQty": 950, "askPrice": 112.25, "underlyingValue": 2033}}, {"strikePrice": 1940, "expiryDate": "31-Jul-2025", "CE": {"strikePrice": 1940, "expiryDate": "31-Jul-2025", "underlying": "BHARTIARTL", "identifier": "OPTSTKBHARTIARTL31-07-2025CE1940.00", "openInterest": 393, "changeinOpenInterest": -2, "pchangeinOpenInterest": -0.5063291139240507, "totalTradedVolume": 9, "impliedVolatility": 0, "lastPrice": 84.9, "change": -7.25, "pChange": -7.867607162235485, "totalBuyQuantity": 31825, "totalSellQuantity": 34675, "bidQty": 950, "bidprice": 90.15, "askQty": 950, "askPrice": 93.05, "underlyingValue": 2033}, "PE": {"strikePrice": 1940, "expiryDate": "31-Jul-2025", "underlying": "BHARTIARTL", "identifier": "OPTSTKBHARTIARTL31-07-2025PE1940.00", "openInterest": 1145, "changeinOpenInterest": -211, "pchangeinOpenInterest": -15.56047197640118, "totalTradedVolume": 1139, "impliedVolatility": 19.91, "lastPrice": 7.3, "change": -1.4500000000000002, "pChange": -16.571428571428573, "totalBuyQuantity": 308275, "totalSellQuantity": 76950, "bidQty": 950, "bidprice": 7.2, "askQty": 950, "askPrice": 7.4, "underlyingValue": 2033}}, {"strikePrice": 1960, "expiryDate": "31-Jul-2025", "CE": {"strikePrice": 1960, "expiryDate": "31-Jul-2025", "underlying": "BHARTIARTL", "identifier": "OPTSTKBHARTIARTL31-07-2025CE1960.00", "openInterest": 479, "changeinOpenInterest": -12, "pchangeinOpenInterest": -2.443991853360489, "totalTradedVolume": 91, "impliedVolatility": 0, "lastPrice": 74.3, "change": 0.3999999999999915, "pChange": 0.5412719891745487, "totalBuyQuantity": 39425, "totalSellQuantity": 39425, "bidQty": 1425, "bidprice": 75, "askQty": 950, "askPrice": 76, "underlyingValue": 2033}, "PE": {"strikePrice": 1960, "expiryDate": "31-Jul-2025", "underlying": "BHARTIARTL", "identifier": "OPTSTKBHARTIARTL31-07-2025PE1960.00", "openInterest": 1133, "changeinOpenInterest": -14, "pchangeinOpenInterest": -1.2205754141238012, "totalTradedVolume": 989, "impliedVolatility": 19.67, "lastPrice": 10.35, "change": -1.75, "pChange": -14.462809917355374, "totalBuyQuantity": 285950, "totalSellQuantity": 84550, "bidQty": 475, "bidprice": 10.15, "askQty": 1425, "askPrice": 10.35, "underlyingValue": 2033}}, {"strikePrice": 1980, "expiryDate": "31-Jul-2025", "CE": {"strikePrice": 1980, "expiryDate": "31-Jul-2025", "underlying": "BHARTIARTL", "identifier": "OPTSTKBHARTIARTL31-07-2025CE1980.00", "openInterest": 465, "changeinOpenInterest": -6, "pchangeinOpenInterest": -1.2738853503184713, "totalTradedVolume": 351, "impliedVolatility": 0, "lastPrice": 59.45, "change": 0.8500000000000014, "pChange": 1.4505119453924937, "totalBuyQuantity": 34200, "totalSellQuantity": 35150, "bidQty": 475, "bidprice": 57.75, "askQty": 475, "askPrice": 60.25, "underlyingValue": 2033}, "PE": {"strikePrice": 1980, "expiryDate": "31-Jul-2025", "underlying": "BHARTIARTL", "identifier": "OPTSTKBHARTIARTL31-07-2025PE1980.00", "openInterest": 952, "changeinOpenInterest": 35, "pchangeinOpenInterest": 3.816793893129771, "totalTradedVolume": 1207, "impliedVolatility": 19.25, "lastPrice": 14.35, "change": -2.4000000000000004, "pChange": -14.328358208955224, "totalBuyQuantity": 285475, "totalSellQuantity": 102125, "bidQty": 950, "bidprice": 14.35, "askQty": 475, "askPrice": 14.55, "underlyingValue": 2033}}, {"strikePrice": 2000, "expiryDate": "31-Jul-2025", "CE": {"strikePrice": 2000, "expiryDate": "31-Jul-2025", "underlying": "BHARTIARTL", "identifier": "OPTSTKBHARTIARTL31-07-2025CE2000.00", "openInterest": 2502, "changeinOpenInterest": -97, "pchangeinOpenInterest": -3.7322046941131206, "totalTradedVolume": 2477, "impliedVolatility": 0, "lastPrice": 45.25, "change": 0.3500000000000014, "pChange": 0.7795100222717181, "totalBuyQuantity": 167200, "totalSellQuantity": 104500, "bidQty": 950, "bidprice": 44.75, "askQty": 475, "askPrice": 45.25, "underlyingValue": 2033}, "PE": {"strikePrice": 2000, "expiryDate": "31-Jul-2025", "underlying": "BHARTIARTL", "identifier": "OPTSTKBHARTIARTL31-07-2025PE2000.00", "openInterest": 2126, "changeinOpenInterest": 89, "pchangeinOpenInterest": 4.369170348551791, "totalTradedVolume": 2839, "impliedVolatility": 19.17, "lastPrice": 20.25, "change": -2.3999999999999986, "pChange": -10.596026490066219, "totalBuyQuantity": 227050, "totalSellQuantity": 152000, "bidQty": 950, "bidprice": 20.2, "askQty": 475, "askPrice": 20.4, "underlyingValue": 2033}}, {"strikePrice": 2020, "expiryDate": "31-Jul-2025", "PE": {"strikePrice": 2020, "expiryDate": "31-Jul-2025", "underlying": "BHARTIARTL", "identifier": "OPTSTKBHARTIARTL31-07-2025PE2020.00", "openInterest": 1267, "changeinOpenInterest": 90, "pchangeinOpenInterest": 7.646559048428207, "totalTradedVolume": 1630, "impliedVolatility": 19.51, "lastPrice": 28.1, "change": -2.549999999999997, "pChange": -8.319738988580742, "totalBuyQuantity": 244625, "totalSellQuantity": 101175, "bidQty": 950, "bidprice": 27.7, "askQty": 475, "askPrice": 28.4, "underlyingValue": 2033}, "CE": {"strikePrice": 2020, "expiryDate": "31-Jul-2025", "underlying": "BHARTIARTL", "identifier": "OPTSTKBHARTIARTL31-07-2025CE2020.00", "openInterest": 1889, "changeinOpenInterest": -3, "pchangeinOpenInterest": -0.15856236786469344, "totalTradedVolume": 3271, "impliedVolatility": 0, "lastPrice": 33.25, "change": 0.29999999999999716, "pChange": 0.9104704097116757, "totalBuyQuantity": 284525, "totalSellQuantity": 148675, "bidQty": 950, "bidprice": 32.75, "askQty": 475, "askPrice": 33.25, "underlyingValue": 2033}}, {"strikePrice": 2040, "expiryDate": "31-Jul-2025", "PE": {"strikePrice": 2040, "expiryDate": "31-Jul-2025", "underlying": "BHARTIARTL", "identifier": "OPTSTKBHARTIARTL31-07-2025PE2040.00", "openInterest": 997, "changeinOpenInterest": 4, "pchangeinOpenInterest": 0.4028197381671702, "totalTradedVolume": 1338, "impliedVolatility": 19.89, "lastPrice": 37.6, "change": -2.8999999999999986, "pChange": -7.16049382716049, "totalBuyQuantity": 90725, "totalSellQuantity": 59375, "bidQty": 475, "bidprice": 37.5, "askQty": 475, "askPrice": 37.95, "underlyingValue": 2033}, "CE": {"strikePrice": 2040, "expiryDate": "31-Jul-2025", "underlying": "BHARTIARTL", "identifier": "OPTSTKBHARTIARTL31-07-2025CE2040.00", "openInterest": 7003, "changeinOpenInterest": 42, "pchangeinOpenInterest": 0.603361585979026, "totalTradedVolume": 5605, "impliedVolatility": 0, "lastPrice": 22.6, "change": -0.09999999999999787, "pChange": -0.4405286343612241, "totalBuyQuantity": 362425, "totalSellQuantity": 228000, "bidQty": 475, "bidprice": 22.7, "askQty": 11400, "askPrice": 22.9, "underlyingValue": 2033}}, {"strikePrice": 2060, "expiryDate": "31-Jul-2025", "PE": {"strikePrice": 2060, "expiryDate": "31-Jul-2025", "underlying": "BHARTIARTL", "identifier": "OPTSTKBHARTIARTL31-07-2025PE2060.00", "openInterest": 334, "changeinOpenInterest": 16, "pchangeinOpenInterest": 5.031446540880503, "totalTradedVolume": 166, "impliedVolatility": 21.1, "lastPrice": 50.5, "change": -2.6000000000000014, "pChange": -4.89642184557439, "totalBuyQuantity": 19950, "totalSellQuantity": 48925, "bidQty": 475, "bidprice": 49.75, "askQty": 950, "askPrice": 50.45, "underlyingValue": 2033}, "CE": {"strikePrice": 2060, "expiryDate": "31-Jul-2025", "underlying": "BHARTIARTL", "identifier": "OPTSTKBHARTIARTL31-07-2025CE2060.00", "openInterest": 4402, "changeinOpenInterest": 76, "pchangeinOpenInterest": 1.756819232547388, "totalTradedVolume": 3043, "impliedVolatility": 10.6, "lastPrice": 15.45, "change": 0.09999999999999964, "pChange": 0.6514657980456003, "totalBuyQuantity": 339625, "totalSellQuantity": 169100, "bidQty": 475, "bidprice": 15.3, "askQty": 475, "askPrice": 15.45, "underlyingValue": 2033}}, {"strikePrice": 2080, "expiryDate": "31-Jul-2025", "PE": {"strikePrice": 2080, "expiryDate": "31-Jul-2025", "underlying": "BHARTIARTL", "identifier": "OPTSTKBHARTIARTL31-07-2025PE2080.00", "openInterest": 96, "changeinOpenInterest": -9, "pchangeinOpenInterest": -8.571428571428571, "totalTradedVolume": 73, "impliedVolatility": 22.95, "lastPrice": 66, "change": -2.299999999999997, "pChange": -3.3674963396778876, "totalBuyQuantity": 41325, "totalSellQuantity": 45125, "bidQty": 3325, "bidprice": 58.1, "askQty": 950, "askPrice": 66, "underlyingValue": 2033}, "CE": {"strikePrice": 2080, "expiryDate": "31-Jul-2025", "underlying": "BHARTIARTL", "identifier": "OPTSTKBHARTIARTL31-07-2025CE2080.00", "openInterest": 2165, "changeinOpenInterest": 20, "pchangeinOpenInterest": 0.9324009324009324, "totalTradedVolume": 1844, "impliedVolatility": 11.43, "lastPrice": 10.15, "change": -0.09999999999999964, "pChange": -0.9756097560975575, "totalBuyQuantity": 334400, "totalSellQuantity": 92625, "bidQty": 475, "bidprice": 10.15, "askQty": 475, "askPrice": 10.3, "underlyingValue": 2033}}, {"strikePrice": 2100, "expiryDate": "31-Jul-2025", "PE": {"strikePrice": 2100, "expiryDate": "31-Jul-2025", "underlying": "BHARTIARTL", "identifier": "OPTSTKBHARTIARTL31-07-2025PE2100.00", "openInterest": 438, "changeinOpenInterest": -5, "pchangeinOpenInterest": -1.1286681715575622, "totalTradedVolume": 97, "impliedVolatility": 24.86, "lastPrice": 82.6, "change": -1.4000000000000057, "pChange": -1.6666666666666736, "totalBuyQuantity": 45600, "totalSellQuantity": 57950, "bidQty": 475, "bidprice": 81.05, "askQty": 950, "askPrice": 82.6, "underlyingValue": 2033}, "CE": {"strikePrice": 2100, "expiryDate": "31-Jul-2025", "underlying": "BHARTIARTL", "identifier": "OPTSTKBHARTIARTL31-07-2025CE2100.00", "openInterest": 3977, "changeinOpenInterest": -274, "pchangeinOpenInterest": -6.445542225358739, "totalTradedVolume": 2660, "impliedVolatility": 12.27, "lastPrice": 7, "change": -0.2999999999999998, "pChange": -4.109589041095888, "totalBuyQuantity": 405175, "totalSellQuantity": 267425, "bidQty": 950, "bidprice": 6.9, "askQty": 2850, "askPrice": 7.1, "underlyingValue": 2033}}, {"strikePrice": 2120, "expiryDate": "31-Jul-2025", "PE": {"strikePrice": 2120, "expiryDate": "31-Jul-2025", "underlying": "BHARTIARTL", "identifier": "OPTSTKBHARTIARTL31-07-2025PE2120.00", "openInterest": 39, "changeinOpenInterest": 0, "pchangeinOpenInterest": 0, "totalTradedVolume": 0, "impliedVolatility": 0, "lastPrice": 0, "change": 0, "pChange": 0, "totalBuyQuantity": 35150, "totalSellQuantity": 37050, "bidQty": 4750, "bidprice": 94.65, "askQty": 1900, "askPrice": 103.35, "underlyingValue": 2033}, "CE": {"strikePrice": 2120, "expiryDate": "31-Jul-2025", "underlying": "BHARTIARTL", "identifier": "OPTSTKBHARTIARTL31-07-2025CE2120.00", "openInterest": 777, "changeinOpenInterest": -36, "pchangeinOpenInterest": -4.428044280442805, "totalTradedVolume": 662, "impliedVolatility": 13.07, "lastPrice": 4.8, "change": -0.04999999999999982, "pChange": -1.0309278350515427, "totalBuyQuantity": 402325, "totalSellQuantity": 87875, "bidQty": 1425, "bidprice": 4.65, "askQty": 1425, "askPrice": 4.8, "underlyingValue": 2033}}, {"strikePrice": 2140, "expiryDate": "31-Jul-2025", "PE": {"strikePrice": 2140, "expiryDate": "31-Jul-2025", "underlying": "BHARTIARTL", "identifier": "OPTSTKBHARTIARTL31-07-2025PE2140.00", "openInterest": 0, "changeinOpenInterest": 0, "pchangeinOpenInterest": 0, "totalTradedVolume": 0, "impliedVolatility": 0, "lastPrice": 0, "change": 0, "pChange": 0, "totalBuyQuantity": 28025, "totalSellQuantity": 32775, "bidQty": 1425, "bidprice": 109.95, "askQty": 2375, "askPrice": 123.9, "underlyingValue": 2033}, "CE": {"strikePrice": 2140, "expiryDate": "31-Jul-2025", "underlying": "BHARTIARTL", "identifier": "OPTSTKBHARTIARTL31-07-2025CE2140.00", "openInterest": 395, "changeinOpenInterest": 43, "pchangeinOpenInterest": 12.215909090909092, "totalTradedVolume": 291, "impliedVolatility": 13.81, "lastPrice": 3.3, "change": -0.15000000000000036, "pChange": -4.347826086956532, "totalBuyQuantity": 400900, "totalSellQuantity": 77425, "bidQty": 475, "bidprice": 3.15, "askQty": 1425, "askPrice": 3.35, "underlyingValue": 2033}}, {"strikePrice": 2160, "expiryDate": "31-Jul-2025", "PE": {"strikePrice": 2160, "expiryDate": "31-Jul-2025", "underlying": "BHARTIARTL", "identifier": "OPTSTKBHARTIARTL31-07-2025PE2160.00", "openInterest": 6, "changeinOpenInterest": 0, "pchangeinOpenInterest": 0, "totalTradedVolume": 0, "impliedVolatility": 0, "lastPrice": 0, "change": 0, "pChange": 0, "totalBuyQuantity": 26125, "totalSellQuantity": 31825, "bidQty": 1900, "bidprice": 125.4, "askQty": 950, "askPrice": 139.95, "underlyingValue": 2033}, "CE": {"strikePrice": 2160, "expiryDate": "31-Jul-2025", "underlying": "BHARTIARTL", "identifier": "OPTSTKBHARTIARTL31-07-2025CE2160.00", "openInterest": 528, "changeinOpenInterest": -17, "pchangeinOpenInterest": -3.1192660550458715, "totalTradedVolume": 152, "impliedVolatility": 0, "lastPrice": 2.4, "change": 0, "pChange": 0, "totalBuyQuantity": 365275, "totalSellQuantity": 59850, "bidQty": 475, "bidprice": 2.2, "askQty": 475, "askPrice": 2.35, "underlyingValue": 2033}}, {"strikePrice": 2180, "expiryDate": "31-Jul-2025", "CE": {"strikePrice": 2180, "expiryDate": "31-Jul-2025", "underlying": "BHARTIARTL", "identifier": "OPTSTKBHARTIARTL31-07-2025CE2180.00", "openInterest": 225, "changeinOpenInterest": -27, "pchangeinOpenInterest": -10.714285714285714, "totalTradedVolume": 92, "impliedVolatility": 0, "lastPrice": 1.65, "change": -0.20000000000000018, "pChange": -10.81081081081082, "totalBuyQuantity": 329650, "totalSellQuantity": 43700, "bidQty": 950, "bidprice": 1.6, "askQty": 475, "askPrice": 1.75, "underlyingValue": 2033}, "PE": {"strikePrice": 2180, "expiryDate": "31-Jul-2025", "underlying": "BHARTIARTL", "identifier": "OPTSTKBHARTIARTL31-07-2025PE2180.00", "openInterest": 0, "changeinOpenInterest": 0, "pchangeinOpenInterest": 0, "totalTradedVolume": 0, "impliedVolatility": 0, "lastPrice": 0, "change": 0, "pChange": 0, "totalBuyQuantity": 24225, "totalSellQuantity": 31350, "bidQty": 1900, "bidprice": 144.85, "askQty": 2375, "askPrice": 162.45, "underlyingValue": 2033}}, {"strikePrice": 2200, "expiryDate": "31-Jul-2025", "PE": {"strikePrice": 2200, "expiryDate": "31-Jul-2025", "underlying": "BHARTIARTL", "identifier": "OPTSTKBHARTIARTL31-07-2025PE2200.00", "openInterest": 11, "changeinOpenInterest": 1, "pchangeinOpenInterest": 10, "totalTradedVolume": 3, "impliedVolatility": 0, "lastPrice": 182, "change": -7, "pChange": -3.7037037037037033, "totalBuyQuantity": 32300, "totalSellQuantity": 39900, "bidQty": 950, "bidprice": 172.65, "askQty": 950, "askPrice": 177, "underlyingValue": 2033}, "CE": {"strikePrice": 2200, "expiryDate": "31-Jul-2025", "underlying": "BHARTIARTL", "identifier": "OPTSTKBHARTIARTL31-07-2025CE2200.00", "openInterest": 2051, "changeinOpenInterest": 11, "pchangeinOpenInterest": 0.5392156862745098, "totalTradedVolume": 292, "impliedVolatility": 16.39, "lastPrice": 1.4, "change": 0, "pChange": 0, "totalBuyQuantity": 441275, "totalSellQuantity": 99750, "bidQty": 1425, "bidprice": 1.2, "askQty": 1425, "askPrice": 1.4, "underlyingValue": 2033}}, {"strikePrice": 2220, "expiryDate": "31-Jul-2025", "PE": {"strikePrice": 2220, "expiryDate": "31-Jul-2025", "underlying": "BHARTIARTL", "identifier": "OPTSTKBHARTIARTL31-07-2025PE2220.00", "openInterest": 0, "changeinOpenInterest": 0, "pchangeinOpenInterest": 0, "totalTradedVolume": 0, "impliedVolatility": 0, "lastPrice": 0, "change": 0, "pChange": 0, "totalBuyQuantity": 24700, "totalSellQuantity": 30400, "bidQty": 1425, "bidprice": 184.15, "askQty": 1425, "askPrice": 202.85, "underlyingValue": 2033}, "CE": {"strikePrice": 2220, "expiryDate": "31-Jul-2025", "underlying": "BHARTIARTL", "identifier": "OPTSTKBHARTIARTL31-07-2025CE2220.00", "openInterest": 55, "changeinOpenInterest": -6, "pchangeinOpenInterest": -9.836065573770492, "totalTradedVolume": 15, "impliedVolatility": 16.81, "lastPrice": 0.9, "change": -0.2499999999999999, "pChange": -21.7391304347826, "totalBuyQuantity": 109725, "totalSellQuantity": 76475, "bidQty": 950, "bidprice": 0.85, "askQty": 1900, "askPrice": 1, "underlyingValue": 2033}}, {"strikePrice": 2240, "expiryDate": "31-Jul-2025", "CE": {"strikePrice": 2240, "expiryDate": "31-Jul-2025", "underlying": "BHARTIARTL", "identifier": "OPTSTKBHARTIARTL31-07-2025CE2240.00", "openInterest": 414, "changeinOpenInterest": -1, "pchangeinOpenInterest": -0.24096385542168675, "totalTradedVolume": 30, "impliedVolatility": 17.63, "lastPrice": 0.7, "change": -0.10000000000000009, "pChange": -12.50000000000001, "totalBuyQuantity": 235125, "totalSellQuantity": 81225, "bidQty": 950, "bidprice": 0.65, "askQty": 2850, "askPrice": 0.8, "underlyingValue": 2033}, "PE": {"strikePrice": 2240, "expiryDate": "31-Jul-2025", "underlying": "BHARTIARTL", "identifier": "OPTSTKBHARTIARTL31-07-2025PE2240.00", "openInterest": 0, "changeinOpenInterest": 0, "pchangeinOpenInterest": 0, "totalTradedVolume": 0, "impliedVolatility": 0, "lastPrice": 0, "change": 0, "pChange": 0, "totalBuyQuantity": 23275, "totalSellQuantity": 30400, "bidQty": 1425, "bidprice": 203.75, "askQty": 1425, "askPrice": 222.4, "underlyingValue": 2033}}, {"strikePrice": 2280, "expiryDate": "31-Jul-2025", "CE": {"strikePrice": 2280, "expiryDate": "31-Jul-2025", "underlying": "BHARTIARTL", "identifier": "OPTSTKBHARTIARTL31-07-2025CE2280.00", "openInterest": 252, "changeinOpenInterest": 1, "pchangeinOpenInterest": 0.398406374501992, "totalTradedVolume": 7, "impliedVolatility": 18.96, "lastPrice": 0.4, "change": -0.15000000000000002, "pChange": -27.272727272727277, "totalBuyQuantity": 177650, "totalSellQuantity": 69825, "bidQty": 950, "bidprice": 0.45, "askQty": 2850, "askPrice": 0.55, "underlyingValue": 2033}, "PE": {"strikePrice": 2280, "expiryDate": "31-Jul-2025", "underlying": "BHARTIARTL", "identifier": "OPTSTKBHARTIARTL31-07-2025PE2280.00", "openInterest": 0, "changeinOpenInterest": 0, "pchangeinOpenInterest": 0, "totalTradedVolume": 0, "impliedVolatility": 0, "lastPrice": 0, "change": 0, "pChange": 0, "totalBuyQuantity": 23275, "totalSellQuantity": 30400, "bidQty": 1425, "bidprice": 241.25, "askQty": 1425, "askPrice": 263.25, "underlyingValue": 2033}}, {"strikePrice": 2320, "expiryDate": "31-Jul-2025", "CE": {"strikePrice": 2320, "expiryDate": "31-Jul-2025", "underlying": "BHARTIARTL", "identifier": "OPTSTKBHARTIARTL31-07-2025CE2320.00", "openInterest": 89, "changeinOpenInterest": 2, "pchangeinOpenInterest": 2.2988505747126435, "totalTradedVolume": 14, "impliedVolatility": 21.56, "lastPrice": 0.4, "change": 0, "pChange": 0, "totalBuyQuantity": 170525, "totalSellQuantity": 56050, "bidQty": 950, "bidprice": 0.35, "askQty": 5700, "askPrice": 0.6, "underlyingValue": 2033}, "PE": {"strikePrice": 2320, "expiryDate": "31-Jul-2025", "underlying": "BHARTIARTL", "identifier": "OPTSTKBHARTIARTL31-07-2025PE2320.00", "openInterest": 0, "changeinOpenInterest": 0, "pchangeinOpenInterest": 0, "totalTradedVolume": 0, "impliedVolatility": 0, "lastPrice": 0, "change": 0, "pChange": 0, "totalBuyQuantity": 23275, "totalSellQuantity": 30400, "bidQty": 1425, "bidprice": 282.95, "askQty": 1425, "askPrice": 301.6, "underlyingValue": 2033}}], "CE": {"totOI": 30867, "totVol": 21024}, "PE": {"totOI": 17345, "totVol": 11245}}}